Workbook

Sheet Start Here
A1: B2B Growth Content Intelligence: Outlier Research Workbook
A2: Built 17 Oct 2026 from Eden (LinkedIn, X, Instagram index) and vidIQ (Instagram Reels outliers). Accounts with 5k-100k followers, last 6-12 months, English + Hindi/Hinglish.
A4: How to use this workbook
A5: 1. ICP & Positioning | B5: Read first. Sharpened ICP, the assumptions I disagree with, and the reasoning. Decide before you write anything.
A6: 2. Strategy & Funnel | B6: Pillars, platform roles, funnel math, cadence and KPIs, grounded in the outlier data.
A7: 3. Master Database | B7: Every relevant post (ICP fit ≥3/10). Filter by Platform, Cluster, Signal, Hook Archetype, Offer. Sort by Priority Score. Use the Status column to track what you have reverse-engineered.
A8: 4. Top 30 Teardowns | B8: Hand-written analysis of the 30 most useful posts: why each worked and the exact adaptation for your offers.
A9: 5. Hidden Gems | B9: Accounts ≤30k followers whose post did ≥5x their own baseline. Idea beat audience, which is the most transferable signal for a new account.
A10: 6. Reels Teardown | B10: vidIQ Instagram outliers with 0-3s hook (visual, text, audio), format template, pacing, editing effort.
A11: 7. Hook Library | B11: Hook archetypes ranked by performance per platform, with fill-in templates for your niche.
A12: 8. Creator Watchlist | B12: Creators to study and engage with (comment-to-pipeline). Ranked by repeat outlier performance.
A13: 9. Cluster x Platform | B13: Live COUNTIFS/AVERAGEIFS pivot on the Master Database. Shows where each topic over-performs.
A14: 10. 30-Day Calendar | B14: 52 ready-to-write slots across LinkedIn, X and IG, each linked to a reference post. Change the start date (yellow cell) to re-date it.
A15: 11. India & Hindi | B15: What the Hindi/Hinglish data says, and why it changes your India plan.
A16: 12. Carousel Formula | B16: Design recipe from Eden study of top B2B client-acquisition carousels.
... A18: 14. Methodology | B18: Sources, queries, filters, definitions, caveats. Read before quoting any number.
A20: Signal definitions
A21: Outlier score | B21: Post performance ÷ that creator's own median (Eden: engagement-based; vidIQ: views ÷ median views). 10x = 10 times their normal post.
A22: Breakout | B22: Outlier ≥10x.
A23: Hidden Gem | B23: Creator ≤30k followers AND outlier ≥5x. Highest priority label when multiple apply.
A24: Viral | B24: ≥500k views, or ≥1k likes on LinkedIn, or ≥2k likes on X (absolute reach).
A25: Outlier | B25: 2-10x. Above baseline, not a breakout.
A26: ICP Fit (1-10) | B26: Model-assigned: topic keyword match to your 9 clusters, minus penalties for off-niche, AI-tool hype, aspirant/side-hustle audiences, and accounts outside 5k-100k. Directional, not gospel.
A28: Priority Score weights (editable inputs)
A29: Weight: ICP Fit | B29: 0.5
A30: Weight: Outlier (capped 50x, ÷5) | B30: 0.3
A31: Bonus: ≤30k followers | B31: 2
A32: Bonus: 30-60k followers | B32: 1
A33: Priority = W_fit × Fit + W_out × MIN(Outlier,50)/5 + small-account bonus. Blue/yellow cells are inputs: change them and every Priority Score in the Master Database recalculates.

Sheet ICP & Positioning
A1: ICP & Positioning: sharpened, with the assumptions I disagree with
A3: Assumptions I disagree with (read these first)
A4: #1 "Boutique firms, consultants, fractional execs" AND "10-50 employees" contradict each other | B4: Fractional executives and most independent consultants are 1-5 people, not 10-50. These are two different buyers with different budgets. A 1-3 person fractional practice ($300k-$1.5M revenue) cannot sustain a $6-10k/mo DFY retainer. A 25-person consultancy ($4-6M revenue) can. Pick the firm as the buyer. Treat solo fractionals as a referral channel, not a client.
A5: #2 "10-50 employees = has money" is only half true | B5: Professional-services revenue per employee is roughly $150-250k, so 10-50 staff is roughly $1.5M-$12M revenue. B2B firms spend about 3-8% of revenue on marketing. At $1.5M that is $45-120k/yr in total, so your retainer would eat the entire budget. At $4M it is $120-320k/yr, where a $90-120k/yr engagement fits. Real floor: about $3M revenue / 20+ staff. Qualify on revenue and founder-sourced-deal %, not headcount.
A6: #3 Two offers × two markets × three platforms × two languages is four businesses, not one | B6: One personal brand cannot credibly speak Hinglish cohort-pricing on Instagram and $10k/mo DFY on LinkedIn without diluting both. The data shows the winners in this research are mono-positioned (e.g. @nickavaria = agency numbers, @theroborourke = service-business sales). Fix: one system, two delivery modes (below).
A7: #4 Hindi-first content will not reach your Indian ICP | B7: I ran 5 dedicated Hindi/Hinglish pulls. At 5k-100k followers, Hindi business content is dominated by "earn in dollars", side hustles, numerology, retail/MSME tips and Raj Shamani clips (see "India & Hindi"). Almost nothing targets 10-50 person B2B service owners. Those owners read English on LinkedIn. Hindi is whitespace, but whitespace here mostly signals low buyer density, not an opportunity.
A8: #5 Virality is the wrong success metric for a content + warm-outbound offer | B8: For a firm selling $90k+/yr engagements, a post with 400 impressions that 6 target founders read beats one with 400k impressions from aspirants. Content's job is to (a) lift outbound reply rate, (b) give prospects proof when they check your profile, and (c) surface warm signals (who engages) to feed outbound. Use outliers to learn hooks and formats, not to chase reach.
A10: The reframe: one system, two delivery modes
A11: Core system (the thing you are known for) | B11: "Authority-to-Pipeline": founder-led content + signal-based warm outbound + a simple pipeline operating rhythm. Turns referral-dependent B2B firms into predictable new-logo machines.
A12: Delivery mode A: DFY (international, primary revenue) | B12: Done-for-you install + run for 10-50 person boutique B2B firms in US/UK/AU/CA/EU-English. $15-25k setup + $6-10k/mo, 6-month minimum. Target: 3-5 clients = $25-50k MRR.
A13: Delivery mode B: Cohort (India, cash flow + case studies) | B13: 6-8 week implementation cohort for Indian B2B service firms, prioritising EXPORT-ORIENTED firms (IT services, dev shops, B2B agencies, KPO/analytics) that want US/UK/ME clients. Same system, taught. ₹1-2.5L per firm (founder + 1 operator). 12-20 firms per cohort.
A14: Why this is sharper | B14: "International client hunting" stops being a separate topic and becomes the bridge. You teach Indian firms to win international clients using the exact system you run for international firms. Every DFY result becomes cohort curriculum; every cohort win becomes DFY social proof ("installed in 40+ firms"). One content engine feeds both.
A16: ICP A: Primary (DFY, international)
A17: Firmographics | B17: B2B professional-services firms, 15-50 staff, $3-12M revenue. US, UK, Canada, Australia, Netherlands/Nordics (English-fluent). Founder-led, not PE-owned.
A18: Sub-verticals (rank 1 to 5) | B18: 1) Boutique management/ops/RevOps consultancies 2) Specialist B2B agencies (demand gen, ABM, dev shops) 3) IT/cyber/compliance services 4) Advisory (M&A, fractional-exec collectives, finance) 5) Engineering/technical consultancies. Avoid: legal/medical (posting constraints), pure B2C agencies.
A19: Buyer | B19: Founder / Managing Partner / CEO. Still the #1 rainmaker. Influencer: Head of Growth or Ops if one exists.
A20: Trigger events (use as outbound signals) | B20: • >50% of new revenue from referrals or founder network • Lost or about to lose a top-3 client (concentration risk) • Hired a salesperson who failed in <9 months • Founder starts posting on LinkedIn inconsistently • Raised prices or launched a new service line • Hiring for "Business Development" or "Marketing Manager" • Just crossed or stalled at $3M / $5M / $10M
A21: Painful status quo (their words) | B21: "Pipeline is feast or famine." "Everything still comes through me." "We're the best-kept secret in our niche." "We tried an agency, got junk leads." "I don't have time to post."
A22: Expensive problem (quantified) | B22: A 25-person firm at $5M with 30% annual client churn must replace about $1.5M/yr of revenue. If the founder closes 70% of deals, that founder's time IS the growth ceiling. One extra $150k/yr client = 1.25x to 2x a $90-120k engagement. The ROI story is new logos, not leads.
A23: Disqualifiers | B23: <$2M revenue; no case studies/clients willing to be named; founder unwilling to be the face (content is founder-led); expects leads in 30 days; >100 staff with in-house marketing.
A25: ICP B: Secondary (India cohort)
A26: Firmographics | B26: Indian B2B service firms, 10-50 staff, ₹5-60 Cr revenue. Priority: firms selling or wanting to sell to international clients (IT services, SaaS dev, design/marketing agencies, data/analytics, KPO). Secondary: domestic B2B services.
A27: Core pains | B27: Dependent on Upwork/Clutch/referrals; competing on price; founder does all sales; no outbound system; LinkedIn profiles that read like CVs; can't articulate an expensive problem (see post: India-based design agency, 40x outlier).
A28: Language/platform reality | B28: English on LinkedIn (where they buy). Hinglish on IG reels for warmth and reach. Hindi only for selective clips. Do not build a Hindi-first channel.
A29: Offer and price logic | B29: Cohort ₹1-2.5L/firm. Outcome-based: "Installed: ICP + offer + 4 profiles + 30 posts + 2 outbound sequences + pipeline cadence in 6 weeks". Optional done-with-you upgrade ₹50-75k/mo.
A31: ICP C: Channel partners (not clients)
A32: Fractional execs & solo consultants | B32: 1-5 people, $300k-$1.5M. They sit inside your ICP A firms. Content for them builds referrals. Offer: referral fee (10-15% of year 1) or white-label. Data: fractional-exec content had the lowest median outlier (7.4x), so do not make them a content pillar; treat them as a relationship play.
A34: Positioning statement (draft)
A35: For founder-led B2B firms with 15-50 people who are stuck relying on referrals, I install an Authority-to-Pipeline system (founder content + signal-based warm outbound + a weekly pipeline rhythm) that produces 8-15 qualified conversations a month without the founder writing every post or sending every DM. Unlike lead-gen agencies, we build on the founder's authority and warm signals, so meetings come pre-trusted.
A37: Profile one-liners (test 2 for 30 days each)
A38: A (outcome) | B38: I help 15-50 person B2B firms get off referral dependency: founder-led content + warm outbound that books 8-15 qualified calls/month.
A39: B (mechanism) | B39: Authority-to-Pipeline for boutique consultancies & agencies | Content that warms. Outbound that converts. | Installed in 6 weeks.

Sheet Strategy & Funnel
A1: Content Strategy & Funnel
A2: Numbers marked [data] come from this research (ICP-fit ≥4, n=303, anomalous baselines excluded; all multiples quoted here are MEDIANS, while the Hook Library and Cluster sheets show capped AVERAGES, so the two differ). Numbers marked [assumption] are planning inputs; replace them with your own as you collect data.
A4: What the data says (and what it does not)
A5: Topic heat [data] | B5: Median outlier by cluster: High-Ticket Sales 52x (n=29) > Freelancing & International Clients 46x (n=11, aspirant-heavy) > Business Growth & Scale 24x (n=63) > Agency Growth 24x (n=19) > Outbound 23x (n=29) > Marketing Strategy 20x (n=95) > Content Marketing 16x (n=26) > Client Acquisition 12x (n=15) > Consulting/Fractional 7x (n=16).
A6: Implication | B6: Lead with SALES and PIPELINE ECONOMICS, not "content strategy". "How to do content" is crowded and under-performs (16x). Talk about content only as the warm layer of the pipeline system.
A7: Account size [data] | B7: Median outlier by follower band: 10-20k = 44x, 20-30k = 32x, 5-10k = 20x, 30-50k = 19x, 50-100k = 11x. Small accounts break out more often relative to their baseline. The bar to "win" is idea quality, not audience. (Caveat: smaller accounts have lower baselines, so multiples inflate.)
A8: Hooks on LinkedIn [data] | B8: Contrarian/Myth-Bust 27x > Objection/Quote 19x > Result-led 17x > Build/Demo 16x > Story 10x > Prediction 6x. Plain text "post" format 22x vs image posts 13x. Prediction/trend posts under-perform on LinkedIn.
A9: Hooks on X [data] | B9: Contrarian 52x > Declarative one-liners 36x > Result-led 35x > Story 31x > How-to 16x. X rewards compressed opinion and numbers.
A10: Hooks on IG [data] | B10: Objection/Quote hooks 108x (n=4) and Insider/Secret 69x (n=5) lead. Result-led 36x. Comment-gate reels 19x but convert reach into DMs. IG favours "here is the exact script/line" formats.
A11: CTA [data] | B11: Comment-keyword to DM posts: 26x median vs 20x for pure-value posts. On IG, 13 of 94 fit-qualified outliers used a comment gate. Use comment-gates for lead magnets 1 in 4 posts, not every post.
A12: What the data cannot tell you | B12: Which posts generated pipeline. Outlier = engagement, not revenue. Engagers on viral sales posts are often aspirants. Your own engager analysis (who from ICP engaged) is the real KPI.
A14: Content pillars and mix
A15: P1 Pipeline Diagnosis (25%) | B15: Referral dependency, founder-led sales ceiling, concentration risk, why agencies fail. Problem-aware TOFU. Hooks: contrarian, objection, number-led. Ref: @kathleenslatterybooth 351x, @silgofak 27x, @theroborourke India agency 41x.
A16: P2 Warm Outbound Plays (20%) | B16: Signal-based DMs, comment-to-pipeline, 2-sentence DMs, follow-up scripts. MOFU how-to. Ref: @theroborourke DM post 48x, @fin465 YC playbook 30x, @magalidereu comment system.
A17: P3 High-Ticket Sales & Pricing (15%) | B17: Discovery lines, objections, proposal-to-close, pricing retainers. Highest-heat cluster (52x). Ref: @theroborourke two-extremes 46x, @writewithkush objection, @itsashleyboston follow-up 220x.
A18: P4 Proof & Build-in-Public (15%) | B18: Client ledgers, pipeline reports, teardowns of real outbound, monthly revenue/source split. BOFU. Ref: @theroborourke $93k month 32x, @harry-wilson LinkedIn DM ledger 20x, @michlieben $153k MRR 326x.
A19: P5 Authority Content System (15%) | B19: How founder content converts (not how to go viral): attribution, invisible buyers, LinkedIn vs YouTube lead quality. Ref: @theroborourke web designer 35x, @paolo_scales whale clients.
A20: P6 Scale Systems (10%) | B20: Founder out of loops, team advocacy, KPI dashboards, onboarding docs. Ref: @nickavaria dashboard 44-112x, @agencysupply.co onboarding 60x.
A21: Series: International Client Hunting | B21: Cross-pillar weekly series for the India cohort: how Indian firms win US/UK clients (positioning, pricing in USD, outbound to international ICPs). English on LinkedIn, Hinglish reel cut on IG.
A23: Platform roles and cadence
A24: LinkedIn: conversion + proof (60% of effort) | B24: Where ICP A and ICP B buy. 5 posts/week (3 text, 1 carousel/doc, 1 proof). 20 strategic comments/day on ICP and adjacent-creator posts (comment-to-pipeline). Featured section: lead magnet + case study.
A25: X: idea lab + operator network (25%) | B25: 1-2 short posts/day plus 1 thread/week. Test hooks here first; promote winners (top 20% by engagement rate) to LinkedIn 3-7 days later. Network with agency/consultancy operators (see Creator Watchlist: 15 X creators).
A26: Instagram: trust video + India cohort (15%) | B26: 3 reels/week: 1 English talking-head (script/line format), 1 screen-record (system/tool), 1 Hinglish India-cohort reel. Pin an "If we've never met" intro reel. Comment-gate the lead magnet.
A27: Time budget [assumption] | B27: ≈10 hrs/week: 4h writing (batch Mon), 1.5h filming (batch Tue, 6 reels/session), 3h engagement (30 min/day ×6), 1.5h review + repurposing.
A29: Funnel architecture
A30: TOFU: Attention | B30: Contrarian diagnosis posts, aphorisms, stories. Goal: profile visits from ICP. KPI: ICP-follower growth (not total followers), profile views.
A31: MOFU: Capture | B31: Lead magnet: "Pipeline Dependency Scorecard" (10 questions, scores referral %, founder-sourced %, concentration, cycle). Delivered via comment-keyword (LinkedIn/IG) and DM. KPI: scorecard completions/week.
A32: Warm signal capture | B32: Everyone who comments, completes the scorecard, or engages 2+ times goes into a warm list (CRM). Enrich: company size 15-50, revenue proxy. This is where content becomes outbound.
A33: Warm outbound | B33: Signal-triggered DM within 24h: reference their engagement/scorecard, one insight, one question. No pitch in message 1. 3-touch over 10 days. KPI: reply rate ≥15% (vs ~3-5% cold).
A34: BOFU: Convert | B34: 30-min "Pipeline Diagnostic" call leading to a paid diagnostic ($1.5-2.5k, credited to setup) or a proposal. India: cohort application call or webinar.
A35: Proof loop | B35: Every client result becomes P4 content within 30 days; every objection heard becomes a P3 post.
A37: Funnel math: 6-month targets [assumption, replace with actuals]
A38: DFY goal | B38: 4 clients × $7.5k/mo = $30k MRR by month 6.
A39: Back-solve | B39: 4 clients ÷ 25% close = 16 qualified calls ÷ 80% show = 20 booked ÷ 30% positive-reply-to-call = 67 positive replies ÷ 15% warm reply rate ≈ 450 warm DMs ≈ 18/week. Content must generate ≥18 new warm ICP signals/week by month 3 (engagers + scorecard + profile viewers), topped up with signal-based outbound (hiring posts, funding, job changes).
A40: Cohort goal | B40: 15 firms × ₹1.5L = ₹22.5L per cohort. At 10% application-to-enrol: 150 applications. From scorecard/lead-magnet at 20% apply rate: 750 leads per cohort cycle (≈8 weeks), or about 95/week. Needs IG + LinkedIn reach, a webinar, and partner promotion. Realistically cohort 1 = 8-10 firms.
A41: Leading KPIs (weekly) | B41: ICP-qualified engagers, scorecard completions, warm DMs sent, reply rate, calls booked, and % of calls sourced from content signals.
A43: Sequencing (opportunity-cost view)
A44: Months 0-2 | B44: LinkedIn + X only. Build scorecard. 30 warm DMs/week from signals. Land 2 DFY pilots at a founder rate ($4-5k/mo) for case studies. Do NOT launch the cohort yet.
A45: Months 2-4 | B45: Add IG (3 reels/wk). Publish the first 2 case studies. Raise DFY to $7.5k+. Run a free 60-min "International Client Hunting" workshop for Indian firms to validate cohort demand (target 100+ registrations).
A46: Months 4-6 | B46: Launch cohort 1 if the workshop hits ≥100 registrations and ≥15 applications; otherwise sell done-with-you to the best 3 Indian firms instead.
A47: Biggest risks | B47: (1) Founder-led content needs YOUR proof. Without case studies, P4 is empty, so pilots come first. (2) Splitting focus across 2 offers too early. (3) Measuring views instead of ICP signals. (4) Copying AI-tool hype formats (common in the data) which attract builders, not buyers.

Sheet Master Database
A1: # | B1: Platform | C1: Language | D1: Source | E1: Signal | F1: Breakout (≥10x) | G1: Hidden Gem | H1: Viral | I1: Primary Cluster | J1: Secondary Clusters | K1: Creator | L1: Handle | M1: Followers | N1: Follower Band | O1: Published | P1: URL | Q1: Hook (first line / title) | R1: Post Text (preview) | S1: Hook Archetype | T1: CTA Mechanism | U1: Funnel Stage | V1: Format | W1: Content Type | X1: Mood | Y1: Views | Z1: Likes | AA1: Comments | AB1: Shares | AC1: Engagement Rate | AD1: Outlier (raw) | AE1: Outlier (capped 100) | AF1: Creator Percentile | AG1: Anomalous Baseline? | AH1: ICP Fit (1-10) | AI1: AI-Tool Angle | AJ1: Aspirant Audience | AK1: Best-Fit Offer | AL1: Priority Score | AM1: Why It Worked | AN1: Reverse-Engineer Prompt | AO1: AI Summary | AP1: Topic Tags | AQ1: Found Via (query) | AR1: Status | AS1: My Adaptation Notes
A2: 1 | B2: X | C2: English | D2: Eden | E2: Hidden Gem | F2: Yes | G2: Yes | H2: No | I2: Marketing Strategy | J2: High-Ticket Sales, Outbound / Warm Outbound, Business Growth & Scale Systems | K2: MONTE | L2: @fromzerotomill | M2: 12888 | N2: 10-20k | O2: 2025-11-24 | P2: https://x.com/fromzerotomill/status/1992916088544256502 | Q2: i know a guy making $400k/yr selling "digital disappearance" guides to burned-out tech bros who want to delete their online presence | R2: i know a guy making $400k/yr selling "digital disappearance" guides to burned-out tech bros who want to delete their online presence instead of teaching people how to BUILD an online presence, this guy is teaching people how to DESTROY theirs and it's the smartest offer i've seen in years first, he understood who's buying this it's not paranoid preppers in bunkers it's: - 34 year old seni | S2: Story / Anecdote | T2: None (pure value) | U2: TOFU: Reach / POV | V2: text | W2: other | X2: informative | Y2: 105656 | Z2: 1016 | AA2: 36 | AB2: 67 | AC2: 0.010590974 | AD2: 243.68 | AE2: =IF(AD2="","",MIN(AD2,100)) -> 100 | AF2: 99 | AG2: No | AH2: 10 | AI2: No | AJ2: No | AK2: Intl: Authority-to-Pipeline DFY | AL2: =ROUND('Start Here'!$B$29*AH2+'Start Here'!$B$30*MIN(IF(AD2="",0,AD2),50)/5+IF(M2<=30000,'Start Here'!$B$31,IF(M2<=60000,'Start Here'!$B$32,0)),1) -> 10 | AM2: Small-account breakout: the idea beat the audience size; Specific number/result in the hook; First-person or observed story: narrative pull | AN2: Keep the story hook mechanic and swap in your own proof. Teach one marketing strategy lesson for founders of 10-50 person boutique firms (US/UK/AU). Ship it as a LinkedIn text/carousel. | AO2: A text post analyzes a high-income entrepreneur's $400k/year business offering guides for digital self-erasure to stressed tech professionals, detailing client demographics, market demand, and the multi-tiered pricing strategy that leverages referrals from affluent customers. | AP2: entrepreneurship, digital privacy, tech industry, business model, client acquisition, market demand, pricing strategy, cash flow | AQ2: referrals plateau service business founder stuck at revenue ceiling; premium pricing offer positioning charge more consulting retainer | AR2: Backlog
A3: 2 | B3: Instagram | C3: English | D3: Eden | E3: Hidden Gem | F3: Yes | G3: Yes | H3: No | I3: Marketing Strategy | J3: Agency Growth, High-Ticket Sales, Client Acquisition | K3: Meghan Clor • Marketing Agency | L3: @meghanclor | M3: 13612 | N3: 10-20k | O3: 2026-10-06 | P3: https://www.instagram.com/reel/DeKt5O_Sz9_/ | Q3: Attract clients who don’t flinch at your price 👀 | R3: Attract clients who don’t flinch at your price 👀 Love this clip from @prime.brains A small shift in messaging can completely change the type of buyer your offer attracts. This is one of my favorite ways to make marketing do more of the qualifying for you 🔥🧲 | S3: Statement / Declarative | T3: None (pure value) | U3: TOFU: Reach / POV | V3: short_video | W3: tutorial | X3: educational | Y3: 73913 | Z3: 2054 | AA3: 117 | AC3: 0.02937237 | AD3: 922.06 | AE3: =IF(AD3="","",MIN(AD3,100)) -> 100 | AF3: 98.6 | AG3: No | AH3: 10 | AI3: No | AJ3: No | AK3: Intl: Authority-to-Pipeline DFY | AL3: =ROUND('Start Here'!$B$29*AH3+'Start Here'!$B$30*MIN(IF(AD3="",0,AD3),50)/5+IF(M3<=30000,'Start Here'!$B$31,IF(M3<=60000,'Start Here'!$B$32,0)),1) -> 10 | AM3: Small-account breakout: the idea beat the audience size | AN3: Keep the statement hook mechanic and swap in your own proof. Teach one marketing strategy lesson for founders of 10-50 person boutique firms (US/UK/AU). Ship it as a IG reel, then repurpose to LinkedIn. | AO3: Marketing agency owner Meghan Clor shares a clip from @prime.brains explaining why words like "premium" and "luxury" don't sell, and how identity-based messaging attracts buyers who pay without flinching. Examples include a luxury travel offer rewritten for five-star travelers and the classic Rolls-Royce clock ad. | AP3: marketing, messaging, pricing, positioning, premium brand, luxury, client attraction, offer | AQ3: premium pricing offer positioning charge more consulting retainer | AR3: Backlog
A4: 3 | B4: Instagram | C4: English | D4: Eden | E4: Hidden Gem | F4: Yes | G4: Yes | H4: No | I4: Consulting / Fractional | J4: High-Ticket Sales, Marketing Strategy, Client Acquisition | K4: David Boland | L4: @justdavidboland | M4: 19437 | N4: 10-20k | O4: 2026-05-22 | P4: https://www.instagram.com/reel/DYo8Da5PPe3/ | Q4: Coaches and consultants: comment “chocolate” for the pricing masterclass for coaches & consultants where you’ll learn exactly how to pick a price for your offer and a plan to land a client in the next few hours (yes, it | R4: Coaches and consultants: comment “chocolate” for the pricing masterclass for coaches & consultants where you’ll learn exactly how to pick a price for your offer and a plan to land a client in the next few hours (yes, it is possible) | S4: Comment-Gate / Lead Magnet | T4: Comment keyword → DM | U4: Lead Capture (MOFU) | V4: text | W4: promo | X4: informative | Y4: 194374 | Z4: 7303 | AA4: 4823 | AC4: 0 | AD4: 410.07 | AE4: =IF(AD4="","",MIN(AD4,100)) -> 100 | AF4: 99.8 | AG4: No | AH4: 10 | AI4: No | AJ4: No | AK4: Intl: Authority-to-Pipeline DFY | AL4: =ROUND('Start Here'!$B$29*AH4+'Start Here'!$B$30*MIN(IF(AD4="",0,AD4),50)/5+IF(M4<=30000,'Start Here'!$B$31,IF(M4<=60000,'Start Here'!$B$32,0)),1) -> 10 | AM4: Small-account breakout: the idea beat the audience size; Comment-gate inflates comments, which the algorithm rewards | AN4: Keep the comment-gate hook mechanic and swap in your own proof. Teach one consulting / fractional lesson for founders of 10-50 person boutique firms (US/UK/AU). Ship it as a IG reel, then repurpose to LinkedIn. | AO4: This video instructs coaches and consultants on premium pricing and differentiation strategies by encouraging exclusive client engagement rather than mass affordability. Audience is instructed to comment 'chocolate' to receive the pricing masterclass. | AP4: pricing strategy, masterclass, exclusive clients, coaching, consulting, premium pricing, marketing | AQ4: premium pricing offer positioning charge more consulting retainer | AR4: Backlog
A5: 4 | B5: Instagram | C5: English | D5: Eden | E5: Hidden Gem | F5: Yes | G5: Yes | H5: No | I5: Marketing Strategy | J5: Consulting / Fractional, Client Acquisition, Outbound / Warm Outbound | K5: Chris Dufey | L5: @chrisdufey | M5: 5949 | N5: 5-10k | O5: 2026-10-05 | P5: https://www.instagram.com/reel/DeIN6T6zB0G/ | Q5: My 7 year old looked at me on the beach today, dead serious. | R5: My 7 year old looked at me on the beach today, dead serious. “Dad. Why aren’t you at work?” I am. (She didn’t buy it. She went back to burying her sister.) Most coaches can’t take half a day off without the whole business grinding to a halt. So you go to the beach “with the kids”. Your body’s on the sand. Your head’s in your phone, like a seagull guarding a chip. But you didn’t start this f | S5: Story / Anecdote | T5: None (pure value) | U5: TOFU: Reach / POV | V5: long_video | W5: promo | X5: aspirational | Y5: 10279 | Z5: 29 | AA5: 0 | AC5: 0.0028212861 | AD5: 161.76 | AE5: =IF(AD5="","",MIN(AD5,100)) -> 100 | AF5: 100 | AG5: No | AH5: 10 | AI5: No | AJ5: No | AK5: Intl: Authority-to-Pipeline DFY | AL5: =ROUND('Start Here'!$B$29*AH5+'Start Here'!$B$30*MIN(IF(AD5="",0,AD5),50)/5+IF(M5<=30000,'Start Here'!$B$31,IF(M5<=60000,'Start Here'!$B$32,0)),1) -> 10 | AM5: Small-account breakout: the idea beat the audience size; First-person or observed story: narrative pull | AN5: Keep the story hook mechanic and swap in your own proof. Teach one marketing strategy lesson for founders of 10-50 person boutique firms (US/UK/AU). Ship it as a IG reel, then repurpose to LinkedIn. | AO5: Chris Dufey tells a beach story about his daughter asking why he isn't at work to argue that coaches should build businesses that run without them. He promotes his team's done-for-you marketing and growth service and asks viewers with a proven offer to DM "TUESDAY" for a free demo call. | AP5: coaching business, client acquisition, time freedom, done-for-you marketing, demo call cta, freedom, business systems, lead generation | AQ5: client kaise laaye business grow kaise kare sales marketing agency | AR5: Backlog
A6: 5 | B6: Instagram | C6: English | D6: Eden | E6: Hidden Gem | F6: Yes | G6: Yes | H6: No | I6: Marketing Strategy | J6: Consulting / Fractional, Business Growth & Scale Systems, Client Acquisition | K6: Ollie Carson | Business Growth Coach | L6: @olliecarson__ | M6: 29450 | N6: 20-30k | O6: 2026-04-10 | P6: https://www.instagram.com/reel/DW8TbCSDWOZ/ | Q6: �Comment “ROADMAP” and I’ll send you my full breakdown on building a coaching offer that actually sells. | R6: �Comment “ROADMAP” and I’ll send you my full breakdown on building a coaching offer that actually sells. If we’ve never spoken before: I’m Ollie. I run RemotePro. I help online coaches and consultants build and scale their businesses without sleazy tactics or the copy-paste strategies that everyone else is selling. I’m the founder of RemotePro - a hands-on one-to-one mentorship program where y | S6: Comment-Gate / Lead Magnet | T6: Comment keyword → DM | U6: Lead Capture (MOFU) | V6: long_video | W6: tutorial | X6: educational | Y6: 120649 | Z6: 3013 | AA6: 3411 | AC6: 0.053245365 | AD6: 62.28 | AE6: =IF(AD6="","",MIN(AD6,100)) -> 62.28 | AF6: 99.7 | AG6: No | AH6: 10 | AI6: No | AJ6: No | AK6: Intl: Authority-to-Pipeline DFY | AL6: =ROUND('Start Here'!$B$29*AH6+'Start Here'!$B$30*MIN(IF(AD6="",0,AD6),50)/5+IF(M6<=30000,'Start Here'!$B$31,IF(M6<=60000,'Start Here'!$B$32,0)),1) -> 10 | AM6: Comment-gate inflates comments, which the algorithm rewards | AN6: Keep the comment-gate hook mechanic and swap in your own proof. Teach one marketing strategy lesson for founders of 10-50 person boutique firms (US/UK/AU). Ship it as a IG reel, then repurpose to LinkedIn. | AO6: A person explains a business funnel diagram on Instagram and Manychat for coaching, highlighting strategies for building and scaling coaching businesses with lead capture, personal branding, and social proof. Examples of client success are mentioned. | AP6: coaching business, business funnel, lead capture, personal brand, social proof, instagram marketing, manychat, client retention | AQ6: founder dependency hiring delegation scaling agency beyond the founder | AR6: Backlog
A7: 6 | B7: X | C7: English | D7: Eden | E7: Hidden Gem | F7: Yes | G7: Yes | H7: Yes | I7: Outbound / Warm Outbound | J7: Marketing Strategy, Client Acquisition, High-Ticket Sales | K7: Rob O'Rourke | L7: @theroborourke | M7: 10660 | N7: 10-20k | O7: 2025-11-17 | P7: https://x.com/theroborourke/status/1990343987148775791 | Q7: I work with a few guys doing anywhere from $50k/m to $400k/m using mostly cold outreach. | R7: I work with a few guys doing anywhere from $50k/m to $400k/m using mostly cold outreach. Here's what kills response rates... Messages that look like copy-paste essays. If your first DM is 6+ sentences in one huge block, you're done. Social media isn't email. People scan, they don't read. - You need to break your pitch into 2-3 short messages - Lead with the single most relevant thing about wh | S7: Story / Anecdote | T7: DM ask | U7: TOFU: Reach / POV | V7: text | W7: tutorial | X7: informative | Y7: 822907 | Z7: 1554 | AA7: 46 | AB7: 77 | AC7: 0.0020378974 | AD7: 48 | AE7: =IF(AD7="","",MIN(AD7,100)) -> 48 | AF7: 99.7 | AG7: No | AH7: 10 | AI7: No | AJ7: No | AK7: Intl: Authority-to-Pipeline DFY | AL7: =ROUND('Start Here'!$B$29*AH7+'Start Here'!$B$30*MIN(IF(AD7="",0,AD7),50)/5+IF(M7<=30000,'Start Here'!$B$31,IF(M7<=60000,'Start Here'!$B$32,0)),1) -> 9.9 | AM7: Authority by proximity ('I work with guys doing $50k-$400k/m') plus one concrete, checkable mistake (6+ sentence DMs). Instant self-audit for the reader. | AN7: 'I reviewed 214 LinkedIn DMs our clients' prospects actually replied to. The 3 that booked calls were all under 40 words.' Use your own outbound data. Attach a before/after DM screenshot. | AO7: The post advises sales professionals on improving cold outreach response rates by avoiding long, essay-like messages and instead using brief, conversational messages that lead with relevant points and proof. The author emphasizes getting initial replies before attempting to close deals. | AP7: cold outreach, sales advice, response rates, communication, dm strategy, sales tips, social media, email alternative | AQ7: LinkedIn DM outreach scripts and warm prospecting signals; cold email outbound that books meetings for consultants | AR7: Backlog
A8: 7 | B8: X | C8: English | D8: Eden | E8: Hidden Gem | F8: Yes | G8: Yes | H8: Yes | I8: Business Growth & Scale Systems | J8: Marketing Strategy, Outbound / Warm Outbound, Content Marketing & Systems | K8: Romàn | L8: @romanbuildsaas | M8: 22306 | N8: 20-30k | O8: 2026-04-24 | P8: https://x.com/romanbuildsaas/status/2047825608030494758 | Q8: Gojiberry AI just hit $2M ARR. | R8: Gojiberry AI just hit $2M ARR. A few months ago we were at €0. This is the second SaaS I've built. The first one I sold at €500K ARR. This time, we moved faster. Here's exactly how we did it, so you can do it too. The core principle that changed everything: We used our own tool to grow our own tool. Gojiberry AI finds high-intent leads and engages with them automatically. We run it on ourse | S8: Result / Number-Led Claim | T8: None (pure value) | U8: TOFU: Reach / POV | V8: image | W8: story | X8: inspirational | Y8: 528885 | Z8: 1769 | AA8: 341 | AB8: 212 | AC8: 0.0043903684 | AD8: 47.07 | AE8: =IF(AD8="","",MIN(AD8,100)) -> 47.07 | AF8: 99.5 | AG8: No | AH8: 10 | AI8: No | AJ8: No | AK8: Intl: Authority-to-Pipeline DFY | AL8: =ROUND('Start Here'!$B$29*AH8+'Start Here'!$B$30*MIN(IF(AD8="",0,AD8),50)/5+IF(M8<=30000,'Start Here'!$B$31,IF(M8<=60000,'Start Here'!$B$32,0)),1) -> 9.8 | AM8: Specific number/result in the hook; Proof-first opening | AN8: Keep the result hook mechanic and swap in your own proof. Teach one business growth & scale systems lesson for founders of 10-50 person boutique firms (US/UK/AU). Ship it as a LinkedIn text/carousel. | AO8: The author shares how his SaaS product reached $2M ARR after starting from zero, detailing growth tactics including outreach, inbound marketing, and AI automation, and discussing scaling challenges. | AP8: mrr milestones, saas, growth hacking, outreach, inbound marketing, reddit marketing, linkedin marketing, ai automation | AQ8: founder dependency hiring delegation scaling agency beyond the founder | AR8: Backlog
A9: 8 | B9: X | C9: English | D9: Eden | E9: Hidden Gem | F9: Yes | G9: Yes | H9: No | I9: High-Ticket Sales | J9: Business Growth & Scale Systems, Client Acquisition, Consulting / Fractional | K9: Nick Bennett | L9: @nickb2005 | M9: 5044 | N9: 5-10k | O9: 2026-09-02 | P9: https://x.com/NickB2005/status/2095121648710037913 | Q9: A client once asked me whether they should spend $40K on a sponsor booth at a major SaaS conference or try something smaller. | R9: A client once asked me whether they should spend $40K on a sponsor booth at a major SaaS conference or try something smaller. I told them to take $800, book a private dining room at a steakhouse 4 blocks away, and invite 8 target VPs of Operations who were already attending the event. We skipped the slide decks entirely. We ordered dry-aged ribeyes, poured two bottles of cabernet, and opened wit | S9: Story / Anecdote | T9: None (pure value) | U9: BOFU: Proof / Case Study | V9: text | W9: tutorial | X9: informative | Y9: 140419 | Z9: 1614 | AA9: 106 | AB9: 97 | AC9: 0.012939844 | AD9: 240.49 | AE9: =IF(AD9="","",MIN(AD9,100)) -> 100 | AF9: 99.8 | AG9: No | AH9: 9 | AI9: No | AJ9: No | AK9: Intl: Authority-to-Pipeline DFY | AL9: =ROUND('Start Here'!$B$29*AH9+'Start Here'!$B$30*MIN(IF(AD9="",0,AD9),50)/5+IF(M9<=30000,'Start Here'!$B$31,IF(M9<=60000,'Start Here'!$B$32,0)),1) -> 9.5 | AM9: Contrast in budget ($40K booth vs $800 dinner) + vivid detail + outcome. Small account (5k) at 240x: story quality beats audience size. | AN9: 'Skip the conference booth' play for boutique firms: 8-person founder dinner, then content recap, then warm outbound to attendees. Describe it as part of your system. | AO9: A consultant shares a case study about using a targeted dinner with key decision-makers instead of a large conference booth investment, resulting in significant closed deals and ARR from minimal spending. | AP9: saas, b2b, conference, client acquisition, sales strategy, dinner meeting, vp of operations, deal closing | AQ9: "fractional" CMO CFO COO getting clients | AR9: Backlog
A10: 9 | B10: X | C10: English | D10: Eden | E10: Hidden Gem | F10: Yes | G10: Yes | H10: No | I10: Business Growth & Scale Systems | J10: Outbound / Warm Outbound, Client Acquisition, Marketing Strategy | K10: Matthew Berman | L10: @themattberman | M10: 13338 | N10: 10-20k | O10: 2026-02-20 | P10: https://x.com/TheMattBerman/status/2024678503598235963 | Q10: I replaced a $200K GTM hire with @openclaw 😱 | R10: I replaced a $200K GTM hire with @openclaw 😱 here's the system that runs my outbound: step 1: mine LinkedIn engagement → @rapidapi scrapes everyone engaging with niche content → someone who commented on specific posts = 10x warmer step 2: enrich + verify → Hunter/Apollo finds the decision-maker + email → @Perplexity deep research pulls signals like hiring, fundraising, media appearances, quot | S10: Story / Anecdote | T10: None (pure value) | U10: TOFU: Reach / POV | V10: long_video | W10: tutorial | X10: educational | Y10: 188880 | Z10: 1905 | AA10: 1088 | AB10: 99 | AC10: 0.016370182 | AD10: 134.05 | AE10: =IF(AD10="","",MIN(AD10,100)) -> 100 | AF10: 98.8 | AG10: No | AH10: 8.6 | AI10: Yes | AJ10: No | AK10: Intl: Authority-to-Pipeline DFY | AL10: =ROUND('Start Here'!$B$29*AH10+'Start Here'!$B$30*MIN(IF(AD10="",0,AD10),50)/5+IF(M10<=30000,'Start Here'!$B$31,IF(M10<=60000,'Start Here'!$B$32,0)),1) -> 9.3 | AM10: Small-account breakout: the idea beat the audience size; Specific number/result in the hook; First-person or observed story: narrative pull; High comment-to-like ratio: debate driver | AN10: Keep the story hook mechanic and swap in your own proof. Teach one business growth & scale systems lesson for founders of 10-50 person boutique firms (US/UK/AU). Ship it as a LinkedIn text/carousel. | AO10: A LinkedIn video shows how the author automated his sales team's outbound lead generation process using various tools. The speaker outlines a six-step system for identifying, enriching, scoring, and reaching out to ideal customer profiles using API scraping, AI research, and personalized email sequences. | AP10: sales automation, outbound prospecting, ai tools, lead generation, marketing efficiency, workflow automation, cost savings, linked in engagement | AQ10: LinkedIn DM outreach scripts and warm prospecting signals | AR10: Backlog
A11: 10 | B11: X | C11: English | D11: Eden | E11: Hidden Gem | F11: Yes | G11: Yes | H11: Yes | I11: Freelancing & International Clients | J11: Consulting / Fractional, Client Acquisition, High-Ticket Sales | K11: Rob O'Rourke | L11: @theroborourke | M11: 10660 | N11: 10-20k | O11: 2025-11-17 | P11: https://x.com/theroborourke/status/1990376468736618997 | Q11: In my first year of freelancing, I went from selling $200 websites to $20k+ websites. | R11: In my first year of freelancing, I went from selling $200 websites to $20k+ websites. Here's a sales trick I used to figure out what clients actually wanted: Give two extreme options and see which way they lean. "Do you want to pause this idea completely and come back when timing is better, or do you want to try to get started on this in the next week or two?" This gets them to lean one way or | S11: Result / Number-Led Claim | T11: None (pure value) | U11: TOFU: Reach / POV | V11: text | W11: tutorial | X11: informative | Y11: 859734 | Z11: 1487 | AA11: 34 | AB11: 80 | AC11: 0.0018622039 | AD11: 45.94 | AE11: =IF(AD11="","",MIN(AD11,100)) -> 45.94 | AF11: 99.6 | AG11: No | AH11: 9 | AI11: No | AJ11: No | AK11: Intl: Authority-to-Pipeline DFY | AL11: =ROUND('Start Here'!$B$29*AH11+'Start Here'!$B$30*MIN(IF(AD11="",0,AD11),50)/5+IF(M11<=30000,'Start Here'!$B$31,IF(M11<=60000,'Start Here'!$B$32,0)),1) -> 9.3 | AM11: Transformation range ($200 to $20k) plus ONE usable sales line (two-extremes question). Low effort to apply, high save rate. | AN11: Series: 'One line I use on discovery calls with $5M consultancies' (e.g., 'If nothing changes in your pipeline for 6 months, what breaks first?'). One line per post, explain the psychology. | AO11: A freelancer shares a sales technique used to determine client intent by offering two extreme options, allowing them to either commit or respectfully decline the proposal. | AP11: freelancing, sales, client acquisition, pricing, web design, consulting | AQ11: freelancer to agency first clients Upwork pricing in dollars Hinglish | AR11: Backlog
A12: 11 | B12: LinkedIn | C12: English | D12: Eden | E12: Hidden Gem | F12: Yes | G12: Yes | H12: No | I12: Agency Growth | J12: Business Growth & Scale Systems, High-Ticket Sales, Marketing Strategy | K12: Nick Avaria | L12: @nickavaria | M12: 18671 | N12: 10-20k | O12: 2026-01-29 | P12: https://www.linkedin.com/feed/update/urn:li:activity:7422654796735807491 | Q12: I scaled my agency to $10M/yr in 3.5 years. | R12: I scaled my agency to $10M/yr in 3.5 years. Closing lots of deals didn’t get me there What did was a holistic understanding of my agency’s numbers and data. Which I used to make high-quality decisions that helped me grow fast. This KPI sheet makes managing your numbers easier. Agency founders, COOs, and heads of ops, this is for you if: - You have a “busy” team, but not a profitable one - | S12: Story / Anecdote | T12: None (pure value) | U12: TOFU: Reach / POV | V12: post | Z12: 214 | AA12: 543 | AB12: 1 | AC12: 0.041855329 | AD12: 43.7 | AE12: =IF(AD12="","",MIN(AD12,100)) -> 43.7 | AF12: 98.6 | AG12: No | AH12: 9 | AI12: No | AJ12: No | AK12: Intl: Authority-to-Pipeline DFY | AL12: =ROUND('Start Here'!$B$29*AH12+'Start Here'!$B$30*MIN(IF(AD12="",0,AD12),50)/5+IF(M12<=30000,'Start Here'!$B$31,IF(M12<=60000,'Start Here'!$B$32,0)),1) -> 9.1 | AM12: Big credible result ($10M agency) + reframe (not closing, numbers) + free KPI sheet. LinkedIn rewards resource posts with a comment-gate. | AN12: Build a 'Pipeline Health Scorecard' for 10-50 person firms (referral %, founder-sourced %, sales cycle, win rate, content-sourced %). Gate it via comment. This is your core lead magnet. | AQ12: agency growth scaling service business revenue | AR12: Backlog
A13: 12 | B13: X | C13: English | D13: Eden | E13: Hidden Gem | F13: Yes | G13: Yes | H13: No | I13: Marketing Strategy | J13: Business Growth & Scale Systems, Client Acquisition, Content Marketing & Systems | K13: Rob O'Rourke | L13: @theroborourke | M13: 10660 | N13: 10-20k | O13: 2026-01-28 | P13: https://x.com/theroborourke/status/2016436919505146264 | Q13: Working with a web designer who 3x'd his revenue last year. | R13: Working with a web designer who 3x'd his revenue last year. Went from $40K to around $130K. Almost ALL of it came from content. Mainly LinkedIn and YouTube. Plus around 10-20% in referrals. But here's what's interesting... His YouTube videos get a ton of views. But nearly all his actual paying leads came through the LinkedIn side. Why? The YT content was all technical. How he builds sites, | S13: Result / Number-Led Claim | T13: None (pure value) | U13: BOFU: Proof / Case Study | V13: text | W13: story | X13: informative | Y13: 271671 | Z13: 1129 | AA13: 26 | AB13: 48 | AC13: 0.0044281502 | AD13: 34.88 | AE13: =IF(AD13="","",MIN(AD13,100)) -> 34.88 | AF13: 99.3 | AG13: No | AH13: 10 | AI13: No | AJ13: No | AK13: Intl: Authority-to-Pipeline DFY | AL13: =ROUND('Start Here'!$B$29*AH13+'Start Here'!$B$30*MIN(IF(AD13="",0,AD13),50)/5+IF(M13<=30000,'Start Here'!$B$31,IF(M13<=60000,'Start Here'!$B$32,0)),1) -> 9.1 | AM13: Case study with a counter-intuitive split: YouTube got views, LinkedIn got paying leads. Data-backed platform insight. | AN13: Directly validates your thesis. Post: 'Our client's reels got 40x the views of their LinkedIn posts. LinkedIn produced 11 of 12 closed deals. Here's why.' Use your own or a client's attribution data. | AO13: Apost about a web designer who 3x’d his revenue to $130K by focusing on content marketing. Most leads came from LinkedIn expert content rather than YouTube technical videos. | AP13: web design, revenue growth, content marketing, social media marketing, linkedina, youtube, digital marketing, lead generation | AQ13: agency growth scaling service business revenue; referrals plateau service business founder stuck at revenue ceiling | AR13: Backlog
A14: 13 | B14: Instagram | C14: English | D14: Eden | E14: Breakout | F14: Yes | G14: No | H14: Yes | I14: High-Ticket Sales | J14: Client Acquisition, Outbound / Warm Outbound, Marketing Strategy | K14: Ashley Boston | Content Strategy for Creatives | L14: @itsashleyboston | M14: 57809 | N14: 50-100k | O14: 2026-03-28 | P14: https://www.instagram.com/reel/DWb9bMukmwe/ | Q14: The follow up message that brought back a lead I thought was gone forever 👇🏼 | R14: The follow up message that brought back a lead I thought was gone forever 👇🏼 No “just checking in.” No “did you get a chance to think about it?” No desperation. Just this: “Hey [Name], I’ve been thinking about our conversation and I realized I never actually asked you the most important question. What would need to be true for you to feel completely confident moving forward? Is it the | S14: Statement / Declarative | T14: None (pure value) | U14: TOFU: Reach / POV | V14: short_video | W14: tutorial | X14: informative | Y14: 896099 | Z14: 9063 | AA14: 2296 | AC14: 0.012676055 | AD14: 219.64 | AE14: =IF(AD14="","",MIN(AD14,100)) -> 100 | AF14: 99.7 | AG14: No | AH14: 10 | AI14: No | AJ14: No | AK14: Intl: Authority-to-Pipeline DFY | AL14: =ROUND('Start Here'!$B$29*AH14+'Start Here'!$B$30*MIN(IF(AD14="",0,AD14),50)/5+IF(M14<=30000,'Start Here'!$B$31,IF(M14<=60000,'Start Here'!$B$32,0)),1) -> 9 | AM14: Swipeable script (exact follow-up text). Specific 'No just checking in' contrast; saves and shares drive reach. | AN14: 'The follow-up I send 9 days after a proposal goes quiet' with the exact text. Make it a recurring 'Script Saturday' format. | AO14: A short sales tutorial video teaches how to write an effective follow-up message to recover a lost lead. The message focuses on understanding the client's real objections and avoids pressuring them, using open-ended questions to invite discussion. | AP14: sales follow-up, lead recovery, client engagement, sales script, high-ticket clients, sales objection handling, client communication, sales strategy | AQ14: sales system CRM follow-up process for service business owners | AR14: Backlog
A15: 14 | B15: X | C15: English | D15: Eden | E15: Hidden Gem | F15: Yes | G15: Yes | H15: Yes | I15: Marketing Strategy | J15: Agency Growth, Client Acquisition, Content Marketing & Systems | K15: MONTE | L15: @fromzerotomill | M15: 12888 | N15: 10-20k | O15: 2026-01-26 | P15: https://x.com/fromzerotomill/status/2015743611237785804 | Q15: had coffee with a guy last thursday who sold his marketing agency for $6.3m and i'm still processing what he told me | R15: had coffee with a guy last thursday who sold his marketing agency for $6.3m and i'm still processing what he told me we were supposed to talk for 30 minutes. ended up being almost 3 hours because what he said completely flipped how i think about building businesses "clients weren't paying for strategy. they were paying for the fact that i could get their message seen by their exact audience fast | S15: Result / Number-Led Claim | T15: None (pure value) | U15: TOFU: Reach / POV | V15: text | W15: story | X15: informative | Y15: 338478 | Z15: 2170 | AA15: 55 | AB15: 155 | AC15: 0.0070314762 | AD15: 520.9 | AE15: =IF(AD15="","",MIN(AD15,100)) -> 100 | AF15: 100 | AG15: No | AH15: 8 | AI15: No | AJ15: No | AK15: Intl: Authority-to-Pipeline DFY | AL15: =ROUND('Start Here'!$B$29*AH15+'Start Here'!$B$30*MIN(IF(AD15="",0,AD15),50)/5+IF(M15<=30000,'Start Here'!$B$31,IF(M15<=60000,'Start Here'!$B$32,0)),1) -> 9 | AM15: Small-account breakout: the idea beat the audience size; Specific number/result in the hook; Proof-first opening | AN15: Keep the result hook mechanic and swap in your own proof. Teach one marketing strategy lesson for founders of 10-50 person boutique firms (US/UK/AU). Ship it as a LinkedIn text/carousel. | AO15: A thread recounts a conversation with an entrepreneur who sold his marketing agency for $6.3M. The discussion focuses on the value of deeply trusted relationships with micro-influencers for customer acquisition, rather than traditional marketing tactics or proprietary strategies. | AP15: marketing agency, influencer relationships, micro influencers, business strategy, network effects, client acquisition, business growth, marketing insights | AQ15: client kaise laaye business grow kaise kare sales marketing agency; agency owner lessons scaling to 7 figures clients retention | AR15: Backlog
A16: 15 | B16: X | C16: English | D16: Eden | E16: Hidden Gem | F16: Yes | G16: Yes | H16: Yes | I16: Business Growth & Scale Systems | J16: Marketing Strategy, Client Acquisition, Content Marketing & Systems | K16: Michel Lieben | L16: @michlieben | M16: 13265 | N16: 10-20k | O16: 2026-04-01 | P16: https://x.com/MichLieben/status/2039432665078923529 | Q16: We offered $5,000 to whichever employee got the most engagement on LinkedIn in a single quarter. | R16: We offered $5,000 to whichever employee got the most engagement on LinkedIn in a single quarter. $2,500 for second. $1,500 for third. Plus $500 for anyone who published 20+ times. The result: 24 employees published 581 posts in 85 days. 43,000+ reactions. 28,000+ comments. 34,000+ new followers. 27 new clients signed. $153,000 in new MRR. I remember one guy from our team had less than 1,000 f | S16: Story / Anecdote | T16: None (pure value) | U16: BOFU: Proof / Case Study | V16: text | W16: story | X16: informative | Y16: 439499 | Z16: 6122 | AA16: 125 | AB16: 258 | AC16: 0.014800944 | AD16: 326.09 | AE16: =IF(AD16="","",MIN(AD16,100)) -> 100 | AF16: 100 | AG16: No | AH16: 8 | AI16: No | AJ16: No | AK16: Intl: Authority-to-Pipeline DFY | AL16: =ROUND('Start Here'!$B$29*AH16+'Start Here'!$B$30*MIN(IF(AD16="",0,AD16),50)/5+IF(M16<=30000,'Start Here'!$B$31,IF(M16<=60000,'Start Here'!$B$32,0)),1) -> 9 | AM16: Hard numbers at every step (581 posts, 85 days, 27 clients, $153K MRR). Employee-advocacy proof that content drives revenue. | AN16: For 10-50 person firms, the team is a distribution asset. Post: 'A 30-person consultancy has 30 LinkedIn accounts and uses 1'. Upsell path: team advocacy as an add-on. | AO16: A company offered tiered monetary prizes for LinkedIn engagement among employees, resulting in 581 posts, 107,000+ interactions, 34k+ new followers and $153k monthly recurring revenue. The $15k prize pool generated significant ROI. | AP16: employee incentives, linkedin engagement, social media competition, content marketing, mrr growth, organic reach, team motivation, reward program | AQ16: LinkedIn content strategy that books sales calls for B2B service businesses | AR16: Backlog
A17: 16 | B17: X | C17: English | D17: Eden | E17: Breakout | F17: Yes | G17: No | H17: Yes | I17: Freelancing & International Clients | J17: Marketing Strategy, Agency Growth, Consulting / Fractional | K17: MarketingMax.com | L17: @marketingmax | M17: 57635 | N17: 50-100k | O17: 2026-02-05 | P17: https://x.com/MarketingMax/status/2019410776201506904 | Q17: Hired a big-time marketing agency for some brand identity work | R17: Hired a big-time marketing agency for some brand identity work Paid them $250,000 They outsourced it to a smaller agency for $100,000 Who in turn outsourced it to a marketing consultant for $25,000 But that consultant outsourced my project to a US-based freelancer for $10,000 Who then outsourced it to an overseas freelancer for $2,000 The freelancer hired someone on Fiverr for $100 to finish | S17: Statement / Declarative | T17: None (pure value) | U17: TOFU: Reach / POV | V17: tweet | Y17: 192934 | Z17: 2448 | AA17: 98 | AB17: 57 | AC17: 0.01349166 | AD17: 212.85 | AE17: =IF(AD17="","",MIN(AD17,100)) -> 100 | AF17: 99.8 | AG17: No | AH17: 10 | AI17: No | AJ17: No | AK17: Intl: Authority-to-Pipeline DFY | AL17: =ROUND('Start Here'!$B$29*AH17+'Start Here'!$B$30*MIN(IF(AD17="",0,AD17),50)/5+IF(M17<=30000,'Start Here'!$B$31,IF(M17<=60000,'Start Here'!$B$32,0)),1) -> 9 | AM17: Outsourcing-chain story ($250K down to $100 on Fiverr). Funny, cynical, very shareable; sparks debate. | AN17: Reframe for your ICP: 'Why your $15K/mo agency retainer is really 2 juniors and a template'. Positions you as founder-led and transparent. Use as a TOFU reach post. | AQ17: freelancer to agency first clients Upwork pricing in dollars Hinglish | AR17: Backlog
A18: 17 | B18: Instagram | C18: Hindi | D18: vidIQ | E18: Hidden Gem | F18: Yes | G18: Yes | H18: No | I18: Agency Growth | J18: Marketing Strategy, Client Acquisition, Freelancing & International Clients | K18: itsliftmedia | L18: @itsliftmedia | M18: 6300 | N18: 5-10k | O18: Apr-Oct 2026 | P18: https://www.instagram.com/reel/DcGk3BOI4_r/ | Q18: aaj 200 | R18: Digital Agency Day 9 #BusinessGrowth #businessowner #agency #marketingagency #instagram | S18: Result / Number-Led Claim | T18: None (pure value) | U18: TOFU: Reach / POV | V18: Reel: B-roll over voiceover | W18: Education | Y18: 21900 | AD18: 106.3 | AE18: =IF(AD18="","",MIN(AD18,100)) -> 100 | AG18: No | AH18: 8 | AI18: No | AJ18: No | AK18: India: Growth & Scale Cohort | AL18: =ROUND('Start Here'!$B$29*AH18+'Start Here'!$B$30*MIN(IF(AD18="",0,AD18),50)/5+IF(M18<=30000,'Start Here'!$B$31,IF(M18<=60000,'Start Here'!$B$32,0)),1) -> 9 | AM18: Small-account breakout: the idea beat the audience size; Proof-first opening; Format: voiceover narration over b-roll montage | AN18: Keep the result hook mechanic and swap in your own proof. Teach one agency growth lesson for Indian B2B service founders (10-50 staff). Ship it as a IG reel, then repurpose to LinkedIn. | AO18: A digital entrepreneur documents the 9th day of building his agency, explaining the challenge of client communication and offering a template pack as a lead magnet. | AP18: Business & Entrepreneurship | AQ18: Client acquisition (Hindi/India); International clients (India) | AR18: Backlog
A19: 18 | B19: Instagram | C19: English | D19: Eden | E19: Breakout | F19: Yes | G19: No | H19: No | I19: Business Growth & Scale Systems | J19: Agency Growth, Marketing Strategy, High-Ticket Sales | K19: Austin Schneider | L19: @theaustinschneider | M19: 46241 | N19: 30-50k | O19: 2026-09-02 | P19: https://www.instagram.com/reel/Dcy173UgAVR/ | Q19: Follow @theaustinschneider for more | R19: Follow @theaustinschneider for more -- Hi, I'm Austin. I teach agency owners how to scale inside @agencyu.co. 7 years ago I started running my own agency. The advice out there? Grind harder, close more deals, just outwork everyone. It didn't work. I was doing $30K a month and still felt like I was drowning. So over the next few years I stopped following everyone else's playbook and built my own | S19: Statement / Declarative | T19: Follow ask | U19: TOFU: Reach / POV | V19: short_video | W19: tutorial | X19: inspirational | Y19: 85662 | Z19: 2055 | AA19: 81 | AC19: 0.02493521 | AD19: 48.12 | AE19: =IF(AD19="","",MIN(AD19,100)) -> 48.12 | AF19: 98.4 | AG19: No | AH19: 10 | AI19: No | AJ19: No | AK19: Intl: Authority-to-Pipeline DFY | AL19: =ROUND('Start Here'!$B$29*AH19+'Start Here'!$B$30*MIN(IF(AD19="",0,AD19),50)/5+IF(M19<=30000,'Start Here'!$B$31,IF(M19<=60000,'Start Here'!$B$32,0)),1) -> 8.9 | AM19: Origin story pinned as intro ('I was at $30K/mo and drowning'). Intro reels convert followers into buyers. | AN19: Record your own 60s 'If we've never met' reel: who you help, the one belief you reject, proof. Pin it on IG and feature it on LinkedIn. | AO19: Austin Schneider, an agency owner, shares his journey of building scalable systems that enabled his agency to grow from $30K to $200K+ per month. He promotes his program Agency U, which helps agency owners implement operational systems to scale without increased workload. | AP19: agency owners, business scaling, operational systems, client management, hiring systems, sales framework, lead generation, onboarding systems | AQ19: agency growth scaling service business revenue; client kaise laaye business grow kaise kare sales marketing agency | AR19: Backlog
A20: 19 | B20: X | C20: English | D20: Eden | E20: Hidden Gem | F20: Yes | G20: Yes | H20: Yes | I20: Outbound / Warm Outbound | J20: Marketing Strategy, Client Acquisition, Business Growth & Scale Systems | K20: Finn Mallery | L20: @fin465 | M20: 23968 | N20: 20-30k | O20: 2026-05-15 | P20: https://x.com/fin465/status/2055137077868814804 | Q20: talked to a bunch of current YC batch founders today | R20: talked to a bunch of current YC batch founders today The ones hitting $1m+ ARR (there are several this batch) are just ripping the same outbound playbook every time: 1. build your lead lists using tools like Origami or Clay 2. Run an auto-connect + DM sequencer on LinkedIn 3. aim for 200 connects/week. linkedin is a goldmine 4. when writing Linkedin DMs, send 2-sentences, ideally with a warm | S20: Statement / Declarative | T20: DM ask | U20: TOFU: Reach / POV | V20: text | W20: other | X20: informative | Y20: 356345 | Z20: 2994 | AA20: 76 | AB20: 129 | AC20: 0.0089772552 | AD20: 29.62 | AE20: =IF(AD20="","",MIN(AD20,100)) -> 29.62 | AF20: 94.5 | AG20: No | AH20: 10 | AI20: No | AJ20: No | AK20: Intl: Authority-to-Pipeline DFY | AL20: =ROUND('Start Here'!$B$29*AH20+'Start Here'!$B$30*MIN(IF(AD20="",0,AD20),50)/5+IF(M20<=30000,'Start Here'!$B$31,IF(M20<=60000,'Start Here'!$B$32,0)),1) -> 8.8 | AM20: Social proof by cohort (YC founders at $1M+ ARR) + numbered playbook with specifics (200 connects/week, 2-sentence DMs). | AN20: 'I looked at how 12 consultancies above $3M get new logos. 9 of them run this same 4-step warm outbound loop.' Follow with numbered steps. | AO20: A social media post by Finn Mallery details an outbound sales playbook used by Y Combinator founders who are achieving over $1M+ ARR. The playbook emphasizes LinkedIn strategies, including lead generation tools, automated connection requests, personalized DMs, frequent posting, and attention engine optimization (AEO) to consistently book demos. | AP20: linkedin marketing, b2b sales, outbound sales, lead generation, sales strategy, social selling, startup growth, demo booking | AQ20: LinkedIn DM outreach scripts and warm prospecting signals | AR20: Backlog
A21: 20 | B21: Instagram | C21: English | D21: Eden | E21: Hidden Gem | F21: Yes | G21: Yes | H21: No | I21: Business Growth & Scale Systems | J21: Marketing Strategy, High-Ticket Sales, Content Marketing & Systems | K21: Jhevanie Ong -Online Marketing | L21: @vanieclicks | M21: 25551 | N21: 20-30k | O21: 2026-05-08 | P21: https://www.instagram.com/reel/DYE9F6qN8uX/ | Q21: 🔹 1. High-Ticket Affiliate Marketing (with AI) | R21: 🔹 1. High-Ticket Affiliate Marketing (with AI) This is the leverage play. Instead of creating your own product, you: * Promote existing digital products ($2K–$10K) * Earn $1K–$5K per sale * Use AI to create content (Reels, captions, hooks) 🔹 2. Amazon KDP • Create low-content books (journals, planners, puzzle books, kids books, cookbooks, etc.) using Canva or Bookbolt. * List them on Amazo | S21: Statement / Declarative | T21: None (pure value) | U21: TOFU: Reach / POV | V21: short_video | W21: tutorial | X21: informative | Y21: 255802 | Z21: 2400 | AA21: 1388 | AC21: 0.014808328 | AD21: 284.56 | AE21: =IF(AD21="","",MIN(AD21,100)) -> 100 | AF21: 99.2 | AG21: No | AH21: 7.5 | AI21: No | AJ21: Yes | AK21: Low fit (aspirant/beginner audience) | AL21: =ROUND('Start Here'!$B$29*AH21+'Start Here'!$B$30*MIN(IF(AD21="",0,AD21),50)/5+IF(M21<=30000,'Start Here'!$B$31,IF(M21<=60000,'Start Here'!$B$32,0)),1) -> 8.8 | AM21: High comment-to-like ratio: debate driver | AN21: Keep the statement hook mechanic and swap in your own proof. Teach one business growth & scale systems lesson for (re-aim at business owners, not aspirants). Ship it as a IG reel, then repurpose to LinkedIn. | AO21: A short video promotes three digital monetization methods for 2026: high-ticket affiliate marketing with AI, Amazon KDP low-content books, and faceless content monetization on social media. The video encourages viewers to use existing systems instead of extra time to generate income. | AP21: affiliate marketing, ai content, amazon kdp, faceless content, digital products, monetization, short-form video, online business | AQ21: content system that generates inbound leads for B2B founders | AR21: Backlog
A22: 21 | B22: X | C22: English | D22: Eden | E22: Hidden Gem | F22: Yes | G22: Yes | H22: Yes | I22: Agency Growth | J22: Marketing Strategy, Content Marketing & Systems, Client Acquisition | K22: Bryan Ng | L22: @boomerrbryan | M22: 29478 | N22: 20-30k | O22: 2026-10-02 | P22: https://x.com/boomerrbryan/status/2105927263208570959 | Q22: I'm BEGGING you to look up what YouTube pays per 1,000 views in different niches before you pick what to make videos about | R22: I'm BEGGING you to look up what YouTube pays per 1,000 views in different niches before you pick what to make videos about This is the single most important number in the entire YouTube business model and almost nobody checks it before starting Entertainment: $2-4 Gaming: $3-5 Vlogs: $4-6 Reactions: $3-5 Now look at the niches nobody wants: Medicare supplements: $44 Estate planning: $38 Commer | S22: Story / Anecdote | T22: None (pure value) | U22: TOFU: Reach / POV | V22: text | W22: other | X22: informative | Y22: 238329 | Z22: 3231 | AA22: 98 | AB22: 285 | AC22: 0.015163912 | AD22: 178.66 | AE22: =IF(AD22="","",MIN(AD22,100)) -> 100 | AF22: 99.8 | AG22: No | AH22: 7.5 | AI22: No | AJ22: Yes | AK22: Low fit (aspirant/beginner audience) | AL22: =ROUND('Start Here'!$B$29*AH22+'Start Here'!$B$30*MIN(IF(AD22="",0,AD22),50)/5+IF(M22<=30000,'Start Here'!$B$31,IF(M22<=60000,'Start Here'!$B$32,0)),1) -> 8.8 | AM22: First-person or observed story: narrative pull | AN22: Keep the story hook mechanic and swap in your own proof. Teach one agency growth lesson for (re-aim at business owners, not aspirants). Ship it as a LinkedIn text/carousel. | AO22: Text thread arguing creators should choose high-CPM, low-competition YouTube niches like Medicare supplements, estate planning and HVAC, citing platform payouts per 1,000 views and inbound lead value, plus a three-step method for finding such niches with Google Keyword Planner. | AP22: youtube, cpm, niche selection, monetization, high cpm niches, youtube business model, lead generation, keyword planner | AQ22: client kaise laaye business grow kaise kare sales marketing agency | AR22: Backlog
A23: 22 | B23: X | C23: English | D23: Eden | E23: Hidden Gem | F23: Yes | G23: Yes | H23: No | I23: Outbound / Warm Outbound | J23: Agency Growth, Marketing Strategy, High-Ticket Sales | K23: ecomchigga | L23: @ecomchigga | M23: 12398 | N23: 10-20k | O23: 2026-01-21 | P23: https://x.com/ecomchigga/status/2014040307755528491 | Q23: nobody's going to tell you this so i will | R23: nobody's going to tell you this so i will the digital product game is rigged in your favor if you know where to look here's everything that's actually working right now: THE NICHES THAT ARE PRINTING ai onlyfans management - teaching people to run OF accounts with ai generated models. guys clearing $30-50K/month. market is 18 months old. basically zero competition. ai ugc - brands need content | S23: Contrarian / Myth-Bust | T23: None (pure value) | U23: TOFU: Reach / POV | V23: text | W23: tutorial | X23: informative | Y23: 44506 | Z23: 750 | AA23: 13 | AB23: 68 | AC23: 0.01867164 | AD23: 101.25 | AE23: =IF(AD23="","",MIN(AD23,100)) -> 100 | AF23: 97.3 | AG23: No | AH23: 7.5 | AI23: No | AJ23: Yes | AK23: Low fit (aspirant/beginner audience) | AL23: =ROUND('Start Here'!$B$29*AH23+'Start Here'!$B$30*MIN(IF(AD23="",0,AD23),50)/5+IF(M23<=30000,'Start Here'!$B$31,IF(M23<=60000,'Start Here'!$B$32,0)),1) -> 8.8 | AM23: Small-account breakout: the idea beat the audience size; Challenges a belief the ICP holds | AN23: Keep the contrarian hook mechanic and swap in your own proof. Teach one outbound / warm outbound lesson for (re-aim at business owners, not aspirants). Ship it as a LinkedIn text/carousel. | AO23: Thread breaks down successful digital product creation including profitable niches, pricing tiers, content strategy (40% problem content, 30% proof, 20% mechanism), bio optimization, engagement tactics and timeline expectations. Also details platform math and DM outreach conversion tactics. | AP23: digital products, side hustle, ecommerce, niche business, product creation, marketing, income, business growth | AQ23: LinkedIn DM outreach scripts and warm prospecting signals | AR23: Backlog
A24: 23 | B24: LinkedIn | C24: English | D24: Eden | E24: Hidden Gem | F24: Yes | G24: Yes | H24: No | I24: Business Growth & Scale Systems | J24: Agency Growth, Marketing Strategy | K24: Nick Avaria | L24: @nickavaria | M24: 18671 | N24: 10-20k | O24: 2026-01-26 | P24: https://www.linkedin.com/feed/update/urn:li:activity:7421567657579196416 | Q24: I scaled my agency to $10M in 3.5 years. | R24: I scaled my agency to $10M in 3.5 years. My secret? This 1 dashboard that's currently runs over 50M+ through it. Get it free today: This is the same dashboard we install inside agencies to give founders visibility into: - Margin - Client retention - Utilization - Forecasting - Revenue per employee - CAC and payback - MRR movement - Team load vs. delivery capacity If you’re an agency owner doin | S24: Story / Anecdote | T24: None (pure value) | U24: BOFU: Proof / Case Study | V24: post | Z24: 546 | AA24: 906 | AB24: 0 | AC24: 0.080176698 | AD24: 111.49 | AE24: =IF(AD24="","",MIN(AD24,100)) -> 100 | AF24: 99.5 | AG24: No | AH24: 7 | AI24: No | AJ24: No | AK24: Intl: Authority-to-Pipeline DFY | AL24: =ROUND('Start Here'!$B$29*AH24+'Start Here'!$B$30*MIN(IF(AD24="",0,AD24),50)/5+IF(M24<=30000,'Start Here'!$B$31,IF(M24<=60000,'Start Here'!$B$32,0)),1) -> 8.5 | AM24: Same creator, same asset, 111x: proves repetition of a winning lead-magnet post works. He reposted the dashboard offer 4+ times with new hooks. | AN24: Rule: when a lead-magnet post hits, re-run it every 3-4 weeks with a new hook. Track in Calendar sheet. | AQ24: client acquisition for agencies and consultants | AR24: Backlog
A25: 24 | B25: Instagram | C25: English | D25: Eden | E25: Breakout | F25: Yes | G25: No | H25: Yes | I25: Outbound / Warm Outbound | J25: High-Ticket Sales, Consulting / Fractional, Client Acquisition | K25: Dylan Smith | L25: @dylansmith.io | M25: 31371 | N25: 30-50k | O25: 2026-10-07 | P25: https://www.instagram.com/reel/DeNIahOMks5/ | Q25: This one actually works | R25: This one actually works #sales #coldcalling #salestips #salescoaching | S25: Statement / Declarative | T25: None (pure value) | U25: TOFU: Reach / POV | V25: short_video | W25: skit | X25: comedic | Y25: 842374 | Z25: 24474 | AA25: 294 | AC25: 0.029402617 | AD25: 81.9 | AE25: =IF(AD25="","",MIN(AD25,100)) -> 81.9 | AF25: 100 | AG25: No | AH25: 9 | AI25: No | AJ25: No | AK25: Intl: Authority-to-Pipeline DFY | AL25: =ROUND('Start Here'!$B$29*AH25+'Start Here'!$B$30*MIN(IF(AD25="",0,AD25),50)/5+IF(M25<=30000,'Start Here'!$B$31,IF(M25<=60000,'Start Here'!$B$32,0)),1) -> 8.5 | AM25: Topic resonance (check the full post) | AN25: Keep the statement hook mechanic and swap in your own proof. Teach one outbound / warm outbound lesson for founders of 10-50 person boutique firms (US/UK/AU). Ship it as a IG reel, then repurpose to LinkedIn. | AO25: Comedic sales skit: a salesperson uses his "one phone call" from the Crawford County Jail to follow up with prospect Gary and ask whether he's ready to move forward on the deal this week. | AP25: cold calling, sales humor, sales tips, sales coaching, cold outbound, skit, follow up, closing the deal | AQ25: high ticket sales calls closing B2B deals | AR25: Backlog
A26: 25 | B26: X | C26: English | D26: Eden | E26: Hidden Gem | F26: Yes | G26: Yes | H26: Yes | I26: Freelancing & International Clients | J26: Consulting / Fractional, Client Acquisition, Business Growth & Scale Systems | K26: Harshil Tomar | L26: @hartdrawss | M26: 22067 | N26: 20-30k | O26: 2026-03-06 | P26: https://x.com/Hartdrawss/status/2029852118723551289 | Q26: This is the TOXIC Indian freelance industry | R26: This is the TOXIC Indian freelance industry got a legal notice today. Rs. 10,00,000 penalty for "non-compliance" here's the full story: - signed a ₹X L ERP project - delivered 100% of agreed scope - they kept adding features saying "this was discussed day 1" - i absorbed it, built 40% extra out of goodwill - 6 months of over-delivering - still got a legal notice the Indian market has a specifi | S26: Statement / Declarative | T26: None (pure value) | U26: TOFU: Reach / POV | V26: image | W26: other | X26: critical | Y26: 1571865 | Z26: 4810 | AA26: 386 | AB26: 483 | AC26: 0.0036129057 | AD26: 221.1 | AE26: =IF(AD26="","",MIN(AD26,100)) -> 100 | AF26: 100 | AG26: No | AH26: 7 | AI26: No | AJ26: No | AK26: India: Growth & Scale Cohort | AL26: =ROUND('Start Here'!$B$29*AH26+'Start Here'!$B$30*MIN(IF(AD26="",0,AD26),50)/5+IF(M26<=30000,'Start Here'!$B$31,IF(M26<=60000,'Start Here'!$B$32,0)),1) -> 8.5 | AM26: Pain + outrage + India specificity (₹10L legal notice, scope creep). Controversy about the Indian market travels. | AN26: India cohort angle: 'Why Indian service firms lose money on Indian clients and how to price for US/UK clients instead'. Bridges to international client hunting. | AO26: The image shows a legal notice demanding a 10 Lakh Rupee penalty, illustrating a freelancers dispute over project scope and client management challenges in the Indian freelance market. | AP26: freelance industry, legal notice, penalty, client management, project scope, indian market, dispute, non-compliance | AQ26: freelancer to agency first clients Upwork pricing in dollars Hinglish | AR26: Backlog
A27: 26 | B27: Instagram | C27: English | D27: vidIQ | E27: Breakout | F27: Yes | G27: No | H27: No | I27: Marketing Strategy | J27: Outbound / Warm Outbound, Client Acquisition, Agency Growth | K27: officialpeterroth | L27: @officialpeterroth | M27: 52200 | N27: 50-100k | O27: Apr-Oct 2026 | P27: https://www.instagram.com/reel/Db58c4nCOXN/ | Q27: THE COLD EMAIL STRATEGY THAT ACTUALLY WORKS | R27: The cold email strategy that actually works ft. @thejasonwojo If you're tired of chasing bad leads... | S27: Statement / Declarative | T27: None (pure value) | U27: TOFU: Reach / POV | V27: Reel: Split screen (creator + screen recording/B-roll) | W27: Education | Y27: 83700 | AD27: 190.6 | AE27: =IF(AD27="","",MIN(AD27,100)) -> 100 | AG27: No | AH27: 9 | AI27: No | AJ27: No | AK27: Intl: Authority-to-Pipeline DFY | AL27: =ROUND('Start Here'!$B$29*AH27+'Start Here'!$B$30*MIN(IF(AD27="",0,AD27),50)/5+IF(M27<=30000,'Start Here'!$B$31,IF(M27<=60000,'Start Here'!$B$32,0)),1) -> 8.5 | AM27: Split-screen software walkthrough + interview guest. 190x median; 'actually works' promise plus proof on screen. | AN27: Screen-record your warm-outbound stack (signal, then enrich, then DM) with a guest client. Use a split-screen format. | AO27: A founder explains his cold email strategy and specific software stack for lead generation and conversion. | AP27: Business & Marketing | AQ27: Client acquisition (EN); Content systems; Agency growth; B2B marketing | AR27: Backlog
A28: 27 | B28: Instagram | C28: English | D28: vidIQ | E28: Hidden Gem | F28: Yes | G28: Yes | H28: No | I28: Marketing Strategy | J28: Client Acquisition, Outbound / Warm Outbound, Business Growth & Scale Systems | K28: calebchae | L28: @calebchae | M28: 15800 | N28: 10-20k | O28: Apr-Oct 2026 | P28: https://www.instagram.com/reel/Db8S4BmJlfM/ | Q28: SERVICE BASED BUSINESS OWNERS RUNNING META ADS | R28: Comment “phone” below for outbound phone setting system | S28: Audience Callout | T28: Comment keyword → DM | U28: Lead Capture (MOFU) | V28: Reel: Split screen reaction transitioning into solo talking head | W28: Education | Y28: 233900 | AD28: 335.5 | AE28: =IF(AD28="","",MIN(AD28,100)) -> 100 | AG28: No | AH28: 7 | AI28: No | AJ28: No | AK28: Intl: Authority-to-Pipeline DFY | AL28: =ROUND('Start Here'!$B$29*AH28+'Start Here'!$B$30*MIN(IF(AD28="",0,AD28),50)/5+IF(M28<=30000,'Start Here'!$B$31,IF(M28<=60000,'Start Here'!$B$32,0)),1) -> 8.5 | AM28: Small-account breakout: the idea beat the audience size; Calls out the exact audience in line 1; Keyword CTA converts reach into DMs; Format: expert reaction and commentary | AN28: Keep the audience callout hook mechanic and swap in your own proof. Teach one marketing strategy lesson for founders of 10-50 person boutique firms (US/UK/AU). Ship it as a IG reel, then repurpose to LinkedIn. | AO28: A creator validates advice from an industry expert about lead calling and offers a lead magnet in exchange for comments. | AP28: Business & Marketing | AQ28: Content systems | AR28: Backlog
A29: 28 | B29: X | C29: English | D29: Eden | E29: Breakout | F29: Yes | G29: No | H29: No | I29: Marketing Strategy | J29: Business Growth & Scale Systems, Agency Growth, High-Ticket Sales | K29: Tim Stoddart | L29: @timstodz | M29: 36531 | N29: 30-50k | O29: 2026-10-08 | P29: https://x.com/TimStodz/status/2108161648506609947 | Q29: The most reliable path to business success: | R29: The most reliable path to business success: - Build a B2B service offer - Sell it for cheap or free - Get proof that you’re good - Raise prices to $4k-20k a month - Do a ton of marketing - Hit your limit on clients - Scale into an agency Not easy, but it’s the easiest. | S29: Statement / Declarative | T29: None (pure value) | U29: TOFU: Reach / POV | V29: text | W29: other | X29: informative | Y29: 14826 | Z29: 374 | AA29: 35 | AB29: 16 | AC29: 0.028665857 | AD29: 41.49 | AE29: =IF(AD29="","",MIN(AD29,100)) -> 41.49 | AF29: 98.9 | AG29: No | AH29: 10 | AI29: No | AJ29: No | AK29: Intl: Authority-to-Pipeline DFY | AL29: =ROUND('Start Here'!$B$29*AH29+'Start Here'!$B$30*MIN(IF(AD29="",0,AD29),50)/5+IF(M29<=30000,'Start Here'!$B$31,IF(M29<=60000,'Start Here'!$B$32,0)),1) -> 8.5 | AM29: A 7-step 'easiest path' list in under 280 chars. Clear, sequential, mildly contrarian ('not easy, but easiest'). | AN29: 'The most reliable path from $1M to $5M for a consultancy:' as 7 short lines. Make this your signature thesis post and repost quarterly. | AO29: Tim Stoddart outlines a step-by-step path to business success: build a B2B service offer, sell cheaply or free to gain proof, raise prices to $4k–20k/month, market heavily, cap out on clients, then scale into an agency. | AP29: b2b services, agency growth, pricing, consulting, client acquisition, scaling, marketing, proof of concept | AQ29: "fractional" CMO CFO COO getting clients | AR29: Backlog
A30: 29 | B30: X | C30: English | D30: Eden | E30: Hidden Gem | F30: Yes | G30: Yes | H30: No | I30: Content Marketing & Systems | J30: Marketing Strategy, Business Growth & Scale Systems, High-Ticket Sales | K30: Singh | L30: @imsehej | M30: 6256 | N30: 5-10k | O30: 2026-01-04 | P30: https://x.com/imsehej/status/2007850577326456879 | Q30: just signed a female creator as a client on IG & closed $30k in info sales on the first day of launch 😂 | R30: just signed a female creator as a client on IG & closed $30k in info sales on the first day of launch 😂 and before anyone asks "what's her niche" or "how big is her audience" those are the wrong fucking questions here's what actually happened and why this works she had 8k followers on instagram decent engagement but making $0 from her content been posting for 8 months, people loved her cont | S30: Story / Anecdote | T30: None (pure value) | U30: BOFU: Proof / Case Study | V30: text | W30: tutorial | X30: informative | Y30: 42190 | Z30: 438 | AA30: 40 | AB30: 23 | AC30: 0.011874852 | AD30: 24.55 | AE30: =IF(AD30="","",MIN(AD30,100)) -> 24.55 | AF30: 99.5 | AG30: No | AH30: 10 | AI30: No | AJ30: No | AK30: Intl: Authority-to-Pipeline DFY | AL30: =ROUND('Start Here'!$B$29*AH30+'Start Here'!$B$30*MIN(IF(AD30="",0,AD30),50)/5+IF(M30<=30000,'Start Here'!$B$31,IF(M30<=60000,'Start Here'!$B$32,0)),1) -> 8.5 | AM30: Small-account breakout: the idea beat the audience size; Specific number/result in the hook; First-person or observed story: narrative pull | AN30: Keep the story hook mechanic and swap in your own proof. Teach one content marketing & systems lesson for founders of 10-50 person boutique firms (US/UK/AU). Ship it as a LinkedIn text/carousel. | AO30: A text post details a step-by-step system used to monetize a female creator's Instagram audience, resulting in $30k in sales on launch day. The post explains the process including defining a specific offer, pre-selling via strategic content, qualification in DMs, pricing strategy, and manufactured urgency. | AP30: monetization strategy, instagram launch, sales funnel, product launch, audience monetization, content marketing, dm sales, pricing strategy | AQ30: premium pricing offer positioning charge more consulting retainer | AR30: Backlog
A31: 30 | B31: X | C31: English | D31: Eden | E31: Hidden Gem | F31: Yes | G31: Yes | H31: No | I31: Agency Growth | J31: Freelancing & International Clients, Client Acquisition, High-Ticket Sales | K31: Rob O'Rourke | L31: @theroborourke | M31: 10660 | N31: 10-20k | O31: 2025-12-15 | P31: https://x.com/theroborourke/status/2000523290205364430 | Q31: Recently started working with an India-based design agency doing $20-50K/month. | R31: Recently started working with an India-based design agency doing $20-50K/month. Strong portfolio. Top rated on Fiverr and Upwork. I asked them: what pain do you actually solve for clients? They listed reliability, fast turnaround, experienced designers, structured process. All good things, but here's the problem - none of that is why someone hires you in the first place. All of that matters | S31: Story / Anecdote | T31: None (pure value) | U31: TOFU: Reach / POV | V31: text | W31: tutorial | X31: educational | Y31: 438978 | Z31: 1316 | AA31: 29 | AB31: 100 | AC31: 0.0032917367 | AD31: 40.65 | AE31: =IF(AD31="","",MIN(AD31,100)) -> 40.65 | AF31: 99.5 | AG31: No | AH31: 8 | AI31: No | AJ31: No | AK31: India: Growth & Scale Cohort | AL31: =ROUND('Start Here'!$B$29*AH31+'Start Here'!$B$30*MIN(IF(AD31="",0,AD31),50)/5+IF(M31<=30000,'Start Here'!$B$31,IF(M31<=60000,'Start Here'!$B$32,0)),1) -> 8.4 | AM31: Client-diagnosis story: names a specific firm type (India-based design agency, $20-50K/mo), asks one sharp question, exposes that 'reliability, fast turnaround' are table stakes, not reasons to buy. The reader self-identifies instantly. | AN31: Your #1 bridge post. 'An Indian IT services firm doing $80K/mo asked me why US prospects ghost them. I asked: what expensive problem do you solve? They listed...'. Ends with the pain-led positioning rewrite. Works for BOTH offers. | AO31: An agency owner criticizes the common approach of presenting reliability and fast turnaround to prospective clients, arguing that these features only support closing sales once demand already exists. He demonstrates an alternative strategy of addressing the underlying business problems of customers before they know they require design solutions. | AP31: agency, marketing, clients, solutions, approach, niche, content, advertisement | AQ31: client acquisition for agencies and consultants | AR31: Backlog
A32: 31 | B32: X | C32: English | D32: Eden | E32: Hidden Gem | F32: Yes | G32: Yes | H32: Yes | I32: Business Growth & Scale Systems | J32: Marketing Strategy, High-Ticket Sales, Agency Growth | K32: Rob O'Rourke | L32: @theroborourke | M32: 10660 | N32: 10-20k | O32: 2025-11-02 | P32: https://x.com/theroborourke/status/1984891228635255217 | Q32: $93k in Oct. | R32: $93k in Oct. And probably my last revenue screen share for a while. Pretty proud of this figure. Started this year with a few specific business goals: - Start a new sales funnel business - Do all sales calls, content, and funnels myself - No launches / discounts / deals / webinars - Sell the exact same way I teach others to sell I also run the business fully myself with just one full time sta | S32: Result / Number-Led Claim | T32: None (pure value) | U32: BOFU: Proof / Case Study | V32: image | W32: story | X32: inspirational | Y32: 1160978 | Z32: 1030 | AA32: 51 | AB32: 43 | AC32: 0.00096814927 | AD32: 31.82 | AE32: =IF(AD32="","",MIN(AD32,100)) -> 31.82 | AF32: 99.2 | AG32: No | AH32: 9 | AI32: No | AJ32: No | AK32: Intl: Authority-to-Pipeline DFY | AL32: =ROUND('Start Here'!$B$29*AH32+'Start Here'!$B$30*MIN(IF(AD32="",0,AD32),50)/5+IF(M32<=30000,'Start Here'!$B$31,IF(M32<=60000,'Start Here'!$B$32,0)),1) -> 8.4 | AM32: Revenue screenshot + constraints (no launches, no discounts, 1 staff). Shows you practice what you preach. | AN32: Monthly 'building in public' revenue/pipeline report: calls booked, source split (content vs outbound), close rate. Builds trust with both ICPs. | AO32: The visual shows a line chart depicting a user's monthly total profit over ten months, with an increasing trend. The accompanying text shares the user's pride in achieving $93k revenue in October and details personal business systems and goals. | AP32: revenue, cash flow, business goals, profit, sales funnel, self-run business, agency model, personal achievement | AQ32: freelancer to agency first clients Upwork pricing in dollars Hinglish | AR32: Backlog
A33: 32 | B33: Instagram | C33: English | D33: Eden | E33: Hidden Gem | F33: Yes | G33: Yes | H33: No | I33: High-Ticket Sales | J33: Consulting / Fractional, Client Acquisition, Content Marketing & Systems | K33: Vincent Hu | L33: @iamvincenthu | M33: 7538 | N33: 5-10k | O33: 2026-03-24 | P33: https://www.instagram.com/reel/DWQxe0VjcyN/ | Q33: Follow @iamvincenthu + Comment 'Traffic' and I'll send you the video :D | R33: Follow @iamvincenthu + Comment 'Traffic' and I'll send you the video :D | S33: Comment-Gate / Lead Magnet | T33: Comment keyword → DM | U33: Lead Capture (MOFU) | V33: long_video | W33: tutorial | X33: educational | Y33: 29264 | Z33: 218 | AA33: 15 | AC33: 0.0079620011 | AD33: 22.64 | AE33: =IF(AD33="","",MIN(AD33,100)) -> 22.64 | AF33: 86.6 | AG33: No | AH33: 10 | AI33: No | AJ33: No | AK33: Intl: Authority-to-Pipeline DFY | AL33: =ROUND('Start Here'!$B$29*AH33+'Start Here'!$B$30*MIN(IF(AD33="",0,AD33),50)/5+IF(M33<=30000,'Start Here'!$B$31,IF(M33<=60000,'Start Here'!$B$32,0)),1) -> 8.4 | AM33: Small-account breakout: the idea beat the audience size; Comment-gate inflates comments, which the algorithm rewards | AN33: Keep the comment-gate hook mechanic and swap in your own proof. Teach one high-ticket sales lesson for founders of 10-50 person boutique firms (US/UK/AU). Ship it as a IG reel, then repurpose to LinkedIn. | AO33: Vincent Hu's video discusses building a profitable consulting business by sharing a 3-step framework he used to earn 100k in one month. He covers how to serve clients without direct sales, how to convert leads, and how to close deals without objections, aiming to help viewers build a 50k/month, ethical service business. | AP33: consulting, client acquisition, lead conversion, coaching, business growth, high-ticket sales, consultant, video series | AQ33: client acquisition for agencies and consultants | AR33: Backlog
A34: 33 | B34: Instagram | C34: English | D34: Eden | E34: Hidden Gem | F34: Yes | G34: Yes | H34: No | I34: Agency Growth | J34: Marketing Strategy, Outbound / Warm Outbound, Client Acquisition | K34: Zach Chang | L34: @zchangd | M34: 25875 | N34: 20-30k | O34: 2026-06-16 | P34: https://www.instagram.com/reel/DZpxfcdhO3g/ | Q34: 1. Ditches are in the niches | R34: 1. Ditches are in the niches 2. Offer flexible tiered retainers 3. Document everything 4. Don’t be a tech nerd 5. Most AI influencers don’t actually know much more about AI than you they’re just better at marketing 6. Organic content amplifies cold outreach 7. Invest money to grow your network 8. Understand b2b sales cycles 9. Sell the outcome not the product 10. Do not become an expert in any one | S34: Statement / Declarative | T34: None (pure value) | U34: TOFU: Reach / POV | V34: short_video | W34: tutorial | X34: informative | Y34: 153496 | Z34: 6621 | AA34: 104 | AC34: 0.043812217 | AD34: 20.12 | AE34: =IF(AD34="","",MIN(AD34,100)) -> 20.12 | AF34: 94.6 | AG34: No | AH34: 10 | AI34: No | AJ34: No | AK34: Intl: Authority-to-Pipeline DFY | AL34: =ROUND('Start Here'!$B$29*AH34+'Start Here'!$B$30*MIN(IF(AD34="",0,AD34),50)/5+IF(M34<=30000,'Start Here'!$B$31,IF(M34<=60000,'Start Here'!$B$32,0)),1) -> 8.2 | AM34: Dense 10-point list ('1 year of advice in 52 seconds'). Includes 'organic content amplifies cold outreach', which is literally your thesis. | AN34: '10 things I'd tell a $2M consultancy founder about pipeline' reel with on-screen numbering. Pull lines from your discovery calls. | AO34: A video presenting 27 concise business advice tips for agency professionals, covering niches, pricing strategies, client acquisition, AI integration, and personal branding. | AP34: agency, business advice, pricing strategy, client acquisition, ai integration, personal branding, sales tips, networking | AQ34: client kaise laaye business grow kaise kare sales marketing agency | AR34: Backlog
A35: 34 | B35: Instagram | C35: English | D35: vidIQ | E35: Hidden Gem | F35: Yes | G35: Yes | H35: No | I35: Client Acquisition | J35: Marketing Strategy, Content Marketing & Systems | K35: coltonhavens6 | L35: @coltonhavens6 | M35: 20800 | N35: 20-30k | O35: Apr-Oct 2026 | P35: https://www.instagram.com/reel/Dbl6NsgSR9R/ | Q35: Claude Is Posting 20x A Day For Me | R35: How To Use ai to get leads. #howtouseaitogetleads. | S35: Result / Number-Led Claim | T35: None (pure value) | U35: TOFU: Reach / POV | V35: Reel: split screen (creator + screen recording) | W35: Education | Y35: 84500 | AD35: 140.1 | AE35: =IF(AD35="","",MIN(AD35,100)) -> 100 | AG35: No | AH35: 6.3 | AI35: No | AJ35: No | AK35: Intl: Authority-to-Pipeline DFY | AL35: =ROUND('Start Here'!$B$29*AH35+'Start Here'!$B$30*MIN(IF(AD35="",0,AD35),50)/5+IF(M35<=30000,'Start Here'!$B$31,IF(M35<=60000,'Start Here'!$B$32,0)),1) -> 8.2 | AM35: Specific number/result in the hook; Proof-first opening; Format: screen recording with talking head | AN35: Keep the result hook mechanic and swap in your own proof. Teach one client acquisition lesson for founders of 10-50 person boutique firms (US/UK/AU). Ship it as a IG reel, then repurpose to LinkedIn. | AO35: A creator explains how he uses AI to automate his social media content generation and lead acquisition. | AP35: Business & Entrepreneurship | AQ35: Client acquisition (EN); Agency growth; B2B marketing | AR35: Backlog
A36: 35 | B36: X | C36: English | D36: Eden | E36: Hidden Gem | F36: Yes | G36: Yes | H36: Yes | I36: Marketing Strategy | J36: Content Marketing & Systems, Freelancing & International Clients, Outbound / Warm Outbound | K36: Marlow | L36: @marlowxbt | M36: 12481 | N36: 10-20k | O36: 2026-05-26 | P36: https://x.com/marlowxbt/status/2059288973101486502 | Q36: A 26 year old freelancer in Phoenix sends cold emails to brands every Monday morning. She offers UGC content. Last month she billed $17,000. The month before, $17,000. 9 straight months. Same number. Her TikTok has 412 f | R36: A 26 year old freelancer in Phoenix sends cold emails to brands every Monday morning. She offers UGC content. Last month she billed $17,000. The month before, $17,000. 9 straight months. Same number. Her TikTok has 412 followers. Her Instagram has 89. She has never gone viral and has never signed with an agent. Most UGC creators pitch the same thing. TikTok video. Instagram reel. Maybe a YouTube | S36: Result / Number-Led Claim | T36: None (pure value) | U36: TOFU: Reach / POV | V36: long_video | W36: tutorial | X36: educational | Y36: 633107 | Z36: 1000 | AA36: 36 | AB36: 73 | AC36: 0.0017516786 | AD36: 51.09 | AE36: =IF(AD36="","",MIN(AD36,100)) -> 51.09 | AF36: 92.2 | AG36: No | AH36: 6.1 | AI36: Yes | AJ36: Yes | AK36: Low fit (aspirant/beginner audience) | AL36: =ROUND('Start Here'!$B$29*AH36+'Start Here'!$B$30*MIN(IF(AD36="",0,AD36),50)/5+IF(M36<=30000,'Start Here'!$B$31,IF(M36<=60000,'Start Here'!$B$32,0)),1) -> 8.1 | AM36: Small-account breakout: the idea beat the audience size; Specific number/result in the hook; Proof-first opening | AN36: Keep the result hook mechanic and swap in your own proof. Teach one marketing strategy lesson for (re-aim at business owners, not aspirants). Ship it as a LinkedIn text/carousel. | AO36: A long-form video tutorial demonstrates a step-by-step process for building AI-generated UGC content, including setting up prompts, using image generation tools, and creating realistic visuals for brand pitches. | AP36: ugc creation, ai tools, prompt engineering, brand pitching, image generation, content strategy, freelancing, tutorial | AQ36: cold email outbound that books meetings for consultants | AR36: Backlog
A37: 36 | B37: LinkedIn | C37: English | D37: Eden | E37: Hidden Gem | F37: Yes | G37: Yes | H37: Yes | I37: Marketing Strategy | J37: High-Ticket Sales, Agency Growth, Business Growth & Scale Systems | K37: Manuel Arrufat | L37: @manuel-arrufat | M37: 12673 | N37: 10-20k | O37: 2025-10-20 | P37: https://www.linkedin.com/feed/update/urn:li:activity:7385915021148438528 | Q37: I’ve analyzed 100+ Google Ads accounts. | R37: I’ve analyzed 100+ Google Ads accounts. 99% of “7× ROAS” claims are misleading. Here’s why: ● Brand traffic inflates results. ● PMax hides real query data. ● Agencies report blended ROAS. ● Search terms stay undisclosed. ● Non-brand performance stays invisible. ❌ You think you’re scaling. ✅ You’re just retargeting loyal customers. Here’s what top 1% advertisers do differently: 1. Separate br | S37: Result / Number-Led Claim | T37: None (pure value) | U37: BOFU: Proof / Case Study | V37: post | Z37: 1396 | AA37: 65 | AB37: 97 | AC37: 0.12293853 | AD37: 58.17 | AE37: =IF(AD37="","",MIN(AD37,100)) -> 58.17 | AF37: 99.6 | AG37: No | AH37: 6 | AI37: No | AJ37: No | AK37: Intl: Authority-to-Pipeline DFY | AL37: =ROUND('Start Here'!$B$29*AH37+'Start Here'!$B$30*MIN(IF(AD37="",0,AD37),50)/5+IF(M37<=30000,'Start Here'!$B$31,IF(M37<=60000,'Start Here'!$B$32,0)),1) -> 8 | AM37: Small-account breakout: the idea beat the audience size; Proof-first opening | AN37: Keep the result hook mechanic and swap in your own proof. Teach one marketing strategy lesson for founders of 10-50 person boutique firms (US/UK/AU). Ship it as a LinkedIn text/carousel. | AQ37: agency growth scaling service business revenue | AR37: Backlog
A38: 37 | B38: X | C38: English | D38: Eden | E38: Breakout | F38: Yes | G38: No | H38: Yes | I38: Marketing Strategy | J38: Client Acquisition, Outbound / Warm Outbound, Consulting / Fractional | K38: Financial Physics | L38: @financialphys | M38: 87931 | N38: 50-100k | O38: 2026-07-22 | P38: https://x.com/FinancialPhys/status/2079933243650982238 | Q38: I’m seeing more of this, and being offered these kinds of lead services (we turn them down for this exact reason) | R38: I’m seeing more of this, and being offered these kinds of lead services (we turn them down for this exact reason) Get referrals https://t.co/EF20VyyrWw | S38: Statement / Declarative | T38: Link / Register | U38: TOFU: Reach / POV | V38: long_video | W38: other | X38: critical | Y38: 177170 | Z38: 8809 | AA38: 307 | AB38: 830 | AC38: 0.056138172 | AD38: 105.19 | AE38: =IF(AD38="","",MIN(AD38,100)) -> 100 | AF38: 99.3 | AG38: No | AH38: 10 | AI38: No | AJ38: No | AK38: Intl: Authority-to-Pipeline DFY | AL38: =ROUND('Start Here'!$B$29*AH38+'Start Here'!$B$30*MIN(IF(AD38="",0,AD38),50)/5+IF(M38<=30000,'Start Here'!$B$31,IF(M38<=60000,'Start Here'!$B$32,0)),1) -> 8 | AM38: Topic resonance (check the full post) | AN38: Keep the statement hook mechanic and swap in your own proof. Teach one marketing strategy lesson for founders of 10-50 person boutique firms (US/UK/AU). Ship it as a LinkedIn text/carousel. | AO38: The video features a financial consultant discussing a recent increase in referral lead services they have started rejecting. Text on screen reads: I’m seeing more of this, and being offered these kinds of lead services (we turn them down for this exact reason) | AP38: lead services, referrals, business rejection, service consultation, business advice, marketing | AQ38: referrals plateau service business founder stuck at revenue ceiling | AR38: Backlog
A39: 38 | B39: X | C39: English | D39: Eden | E39: Hidden Gem | F39: Yes | G39: Yes | H39: No | I39: Marketing Strategy | J39: Business Growth & Scale Systems, Client Acquisition | K39: Scott Bair | L39: @scott_bair | M39: 21787 | N39: 20-30k | O39: 2026-04-13 | P39: https://x.com/scott_bair/status/2043596395580670401 | Q39: How to Brand Your Company: The Complete Playbook | R39: Your brand is the single most underleveraged asset in your business. It's not your logo. It's not your color palette. It's not the font on your website. Your brand is the total perception people hold in their heads when they hear your company's name. It's the gut feeling a prospect has before they ever talk to your sales team. It's the reason one company charges $200K for the same service anot | S39: How-To / Listicle | T39: None (pure value) | U39: MOFU: Framework / How-To | V39: text | W39: news | X39: neutral | Y39: 159332 | Z39: 1219 | AA39: 33 | AB39: 110 | AC39: 0.0085481887 | AD39: 162.21 | AE39: =IF(AD39="","",MIN(AD39,100)) -> 100 | AF39: 99.9 | AG39: No | AH39: 6 | AI39: No | AJ39: No | AK39: Intl: Authority-to-Pipeline DFY | AL39: =ROUND('Start Here'!$B$29*AH39+'Start Here'!$B$30*MIN(IF(AD39="",0,AD39),50)/5+IF(M39<=30000,'Start Here'!$B$31,IF(M39<=60000,'Start Here'!$B$32,0)),1) -> 8 | AM39: Scannable, save-worthy steps | AN39: Keep the how-to hook mechanic and swap in your own proof. Teach one marketing strategy lesson for founders of 10-50 person boutique firms (US/UK/AU). Ship it as a LinkedIn text/carousel. | AO39: The post shares a link to an article about Ferrari's new racing simulator technology. | AP39: ferrari, racing simulator, technology, automotive news | AQ39: client kaise laaye business grow kaise kare sales marketing agency; cold email outbound that books meetings for consultants | AR39: Backlog
A40: 39 | B40: Instagram | C40: English | D40: Eden | E40: Breakout | F40: Yes | G40: No | H40: No | I40: Marketing Strategy | J40: High-Ticket Sales, Client Acquisition, Content Marketing & Systems | K40: Paul Foh | L40: @paulfoh | M40: 69116 | N40: 50-100k | O40: 2025-11-24 | P40: https://www.instagram.com/reel/DRbhwTODVM1/ | Q40: The agents getting the best deals in Lagos, Abuja, and London aren’t always the best closers. | R40: The agents getting the best deals in Lagos, Abuja, and London aren’t always the best closers. They’re the ones who show up online every day with sharp content, clear offers and simple CTAs. Your problem isn’t laziness. After viewings, traffic, lawyers, developers and family… your brain is finished. You open Instagram or LinkedIn and there are no ideas. That’s why I built Unlimited Realtor Co | S40: Statement / Declarative | T40: None (pure value) | U40: TOFU: Reach / POV | V40: long_video | W40: promo | X40: informative | Y40: 38135 | Z40: 2023 | AA40: 85 | AC40: 0.055277304 | AD40: 73.13 | AE40: =IF(AD40="","",MIN(AD40,100)) -> 73.13 | AF40: 99.7 | AG40: No | AH40: 10 | AI40: No | AJ40: No | AK40: Intl: Authority-to-Pipeline DFY | AL40: =ROUND('Start Here'!$B$29*AH40+'Start Here'!$B$30*MIN(IF(AD40="",0,AD40),50)/5+IF(M40<=30000,'Start Here'!$B$31,IF(M40<=60000,'Start Here'!$B$32,0)),1) -> 8 | AM40: Topic resonance (check the full post) | AN40: Keep the statement hook mechanic and swap in your own proof. Teach one marketing strategy lesson for founders of 10-50 person boutique firms (US/UK/AU). Ship it as a IG reel, then repurpose to LinkedIn. | AO40: Video marketing pitch for a real estate agent content toolkit designed to help agents generate leads and close deals through social media and webinars, targeting audiences in Nigeria and the UK. | AP40: real estate, leads, webinar, marketing, social media, content creation, Nigeria, UK | AQ40: LinkedIn content strategy that books sales calls for B2B service businesses | AR40: Backlog
A41: 40 | B41: LinkedIn | C41: English | D41: Eden | E41: Hidden Gem | F41: Yes | G41: Yes | H41: Yes | I41: Marketing Strategy | J41: High-Ticket Sales, Business Growth & Scale Systems, Consulting / Fractional | K41: Matt Huang | L41: @matt-huang-103299138 | M41: 19371 | N41: 10-20k | O41: 2025-11-19 | P41: https://www.linkedin.com/feed/update/urn:li:activity:7396917745914781696 | Q41: Friday was my last day at Google. | R41: Friday was my last day at Google. This chapter is over. It’s truly been a wild last few years. Back when I left Boston Consulting Group (BCG) to join Google, I had a vague idea what my new role entailed. Soon I found out the strategy team I joined worked very closely with marketing. I had no idea what "GTM strategy" or b2b marketing really meant. But I'm glad to have learned from some of | S41: Statement / Declarative | T41: None (pure value) | U41: TOFU: Reach / POV | V41: post | Z41: 1336 | AA41: 161 | AB41: 1 | AC41: 0.078204124 | AD41: 58.09 | AE41: =IF(AD41="","",MIN(AD41,100)) -> 58.09 | AF41: 100 | AG41: No | AH41: 6 | AI41: No | AJ41: No | AK41: Intl: Authority-to-Pipeline DFY | AL41: =ROUND('Start Here'!$B$29*AH41+'Start Here'!$B$30*MIN(IF(AD41="",0,AD41),50)/5+IF(M41<=30000,'Start Here'!$B$31,IF(M41<=60000,'Start Here'!$B$32,0)),1) -> 8 | AM41: Small-account breakout: the idea beat the audience size | AN41: Keep the statement hook mechanic and swap in your own proof. Teach one marketing strategy lesson for founders of 10-50 person boutique firms (US/UK/AU). Ship it as a LinkedIn text/carousel. | AQ41: LinkedIn content strategy that books sales calls for B2B service businesses | AR41: Backlog
A42: 41 | B42: LinkedIn | C42: English | D42: Eden | E42: Breakout | F42: Yes | G42: No | H42: Yes | I42: Marketing Strategy | J42: Client Acquisition, Agency Growth, Business Growth & Scale Systems | K42: Kathleen Booth | L42: @kathleenslatterybooth | M42: 52441 | N42: 50-100k | O42: 2026-04-08 | P42: https://www.linkedin.com/feed/update/urn:li:activity:7447674013230841856 | Q42: I ran a marketing agency for 10+ years before going in-house, and here's something I learned the hard way. | R42: I ran a marketing agency for 10+ years before going in-house, and here's something I learned the hard way. 👉 Most marketing campaigns don't fail because of bad targeting. They fail because of what happens after the lead comes in. Too often, the campaigns themselves work and leads come in, but they sit in a spreadsheet or in a lead list that the team forgets to check. By the time sales follow | S42: Story / Anecdote | T42: None (pure value) | U42: TOFU: Reach / POV | V42: post | Z42: 12479 | AA42: 993 | AB42: 279 | AC42: 0.26221849 | AD42: 351.52 | AE42: =IF(AD42="","",MIN(AD42,100)) -> 100 | AF42: 99.9 | AG42: No | AH42: 8 | AI42: No | AJ42: No | AK42: Intl: Authority-to-Pipeline DFY | AL42: =ROUND('Start Here'!$B$29*AH42+'Start Here'!$B$30*MIN(IF(AD42="",0,AD42),50)/5+IF(M42<=30000,'Start Here'!$B$31,IF(M42<=60000,'Start Here'!$B$32,0)),1) -> 8 | AM42: Insider credibility (10+ yrs running agency) + reframe: campaigns don't fail at targeting, they fail after the lead arrives. 351x on LinkedIn. | AN42: Your systems angle: 'Most B2B firms don't have a lead problem. They have a follow-up problem.' Show the speed-to-lead and follow-up layer of your system. | AQ42: marketing agency business model productized service niche down | AR42: Backlog
A43: 42 | B43: X | C43: English | D43: Eden | E43: Hidden Gem | F43: Yes | G43: Yes | H43: No | I43: Business Growth & Scale Systems | J43: Marketing Strategy | K43: Adam Robinson | L43: @retentionadam | M43: 10777 | N43: 10-20k | O43: 2026-01-27 | P43: https://x.com/RetentionAdam/status/2016190513251287229 | Q43: How to Launch an AI Company From 0 Today (And Scale to $1M+) | R43: If I had to start a brand new SaaS or AI company from absolute zero, knowing everything I know from building 3 software companies to over $35M in combined ARR, this is exactly what I would do. —- Why Most Founders Fail Founders fall in love with their idea instead of their customers’ problems. They build something for 12-18 months before talking to anyone. That’s why 90% of startups don't make | S43: How-To / Listicle | T43: None (pure value) | U43: MOFU: Framework / How-To | V43: article | Y43: 295249 | Z43: 1268 | AA43: 10 | AB43: 118 | AC43: 0.0047282125 | AD43: 59.12 | AE43: =IF(AD43="","",MIN(AD43,100)) -> 59.12 | AF43: 99.6 | AG43: No | AH43: 6 | AI43: No | AJ43: No | AK43: Intl: Authority-to-Pipeline DFY | AL43: =ROUND('Start Here'!$B$29*AH43+'Start Here'!$B$30*MIN(IF(AD43="",0,AD43),50)/5+IF(M43<=30000,'Start Here'!$B$31,IF(M43<=60000,'Start Here'!$B$32,0)),1) -> 8 | AM43: Small-account breakout: the idea beat the audience size; Specific number/result in the hook; Scannable, save-worthy steps | AN43: Keep the how-to hook mechanic and swap in your own proof. Teach one business growth & scale systems lesson for founders of 10-50 person boutique firms (US/UK/AU). Ship it as a LinkedIn text/carousel. | AQ43: cold email outbound that books meetings for consultants | AR43: Backlog
A44: 43 | B44: X | C44: English | D44: Eden | E44: Hidden Gem | F44: Yes | G44: Yes | H44: Yes | I44: High-Ticket Sales | J44: Client Acquisition, Outbound / Warm Outbound, Consulting / Fractional | K44: Marlow | L44: @marlowxbt | M44: 12481 | N44: 10-20k | O44: 2026-06-08 | P44: https://x.com/marlowxbt/status/2064014528401277174 | Q44: A 14 year old has closed $20,500 in barbershop website deals over 7 months. Not one owner has ever asked his age. | R44: A 14 year old has closed $20,500 in barbershop website deals over 7 months. Not one owner has ever asked his age. He uses one move the rest of the cold-calling internet has not figured out yet. He does not pitch. He screenshares. The call goes like this. He opens Google Maps. Types "barbershop." Finds one with 4.8 stars and no website. Builds a clean demo site in Lovable in 4 minutes. Then he di | S44: Result / Number-Led Claim | T44: None (pure value) | U44: TOFU: Reach / POV | V44: long_video | W44: tutorial | X44: educational | Y44: 616914 | Z44: 4170 | AA44: 129 | AB44: 270 | AC44: 0.0074062187 | AD44: 213.08 | AE44: =IF(AD44="","",MIN(AD44,100)) -> 100 | AF44: 98.4 | AG44: No | AH44: 6 | AI44: No | AJ44: No | AK44: Intl: Authority-to-Pipeline DFY | AL44: =ROUND('Start Here'!$B$29*AH44+'Start Here'!$B$30*MIN(IF(AD44="",0,AD44),50)/5+IF(M44<=30000,'Start Here'!$B$31,IF(M44<=60000,'Start Here'!$B$32,0)),1) -> 8 | AM44: Small-account breakout: the idea beat the audience size; Specific number/result in the hook; Proof-first opening | AN44: Keep the result hook mechanic and swap in your own proof. Teach one high-ticket sales lesson for founders of 10-50 person boutique firms (US/UK/AU). Ship it as a LinkedIn text/carousel. | AO44: A video shows a person explaining how to acquire clients by building a website directly for barbershops using Screen Sharing. The method avoids pitching and instead demonstrates a completed demo. | AP44: client acquisition, screen share, barbershop, website building, cold calling, demo, young entrepreneur, google maps | AQ44: agency owner lessons scaling to 7 figures clients retention | AR44: Backlog
A45: 44 | B45: Instagram | C45: English | D45: vidIQ | E45: Hidden Gem | F45: Yes | G45: Yes | H45: No | I45: High-Ticket Sales | J45: Consulting / Fractional, Client Acquisition, Business Growth & Scale Systems | K45: jordan._davidson | L45: @jordan._davidson | M45: 23400 | N45: 20-30k | O45: Apr-Oct 2026 | P45: https://www.instagram.com/reel/DblbBF0gJ8g/ | Q45: How to handle "I need a day to think about it" | R45: Comment "JDS" for my FREE 2-hour training breaking down exactly how you can go from $0 to $10k/month... | S45: Objection / Quote Hook | T45: Comment keyword → DM | U45: Lead Capture (MOFU) | V45: Reel: Split-screen video call/Zoom recording. | W45: Education | Y45: 84300 | AD45: 52 | AE45: =IF(AD45="","",MIN(AD45,100)) -> 52 | AG45: No | AH45: 6 | AI45: No | AJ45: No | AK45: Intl: Authority-to-Pipeline DFY | AL45: =ROUND('Start Here'!$B$29*AH45+'Start Here'!$B$30*MIN(IF(AD45="",0,AD45),50)/5+IF(M45<=30000,'Start Here'!$B$31,IF(M45<=60000,'Start Here'!$B$32,0)),1) -> 8 | AM45: Opens on a real objection/quote the buyer recognises; Keyword CTA converts reach into DMs; Format: recorded video call dialogue | AN45: Keep the objection hook mechanic and swap in your own proof. Teach one high-ticket sales lesson for founders of 10-50 person boutique firms (US/UK/AU). Ship it as a IG reel, then repurpose to LinkedIn. | AO45: A two-person video call discussion/coaching session about how to handle prospects who ask for 'a day to think about it' regarding business services. | AP45: Business Coaching | AQ45: High ticket sales | AR45: Backlog
A46: 45 | B46: Instagram | C46: English | D46: Eden | E46: Hidden Gem | F46: Yes | G46: Yes | H46: No | I46: High-Ticket Sales | J46: Outbound / Warm Outbound, Client Acquisition, Consulting / Fractional | K46: Sam Mina | High Ticket Sales Coach | L46: @samyeoo | M46: 26810 | N46: 20-30k | O46: 2026-09-24 | P46: https://www.instagram.com/reel/Ddr6DBaRrL7/ | Q46: Your CRM isn’t the problem. Your follow up is. 6 texts I actually send to dead prospects, steal all of them. Comment PLAYBOOK for the full objection playbook. #highticketsales #salestips #closer #salescoach #commissionsa | R46: Your CRM isn’t the problem. Your follow up is. 6 texts I actually send to dead prospects, steal all of them. Comment PLAYBOOK for the full objection playbook. #highticketsales #salestips #closer #salescoach #commissionsales | S46: Comment-Gate / Lead Magnet | T46: Comment keyword → DM | U46: Lead Capture (MOFU) | V46: long_video | W46: tutorial | X46: educational | Y46: 73531 | Z46: 2205 | AA46: 555 | AC46: 0.037535189 | AD46: 16.08 | AE46: =IF(AD46="","",MIN(AD46,100)) -> 16.08 | AF46: 97.9 | AG46: No | AH46: 10 | AI46: No | AJ46: No | AK46: Intl: Authority-to-Pipeline DFY | AL46: =ROUND('Start Here'!$B$29*AH46+'Start Here'!$B$30*MIN(IF(AD46="",0,AD46),50)/5+IF(M46<=30000,'Start Here'!$B$31,IF(M46<=60000,'Start Here'!$B$32,0)),1) -> 8 | AM46: Comment-gate inflates comments, which the algorithm rewards | AN46: Keep the comment-gate hook mechanic and swap in your own proof. Teach one high-ticket sales lesson for founders of 10-50 person boutique firms (US/UK/AU). Ship it as a IG reel, then repurpose to LinkedIn. | AO46: High-ticket sales coach Sam Mina shares six follow-up text scripts he uses on unresponsive prospects and explains why each one re-engages them, framing follow-up as making buyers feel "chosen" rather than "chased." He offers a full objection playbook to commenters. | AP46: high ticket sales, follow up, sales texts, objection handling, cold prospects, sales coach, commission sales, pipeline | AQ46: sales system CRM follow-up process for service business owners | AR46: Backlog
A47: 46 | B47: Instagram | C47: English | D47: Eden | E47: Hidden Gem | F47: Yes | G47: Yes | H47: No | I47: Marketing Strategy | J47: Freelancing & International Clients, High-Ticket Sales, Agency Growth | K47: Ananya Bagri | L47: @ananyabagri | M47: 29839 | N47: 20-30k | O47: 2026-03-14 | P47: https://www.instagram.com/reel/DV2q3zoErC3/ | Q47: How I went from earning ₹5k to ₹1 Lakh, | R47: How I went from earning ₹5k to ₹1 Lakh, just by these two changes🤑💰 Easiest growth hack ever 🤭🤭🤫 {freelancing, money, branding, quotations, client, design, communication, business, strategy} | S47: How-To / Listicle | T47: None (pure value) | U47: MOFU: Framework / How-To | V47: short_video | W47: tutorial | X47: educational | Y47: 148208 | Z47: 5369 | AA47: 164 | AC47: 0.037332668 | AD47: 14.36 | AE47: =IF(AD47="","",MIN(AD47,100)) -> 14.36 | AF47: 96.1 | AG47: No | AH47: 10 | AI47: No | AJ47: No | AK47: India: Growth & Scale Cohort | AL47: =ROUND('Start Here'!$B$29*AH47+'Start Here'!$B$30*MIN(IF(AD47="",0,AD47),50)/5+IF(M47<=30000,'Start Here'!$B$31,IF(M47<=60000,'Start Here'!$B$32,0)),1) -> 7.9 | AM47: Hinglish income transformation (₹5k to ₹1L) via 2 pricing/quotation changes. Indian IG responds to rupee specificity. | AN47: India cohort reel in Hinglish: 'Indian agency ka ₹3L/month se ₹15L/month: 2 cheezein jo badli'. Aim at owners, not freelancers: use team size and retainer language. | AO47: An influencer shares two specific strategies that dramatically increased her freelance rates from 5,000 to 100,000 rupees per branding project: detailed, itemized quotations and a comprehensive onboarding process. This tutorial-style video explains the practical steps and mindset shifts behind the growth hack. | AP47: freelancing, pricing strategy, branding, client relationships, business growth, onboarding process, quotation breakdown, value perception | AQ47: freelancer to agency first clients Upwork pricing in dollars Hinglish | AR47: Backlog
A48: 47 | B48: Instagram | C48: English | D48: Eden | E48: Hidden Gem | F48: Yes | G48: Yes | H48: No | I48: Marketing Strategy | J48: Business Growth & Scale Systems, Freelancing & International Clients, High-Ticket Sales | K48: Ananya Bagri | L48: @ananyabagri | M48: 29839 | N48: 20-30k | O48: 2026-04-30 | P48: https://www.instagram.com/reel/DXwmJB0S7TG/ | Q48: You can easily earn 1-2 Lakh / Per Month as a designer. | R48: You can easily earn 1-2 Lakh / Per Month as a designer. These websites help you get high ticket clients! {freelancing, branding, logo, packaging, marketing, strategy, earn money} #graphicdesigner #design #branding #packaging #logo | S48: Result / Number-Led Claim | T48: None (pure value) | U48: TOFU: Reach / POV | V48: short_video | W48: promo | X48: informative | Y48: 123705 | Z48: 2220 | AA48: 38 | AC48: 0.018253102 | AD48: 11.99 | AE48: =IF(AD48="","",MIN(AD48,100)) -> 11.99 | AF48: 95 | AG48: No | AH48: 10 | AI48: No | AJ48: No | AK48: India: Growth & Scale Cohort | AL48: =ROUND('Start Here'!$B$29*AH48+'Start Here'!$B$30*MIN(IF(AD48="",0,AD48),50)/5+IF(M48<=30000,'Start Here'!$B$31,IF(M48<=60000,'Start Here'!$B$32,0)),1) -> 7.7 | AM48: Specific number/result in the hook; Proof-first opening | AN48: Keep the result hook mechanic and swap in your own proof. Teach one marketing strategy lesson for Indian B2B service founders (10-50 staff). Ship it as a IG reel, then repurpose to LinkedIn. | AO48: A short video discusses earning potential for designers by freelancing, mentioning how to get high-ticket clients and list some useful websites. The content is mostly in English with some numerals in Indian Rupees format. | AP48: freelancing, earning, clients, branding, design, logo, packaging, marketing | AQ48: freelancer to agency first clients Upwork pricing in dollars Hinglish | AR48: Backlog
A49: 48 | B49: X | C49: English | D49: Eden | E49: Hidden Gem | F49: Yes | G49: Yes | H49: Yes | I49: Marketing Strategy | J49: Business Growth & Scale Systems | K49: Matthew Berman | L49: @themattberman | M49: 13338 | N49: 10-20k | O49: 2026-02-27 | P49: https://x.com/TheMattBerman/status/2027220216409723296 | Q49: I run my meta ads with @openclaw for $0/month 😱 | R49: I run my meta ads with @openclaw for $0/month 😱 here's the system that runs autonomously: step 1: daily health check → social-cli (major shoutout to @vishalojha_me) wraps @Meta's marketing API (token refresh, pagination, rate limits all handled) → am I on track? what's running? who's winning? who's bleeding? any fatigue? → the same 5 questions I asked Ads Manager every morning for 20 years ste | S49: Story / Anecdote | T49: None (pure value) | U49: TOFU: Reach / POV | V49: long_video | W49: tutorial | X49: informative | Y49: 639071 | Z49: 4236 | AA49: 2412 | AB49: 249 | AC49: 0.010792228 | AD49: 298.07 | AE49: =IF(AD49="","",MIN(AD49,100)) -> 100 | AF49: 99.4 | AG49: No | AH49: 5.3 | AI49: No | AJ49: No | AK49: Intl: Authority-to-Pipeline DFY | AL49: =ROUND('Start Here'!$B$29*AH49+'Start Here'!$B$30*MIN(IF(AD49="",0,AD49),50)/5+IF(M49<=30000,'Start Here'!$B$31,IF(M49<=60000,'Start Here'!$B$32,0)),1) -> 7.7 | AM49: Small-account breakout: the idea beat the audience size; Specific number/result in the hook; First-person or observed story: narrative pull; High comment-to-like ratio: debate driver | AN49: Keep the story hook mechanic and swap in your own proof. Teach one marketing strategy lesson for founders of 10-50 person boutique firms (US/UK/AU). Ship it as a LinkedIn text/carousel. | AO49: A long video tutorial explaining an autonomous system for managing Meta ads, including daily health checks, ad fatigue detection, budget optimization, ad copy generation, and automated ad publishing. The system is offered as a free Meta Ads Kit. | AP49: meta ads, facebook ads, paid acquisition, automation, ad management, budget optimization, ad copy generation, ai advertising | AQ49: content system that generates inbound leads for B2B founders | AR49: Backlog
A50: 49 | B50: X | C50: English | D50: Eden | E50: Hidden Gem | F50: Yes | G50: Yes | H50: Yes | I50: Business Growth & Scale Systems | J50: Marketing Strategy, Outbound / Warm Outbound | K50: caiden | L50: @imcaiden | M50: 21310 | N50: 20-30k | O50: 2026-01-01 | P50: https://x.com/parsedpatterns/status/2006786675741962478 | Q50: someone stop me. seriously. | R50: someone stop me. seriously. i am going to CLONE your shtty enterprise backend in ONE AFTERNOON. then i am going to SCRAPE your entire customer list. then i am going to COLD EMAIL every single one of them offering the same product but BETTER and for like 80% LESS because i built it in a DAY with CLAUDE and MODAFINIL and ZERO VENTURE CAPITAL OVERHEAD. your entire engineering team? 47 people. me | S50: Contrarian / Myth-Bust | T50: None (pure value) | U50: TOFU: Reach / POV | V50: image | W50: other | X50: critical | Y50: 1259263 | Z50: 9348 | AA50: 844 | AB50: 812 | AC50: 0.0087384446 | AD50: 51.65 | AE50: =IF(AD50="","",MIN(AD50,100)) -> 51.65 | AF50: 98.5 | AG50: No | AH50: 5.3 | AI50: No | AJ50: No | AK50: Intl: Authority-to-Pipeline DFY | AL50: =ROUND('Start Here'!$B$29*AH50+'Start Here'!$B$30*MIN(IF(AD50="",0,AD50),50)/5+IF(M50<=30000,'Start Here'!$B$31,IF(M50<=60000,'Start Here'!$B$32,0)),1) -> 7.7 | AM50: Challenges a belief the ICP holds | AN50: Keep the contrarian hook mechanic and swap in your own proof. Teach one business growth & scale systems lesson for founders of 10-50 person boutique firms (US/UK/AU). Ship it as a LinkedIn text/carousel. | AO50: The image shows a terminal interface screenshot featuring enterprise cybersecurity software documentation with features like AI-powered detection and real-time analysis of phishing emails, though it also shows a text overlay about cloning an enterprise backend for competitive advantage. | AP50: security, terminal, cybersecurity, ai detection, enterprise, system, software, phishing | AQ50: cold email outbound that books meetings for consultants | AR50: Backlog
A51: 50 | B51: Instagram | C51: English | D51: Eden | E51: Hidden Gem | F51: Yes | G51: Yes | H51: No | I51: Consulting / Fractional | J51: High-Ticket Sales, Marketing Strategy, Outbound / Warm Outbound | K51: Dr. Peter Yu | L51: @dr.peteryu | M51: 11632 | N51: 10-20k | O51: 2026-08-30 | P51: https://www.instagram.com/reel/DcriHRDS7Gt/ | Q51: Most clinic owners keep their prices low because they think a higher number means fewer patients say yes. | R51: Most clinic owners keep their prices low because they think a higher number means fewer patients say yes. What actually happens is you get fewer of the wrong ones. The people who negotiate, no-show, and disappear after three visits are the same people who picked you because you were the cheapest option available. Charge what the outcome is worth and the people who show up are already sold. Hey | S51: Statement / Declarative | T51: None (pure value) | U51: TOFU: Reach / POV | V51: short_video | W51: other | X51: informative | Y51: 16560 | Z51: 91 | AA51: 3 | AC51: 0.0056763285 | AD51: 10.71 | AE51: =IF(AD51="","",MIN(AD51,100)) -> 10.71 | AF51: 93.2 | AG51: No | AH51: 10 | AI51: No | AJ51: No | AK51: Intl: Authority-to-Pipeline DFY | AL51: =ROUND('Start Here'!$B$29*AH51+'Start Here'!$B$30*MIN(IF(AD51="",0,AD51),50)/5+IF(M51<=30000,'Start Here'!$B$31,IF(M51<=60000,'Start Here'!$B$32,0)),1) -> 7.6 | AM51: Small-account breakout: the idea beat the audience size | AN51: Keep the statement hook mechanic and swap in your own proof. Teach one consulting / fractional lesson for founders of 10-50 person boutique firms (US/UK/AU). Ship it as a IG reel, then repurpose to LinkedIn. | AO51: Dr. Peter Yu, founder of Go Getters Coaching, argues that cash-based PT clinic owners should raise prices because cheap pricing attracts patients who negotiate, no-show, and churn. He promotes his coaching program, which installs the MOTION RX clinic operating system, with a DM or bio link call to action. | AP51: pricing, physical therapy, clinic owners, coaching, cash-based practice, consulting offer, positioning, premium pricing | AQ51: founder dependency hiring delegation scaling agency beyond the founder | AR51: Backlog
A52: 51 | B52: Instagram | C52: English | D52: Eden | E52: Hidden Gem | F52: Yes | G52: Yes | H52: No | I52: Agency Growth | J52: Business Growth & Scale Systems, Client Acquisition, Marketing Strategy | K52: Ayrton Sudholz | Business Coach | L52: @ayrtonsudholz | M52: 7184 | N52: 5-10k | O52: 2026-06-05 | P52: https://www.instagram.com/reel/DZMEp61IK8J/ | Q52: follow @ayrtonsudholz for more Video Agency tips | R52: follow @ayrtonsudholz for more Video Agency tips . . . Hi, my name is Ayrton! I teach Video Agency Owners at @videoagencyos how to scale to $30K–$50K+ months by installing predictable client acquisition, authority marketing, and retainer systems into their business. To date, I’ve helped hundreds of Video Agency Owners generate more predictable revenue, land high-paying retainer clients, build rea | S52: Statement / Declarative | T52: Follow ask | U52: TOFU: Reach / POV | V52: video | Y52: 23276 | Z52: 38 | AA52: 0 | AC52: 0.0016325829 | AD52: 26.11 | AE52: =IF(AD52="","",MIN(AD52,100)) -> 26.11 | AF52: 95.8 | AG52: No | AH52: 8 | AI52: No | AJ52: No | AK52: Intl: Authority-to-Pipeline DFY | AL52: =ROUND('Start Here'!$B$29*AH52+'Start Here'!$B$30*MIN(IF(AD52="",0,AD52),50)/5+IF(M52<=30000,'Start Here'!$B$31,IF(M52<=60000,'Start Here'!$B$32,0)),1) -> 7.6 | AM52: Small-account breakout: the idea beat the audience size | AN52: Keep the statement hook mechanic and swap in your own proof. Teach one agency growth lesson for founders of 10-50 person boutique firms (US/UK/AU). Ship it as a IG reel, then repurpose to LinkedIn. | AQ52: freelancer to agency first clients Upwork pricing in dollars Hinglish | AR52: Backlog
A53: 52 | B53: LinkedIn | C53: English | D53: Eden | E53: Hidden Gem | F53: Yes | G53: Yes | H53: Yes | I53: Marketing Strategy | J53: High-Ticket Sales, Business Growth & Scale Systems | K53: Lisa Cole | L53: @lisacole01 | M53: 11901 | N53: 10-20k | O53: 2026-06-11 | P53: https://www.linkedin.com/feed/update/urn:li:activity:7470938105974362112 | Q53: I facilitated a closed-door boardroom session with 28 CMOs at Gartner’s CMO Symposium this week. The topic was AI. | R53: I facilitated a closed-door boardroom session with 28 CMOs at Gartner’s CMO Symposium this week. The topic was AI. But the conversation was not really about AI. It was about pressure. Pressure to move faster. Pressure to prove efficiency. Pressure to do more with fewer headcount. Pressure to make AI “real” before the organization has figured out what that actually means. The biggest themes | S53: Story / Anecdote | T53: None (pure value) | U53: TOFU: Reach / POV | V53: image | W53: review | X53: informative | Z53: 1066 | AA53: 104 | AB53: 42 | AC53: 0.085695575 | AD53: 103.14 | AE53: =IF(AD53="","",MIN(AD53,100)) -> 100 | AF53: 99.7 | AG53: No | AH53: 5 | AI53: No | AJ53: No | AK53: Intl: Authority-to-Pipeline DFY | AL53: =ROUND('Start Here'!$B$29*AH53+'Start Here'!$B$30*MIN(IF(AD53="",0,AD53),50)/5+IF(M53<=30000,'Start Here'!$B$31,IF(M53<=60000,'Start Here'!$B$32,0)),1) -> 7.5 | AM53: Small-account breakout: the idea beat the audience size; First-person or observed story: narrative pull | AN53: Keep the story hook mechanic and swap in your own proof. Teach one marketing strategy lesson for founders of 10-50 person boutique firms (US/UK/AU). Ship it as a LinkedIn text/carousel. | AO53: A graphic illustrates a marketing department structure titled 'The AI-First Marketing Org Chart,' showing hierarchical layers for strategy, orchestration/governance, and offshore execution, emphasizing organization redesign over AI tooling for efficiency. | AP53: ai in marketing, marketing org structure, ai adoption, operational efficiency, scaling, budget constraints, workforce anxiety, automation | AQ53: agency growth scaling service business revenue; fractional executive CMO consulting business positioning and pricing; marketing agency business model productized service niche down | AR53: Backlog
A54: 53 | B54: Instagram | C54: English | D54: Eden | E54: Hidden Gem | F54: Yes | G54: Yes | H54: No | I54: High-Ticket Sales | J54: Client Acquisition, Outbound / Warm Outbound | K54: NCI Sales | L54: @ncisales | M54: 11957 | N54: 10-20k | O54: 2026-09-12 | P54: https://www.instagram.com/reel/DdL7H1QFDHh/ | Q54: Eli Sanchez closed 91 of 101 calls with one pre-call ritual. | R54: Eli Sanchez closed 91 of 101 calls with one pre-call ritual. Comment “SALES” and we’ll send you the NCI Sales waitlist. Sales, persuasion, and human behavior frameworks from Chase Hughes, Eli Wilde, and Eli Sanchez. Follow @ncisales for more. | S54: Result / Number-Led Claim | T54: Comment keyword → DM | U54: Lead Capture (MOFU) | V54: short_video | W54: tutorial | X54: educational | Y54: 114567 | Z54: 3565 | AA54: 219 | AC54: 0.033028708 | AD54: 55.79 | AE54: =IF(AD54="","",MIN(AD54,100)) -> 55.79 | AF54: 98.8 | AG54: No | AH54: 5 | AI54: No | AJ54: No | AK54: Intl: Authority-to-Pipeline DFY | AL54: =ROUND('Start Here'!$B$29*AH54+'Start Here'!$B$30*MIN(IF(AD54="",0,AD54),50)/5+IF(M54<=30000,'Start Here'!$B$31,IF(M54<=60000,'Start Here'!$B$32,0)),1) -> 7.5 | AM54: Small-account breakout: the idea beat the audience size; Proof-first opening; Keyword CTA converts reach into DMs | AN54: Keep the result hook mechanic and swap in your own proof. Teach one high-ticket sales lesson for founders of 10-50 person boutique firms (US/UK/AU). Ship it as a IG reel, then repurpose to LinkedIn. | AO54: Sales trainer shares a pre-call priming ritual: before admitting a prospect to a Zoom call, he records himself narrating the call plan aloud — connecting, uncovering the problem, going to negative implication, then presenting. He credits this habit for closing 91 of 101 calls. | AP54: sales, closing, cold calling, pre-call ritual, self-install, priming, zoom sales calls, persuasion | AQ54: high ticket sales calls closing B2B deals | AR54: Backlog
A55: 54 | B55: X | C55: English | D55: Eden | E55: Hidden Gem | F55: Yes | G55: Yes | H55: Yes | I55: Outbound / Warm Outbound | J55: Client Acquisition, Marketing Strategy | K55: Tech Sales Guy | L55: @techsalesguy | M55: 22288 | N55: 20-30k | O55: 2026-08-27 | P55: https://x.com/TechSalesGuy/status/2092971899659681881 | Q55: The best cold call I’ve heard in a while: https://t.co/3Vho0M7nIV | R55: The best cold call I’ve heard in a while: https://t.co/3Vho0M7nIV | S55: Statement / Declarative | T55: Link / Register | U55: TOFU: Reach / POV | V55: long_video | W55: tutorial | X55: informative | Y55: 2321726 | Z55: 8645 | AA55: 133 | AB55: 418 | AC55: 0.0039608464 | AD55: 54.32 | AE55: =IF(AD55="","",MIN(AD55,100)) -> 54.32 | AF55: 98.4 | AG55: No | AH55: 5 | AI55: No | AJ55: No | AK55: Intl: Authority-to-Pipeline DFY | AL55: =ROUND('Start Here'!$B$29*AH55+'Start Here'!$B$30*MIN(IF(AD55="",0,AD55),50)/5+IF(M55<=30000,'Start Here'!$B$31,IF(M55<=60000,'Start Here'!$B$32,0)),1) -> 7.5 | AM55: Topic resonance (check the full post) | AN55: Keep the statement hook mechanic and swap in your own proof. Teach one outbound / warm outbound lesson for founders of 10-50 person boutique firms (US/UK/AU). Ship it as a LinkedIn text/carousel. | AO55: A video showcasing an example of an effective cold call script and technique, demonstrating successful sales outreach. | AP55: cold calling, sales technique, sales training, sales outreach, sales script, business development, lead generation, sales tips | AQ55: high ticket sales calls closing B2B deals | AR55: Backlog
A56: 55 | B56: X | C56: English | D56: Eden | E56: Hidden Gem | F56: Yes | G56: Yes | H56: Yes | I56: Outbound / Warm Outbound | J56: High-Ticket Sales, Consulting / Fractional | K56: Tune, MBA, CISSP | L56: @cartunenetwerk | M56: 19649 | N56: 10-20k | O56: 2026-06-06 | P56: https://x.com/CartuneNetwerk/status/2063291410049065307 | Q56: Lawyering has the widest gap in quality of any professional service I’ve dealt with. I see why it’s a referral based business | R56: Lawyering has the widest gap in quality of any professional service I’ve dealt with. I see why it’s a referral based business | S56: Statement / Declarative | T56: None (pure value) | U56: TOFU: Reach / POV | V56: text | W56: other | X56: critical | Y56: 152073 | Z56: 2192 | AA56: 27 | AB56: 243 | AC56: 0.016189593 | AD56: 438.4 | AE56: =IF(AD56="","",MIN(AD56,100)) -> 100 | AF56: 99.4 | AG56: No | AH56: 5 | AI56: No | AJ56: No | AK56: Intl: Authority-to-Pipeline DFY | AL56: =ROUND('Start Here'!$B$29*AH56+'Start Here'!$B$30*MIN(IF(AD56="",0,AD56),50)/5+IF(M56<=30000,'Start Here'!$B$31,IF(M56<=60000,'Start Here'!$B$32,0)),1) -> 7.5 | AM56: Small-account breakout: the idea beat the audience size | AN56: Keep the statement hook mechanic and swap in your own proof. Teach one outbound / warm outbound lesson for founders of 10-50 person boutique firms (US/UK/AU). Ship it as a LinkedIn text/carousel. | AO56: The post argues that the legal profession has the greatest discrepancy between quality levels of service among professional services, explaining why referrals dominate in this field. | AP56: legal profession, professional service, quality gap, referral business, business commentary | AQ56: referrals plateau service business founder stuck at revenue ceiling | AR56: Backlog
A57: 56 | B57: X | C57: English | D57: Eden | E57: Breakout | F57: Yes | G57: No | H57: Yes | I57: Marketing Strategy | J57: Client Acquisition, Content Marketing & Systems, Business Growth & Scale Systems | K57: Jil Theo | L57: @theo_jil | M57: 41537 | N57: 30-50k | O57: 2026-04-04 | P57: https://x.com/theo_jil/status/2040494043713425822 | Q57: Branding is how people see you. | R57: Branding is how people see you. Marketing is how they find you. Sales is how you get paid. Master all three. | S57: Statement / Declarative | T57: None (pure value) | U57: TOFU: Reach / POV | V57: text | W57: other | X57: informative | Y57: 474354 | Z57: 27088 | AA57: 163 | AB57: 6640 | AC57: 0.071446641 | AD57: 358.59 | AE57: =IF(AD57="","",MIN(AD57,100)) -> 100 | AF57: 99.9 | AG57: No | AH57: 7 | AI57: No | AJ57: No | AK57: Intl: Authority-to-Pipeline DFY | AL57: =ROUND('Start Here'!$B$29*AH57+'Start Here'!$B$30*MIN(IF(AD57="",0,AD57),50)/5+IF(M57<=30000,'Start Here'!$B$31,IF(M57<=60000,'Start Here'!$B$32,0)),1) -> 7.5 | AM57: Three-line definitional aphorism (branding/marketing/sales). 358x: ultra-short, quotable, repostable. | AN57: Write 3-line aphorisms on your thesis: 'Content earns attention. Outbound earns conversations. Systems earn predictability.' Post as text and as a quote card. | AO57: A concise yet impactful statement summarizing the interconnected roles of branding, marketing, and sales in business success. | AP57: branding, marketing, sales, business strategy, customer journey, company growth, lead generation, client acquisition | AQ57: client kaise laaye business grow kaise kare sales marketing agency | AR57: Backlog
A58: 57 | B58: X | C58: English | D58: Eden | E58: Hidden Gem | F58: Yes | G58: Yes | H58: Yes | I58: Marketing Strategy | J58: Outbound / Warm Outbound, Agency Growth, Business Growth & Scale Systems | K58: James Shields | L58: @scaling_shields | M58: 20541 | N58: 20-30k | O58: 2026-01-22 | P58: https://x.com/scaling_shields/status/2014306814054244421 | Q58: my mates dad ran a recruitment agency for 23 years | R58: my mates dad ran a recruitment agency for 23 years sold it for €4.2m asked him at a bbq how he built it "james, i never recruited a single person" "what do you mean" "i made 600 cold calls a week for 23 years. thats it. found companies who needed staff. found people who needed jobs. connected them. took a cut. no skill involved" he lit a cigar "the lads who try to 'build systems' and 'creat | S58: Story / Anecdote | T58: None (pure value) | U58: TOFU: Reach / POV | V58: tweet | Y58: 1495660 | Z58: 2537 | AA58: 128 | AB58: 71 | AC58: 0.0018292928 | AD58: 103.94 | AE58: =IF(AD58="","",MIN(AD58,100)) -> 100 | AF58: 98.9 | AG58: No | AH58: 5 | AI58: No | AJ58: No | AK58: Intl: Authority-to-Pipeline DFY | AL58: =ROUND('Start Here'!$B$29*AH58+'Start Here'!$B$30*MIN(IF(AD58="",0,AD58),50)/5+IF(M58<=30000,'Start Here'!$B$31,IF(M58<=60000,'Start Here'!$B$32,0)),1) -> 7.5 | AM58: First-person or observed story: narrative pull | AN58: Keep the story hook mechanic and swap in your own proof. Teach one marketing strategy lesson for founders of 10-50 person boutique firms (US/UK/AU). Ship it as a LinkedIn text/carousel. | AQ58: LinkedIn content strategy that books sales calls for B2B service businesses | AR58: Backlog
A59: 58 | B59: X | C59: English | D59: Eden | E59: Hidden Gem | F59: Yes | G59: Yes | H59: Yes | I59: Content Marketing & Systems | J59: Marketing Strategy | K59: Cailyn Y. | L59: @cailynyongyong | M59: 8603 | N59: 5-10k | O59: 2026-04-13 | P59: https://x.com/cailynyongyong/status/2043832596304670749 | Q59: HOW TO GO VIRAL ON X: complete basics easy mode | R59: HOW TO GO VIRAL ON X: complete basics easy mode with first guest as @minmax0501 00:00 Intro 00:50 @getyourmomo 01:16 First guest intro 02:16 Warm up account 02:51 Tip 1: tag communities 04:19 Tip 2: tag famous accounts 05:06 Understanding X audience 06:00 Things that didn’t work 06:28 Linkedin vs X 07:14 Tip 3: post everyday 08:20 Do videos work? 09:03 Tip 4: post successes 09:44 Do multiple ch | S59: How-To / Listicle | T59: None (pure value) | U59: MOFU: Framework / How-To | V59: long_video | W59: tutorial | X59: educational | Y59: 349353 | Z59: 3044 | AA59: 164 | AB59: 326 | AC59: 0.010115843 | AD59: 54.38 | AE59: =IF(AD59="","",MIN(AD59,100)) -> 54.38 | AF59: 99.6 | AG59: No | AH59: 5 | AI59: No | AJ59: No | AK59: Intl: Authority-to-Pipeline DFY | AL59: =ROUND('Start Here'!$B$29*AH59+'Start Here'!$B$30*MIN(IF(AD59="",0,AD59),50)/5+IF(M59<=30000,'Start Here'!$B$31,IF(M59<=60000,'Start Here'!$B$32,0)),1) -> 7.5 | AM59: Small-account breakout: the idea beat the audience size; Scannable, save-worthy steps | AN59: Keep the how-to hook mechanic and swap in your own proof. Teach one content marketing & systems lesson for founders of 10-50 person boutique firms (US/UK/AU). Ship it as a LinkedIn text/carousel. | AO59: This video provides a complete guide on how to go viral on X (formerly Twitter), offering tips on tagging, understanding the audience, posting frequency, and leveraging viral templates. It also covers strategies for structuring demo videos, creating effective hooks, and writing compelling scripts for social media content. | AP59: x content strategy, going viral, social media tips, audience engagement, content creation, twitter strategy, hooks, scripts | AQ59: LinkedIn content strategy that books sales calls for B2B service businesses | AR59: Backlog
A60: 59 | B60: X | C60: English | D60: Eden | E60: Hidden Gem | F60: Yes | G60: Yes | H60: Yes | I60: Outbound / Warm Outbound | J60: Marketing Strategy, Client Acquisition | K60: Om Patel | L60: @om_patel5 | M60: 27268 | N60: 20-30k | O60: 2026-04-04 | P60: https://x.com/om_patel5/status/2040295631793635465 | Q60: SOMEONE VIBE CODED A TOOL THAT FINDS BUSINESSES, READS THEIR REVIEWS, AND WRITES COLD EMAILS BASED ON THEIR OWN CUSTOMERS' COMPLAINTS | R60: SOMEONE VIBE CODED A TOOL THAT FINDS BUSINESSES, READS THEIR REVIEWS, AND WRITES COLD EMAILS BASED ON THEIR OWN CUSTOMERS' COMPLAINTS this is insane. you type in any business type and pick a city. it scrapes every matching business off Google Maps with 30+ data fields. then it visits their actual websites and pulls verified emails, phone numbers, and every social media profile they have scrap | S60: Build / Demo Reveal | T60: None (pure value) | U60: TOFU: Reach / POV | V60: long_video | W60: review | X60: informative | Y60: 600724 | Z60: 5880 | AA60: 179 | AB60: 416 | AC60: 0.01077866 | AD60: 164.49 | AE60: =IF(AD60="","",MIN(AD60,100)) -> 100 | AF60: 97.6 | AG60: No | AH60: 5 | AI60: No | AJ60: No | AK60: Intl: Authority-to-Pipeline DFY | AL60: =ROUND('Start Here'!$B$29*AH60+'Start Here'!$B$30*MIN(IF(AD60="",0,AD60),50)/5+IF(M60<=30000,'Start Here'!$B$31,IF(M60<=60000,'Start Here'!$B$32,0)),1) -> 7.5 | AM60: Shows the system or tool, not just claims | AN60: Keep the build hook mechanic and swap in your own proof. Teach one outbound / warm outbound lesson for founders of 10-50 person boutique firms (US/UK/AU). Ship it as a LinkedIn text/carousel. | AO60: The video presents a map-based platform and showcases a user interacting with company data, location mapping, and CRM features. The user navigates through map views, zooms into locations, browsing company entries to view details including contact information and reviews. | AP60: business tool, CRM, lead generation, geolocation, cold emailing, data scraping, ai assistant, platform navigation | AQ60: cold email outbound that books meetings for consultants | AR60: Backlog
A61: 60 | B61: Instagram | C61: English | D61: vidIQ | E61: Hidden Gem | F61: Yes | G61: Yes | H61: No | I61: High-Ticket Sales | J61: Freelancing & International Clients, Marketing Strategy | K61: anguspoh.bpchiro | L61: @anguspoh.bpchiro | M61: 18100 | N61: 10-20k | O61: Apr-Oct 2026 | P61: https://www.instagram.com/reel/Dcbe_AuOO3L/ | Q61: When your Patient Say You are Too Expensive | R61: You Are Too Expensive! . . . . #entrepreneurship #drangus #chiropractor #doctor #physiotherapy | S61: Objection / Quote Hook | T61: None (pure value) | U61: TOFU: Reach / POV | V61: Reel: talking head | W61: Education | Y61: 385300 | AD61: 96 | AE61: =IF(AD61="","",MIN(AD61,100)) -> 96 | AG61: No | AH61: 5 | AI61: No | AJ61: No | AK61: Intl: Authority-to-Pipeline DFY | AL61: =ROUND('Start Here'!$B$29*AH61+'Start Here'!$B$30*MIN(IF(AD61="",0,AD61),50)/5+IF(M61<=30000,'Start Here'!$B$31,IF(M61<=60000,'Start Here'!$B$32,0)),1) -> 7.5 | AM61: Small-account breakout: the idea beat the audience size; Opens on a real objection/quote the buyer recognises; Format: on-camera expert advice | AN61: Keep the objection hook mechanic and swap in your own proof. Teach one high-ticket sales lesson for founders of 10-50 person boutique firms (US/UK/AU). Ship it as a IG reel, then repurpose to LinkedIn. | AO61: A professional explains a sales strategy to handle client price objections by focusing on value instead of discounts. | AP61: Business and Professional Development | AQ61: Client acquisition (EN); High ticket sales | AR61: Backlog
A62: 61 | B62: Instagram | C62: English | D62: vidIQ | E62: Breakout | F62: Yes | G62: No | H62: Yes | I62: High-Ticket Sales | J62: Client Acquisition, Business Growth & Scale Systems, Freelancing & International Clients | K62: _owensantos_ | L62: @_owensantos_ | M62: 47100 | N62: 30-50k | O62: Apr-Oct 2026 | P62: https://www.instagram.com/reel/Ddl5gR1xz9b/ | Q62: 26M Dollar Closer Vs Kid | R62: If we haven’t met, I’m Owen Santos. I spent 15 years selling & building sales teams. We sold over... | S62: POV / Comparison | T62: None (pure value) | U62: TOFU: Reach / POV | V62: Reel: Split screen (creator providing commentary over external footage). | W62: Education | Y62: 1700000 | AD62: 765 | AE62: =IF(AD62="","",MIN(AD62,100)) -> 100 | AG62: No | AH62: 7 | AI62: No | AJ62: No | AK62: Intl: Authority-to-Pipeline DFY | AL62: =ROUND('Start Here'!$B$29*AH62+'Start Here'!$B$30*MIN(IF(AD62="",0,AD62),50)/5+IF(M62<=30000,'Start Here'!$B$31,IF(M62<=60000,'Start Here'!$B$32,0)),1) -> 7.5 | AM62: Specific number/result in the hook; Contrast format (X vs Y) creates instant tension; Format: An expert provides real-time analysis of a recorded interaction by pausing the footage at | AN62: Keep the pov hook mechanic and swap in your own proof. Teach one high-ticket sales lesson for founders of 10-50 person boutique firms (US/UK/AU). Ship it as a IG reel, then repurpose to LinkedIn. | AO62: A sales expert breaks down and analyzes a cold-calling interaction between a high-ticket closer and a potential lead. | AP62: Business & Entrepreneurship | AQ62: Client acquisition (EN); High ticket sales | AR62: Backlog
A63: 62 | B63: Instagram | C63: English | D63: vidIQ | E63: Hidden Gem | F63: Yes | G63: Yes | H63: Yes | I63: High-Ticket Sales | J63: Business Growth & Scale Systems | K63: john_s_hawes | L63: @john_s_hawes | M63: 14400 | N63: 10-20k | O63: Apr-Oct 2026 | P63: https://www.instagram.com/reel/DbOTspij6yZ/ | Q63: As a 7-figure bakery owner, I probably shouldn't share this pricing formula... | R63: Here's the exact pricing formula we use across our bakeries: Price = ingredient cost ÷ 0.30 That's... | S63: Insider Secret / Curiosity | T63: Save/Share ask | U63: TOFU: Reach / POV | V63: Reel: Static background b-roll with text overlay | W63: Education | Y63: 771100 | AD63: 276.1 | AE63: =IF(AD63="","",MIN(AD63,100)) -> 100 | AG63: No | AH63: 5 | AI63: No | AJ63: No | AK63: Intl: Authority-to-Pipeline DFY | AL63: =ROUND('Start Here'!$B$29*AH63+'Start Here'!$B$30*MIN(IF(AD63="",0,AD63),50)/5+IF(M63<=30000,'Start Here'!$B$31,IF(M63<=60000,'Start Here'!$B$32,0)),1) -> 7.5 | AM63: Small-account breakout: the idea beat the audience size; Curiosity gap / insider framing; Format: b-roll with text overlay | AN63: Keep the insider secret hook mechanic and swap in your own proof. Teach one high-ticket sales lesson for founders of 10-50 person boutique firms (US/UK/AU). Ship it as a IG reel, then repurpose to LinkedIn. | AO63: A 7-figure business owner hints at a secret pricing formula while filming a static b-roll shot of a bakery kitchen. | AP63: Business | AQ63: Client acquisition (EN) | AR63: Backlog
A64: 63 | B64: Instagram | C64: Hindi | D64: vidIQ | E64: Hidden Gem | F64: Yes | G64: Yes | H64: No | I64: Freelancing & International Clients | J64: Business Growth & Scale Systems, Marketing Strategy | K64: thevibebusiness | L64: @thevibebusiness | M64: 18900 | N64: 10-20k | O64: Apr-Oct 2026 | P64: https://www.instagram.com/reel/DclVkO-ym1J/ | Q64: A 29 Years old trier 3 city guy doing 20lakhs a month!! | R64: You can do it too | S64: Result / Number-Led Claim | T64: None (pure value) | U64: TOFU: Reach / POV | V64: Reel: single-shot talking head | W64: Education | Y64: 263300 | AD64: 92.8 | AE64: =IF(AD64="","",MIN(AD64,100)) -> 92.8 | AG64: No | AH64: 5 | AI64: No | AJ64: No | AK64: India: Growth & Scale Cohort | AL64: =ROUND('Start Here'!$B$29*AH64+'Start Here'!$B$30*MIN(IF(AD64="",0,AD64),50)/5+IF(M64<=30000,'Start Here'!$B$31,IF(M64<=60000,'Start Here'!$B$32,0)),1) -> 7.5 | AM64: Small-account breakout: the idea beat the audience size; Proof-first opening; Format: talking head with overlay proof | AN64: Keep the result hook mechanic and swap in your own proof. Teach one freelancing & international clients lesson for Indian B2B service founders (10-50 staff). Ship it as a IG reel, then repurpose to LinkedIn. | AO64: A successful freelancer explains how he earns a high income on Upwork and offers a guide to viewers. | AP64: Business | AQ64: Client acquisition (Hindi/India); International clients (India) | AR64: Backlog
A65: 64 | B65: Instagram | C65: English | D65: vidIQ | E65: Hidden Gem | F65: Yes | G65: Yes | H65: No | I65: High-Ticket Sales | J65: Marketing Strategy, Consulting / Fractional | K65: nicksayala | L65: @nicksayala | M65: 17500 | N65: 10-20k | O65: Apr-Oct 2026 | P65: https://www.instagram.com/reel/DbpURTwRL_W/ | Q65: when somebody low balls you never defend your price here's what to say instead | R65: @nickjayala is giving free access to The Come Up — a weekly room that finds and fixes what's slowing... | S65: Contrarian / Myth-Bust | T65: None (pure value) | U65: TOFU: Reach / POV | V65: Reel: Talking head, caption-driven | W65: Education | Y65: 211000 | AD65: 199.3 | AE65: =IF(AD65="","",MIN(AD65,100)) -> 100 | AG65: No | AH65: 5 | AI65: No | AJ65: No | AK65: Intl: Authority-to-Pipeline DFY | AL65: =ROUND('Start Here'!$B$29*AH65+'Start Here'!$B$30*MIN(IF(AD65="",0,AD65),50)/5+IF(M65<=30000,'Start Here'!$B$31,IF(M65<=60000,'Start Here'!$B$32,0)),1) -> 7.5 | AM65: Small-account breakout: the idea beat the audience size; Challenges a belief the ICP holds; Format: spoken advice with text overlay | AN65: Keep the contrarian hook mechanic and swap in your own proof. Teach one high-ticket sales lesson for founders of 10-50 person boutique firms (US/UK/AU). Ship it as a IG reel, then repurpose to LinkedIn. | AO65: A sales coach provides actionable advice on how to respond when a client offers a low price. | AP65: Business & Entrepreneurship | AQ65: High ticket sales | AR65: Backlog
A66: 65 | B66: Instagram | C66: Hindi | D66: vidIQ | E66: Hidden Gem | F66: Yes | G66: Yes | H66: No | I66: Freelancing & International Clients | J66: Marketing Strategy | K66: biz_rahulgupta | L66: @biz_rahulgupta | M66: 5600 | N66: 5-10k | O66: Apr-Oct 2026 | P66: https://www.instagram.com/reel/DbYHkLmtIBv/ | Q66: Foreign Buyers in Noida? Meet them for FREE | R66: Export ka sabse sasta जुगाड़! 💼 500+ Foreign Buyers are coming to Greater Noida, not you going to D... | S66: Statement / Declarative | T66: None (pure value) | U66: TOFU: Reach / POV | V66: Reel: talking head | W66: Education | Y66: 151400 | AD66: 52.6 | AE66: =IF(AD66="","",MIN(AD66,100)) -> 52.6 | AG66: No | AH66: 5 | AI66: No | AJ66: No | AK66: India: Growth & Scale Cohort | AL66: =ROUND('Start Here'!$B$29*AH66+'Start Here'!$B$30*MIN(IF(AD66="",0,AD66),50)/5+IF(M66<=30000,'Start Here'!$B$31,IF(M66<=60000,'Start Here'!$B$32,0)),1) -> 7.5 | AM66: Small-account breakout: the idea beat the audience size; Format: talking head with key points text | AN66: Keep the statement hook mechanic and swap in your own proof. Teach one freelancing & international clients lesson for Indian B2B service founders (10-50 staff). Ship it as a IG reel, then repurpose to LinkedIn. | AO66: A business expert explains why Indian exporters should utilize local trade shows to find international buyers instead of traveling abroad. | AP66: Business | AQ66: Business growth (India/Hindi) | AR66: Backlog
A67: 66 | B67: X | C67: English | D67: Eden | E67: Hidden Gem | F67: Yes | G67: Yes | H67: Yes | I67: Agency Growth | J67: Business Growth & Scale Systems, Marketing Strategy | K67: Jonny Miller | L67: @jonnym1ller | M67: 23777 | N67: 20-30k | O67: 2026-09-07 | P67: https://x.com/jonnym1ller/status/2096786649149825058 | Q67: This is a banger benchmark prompt to ask Astra/Fable: “based on everything you know about me, if I had 10x the agency, what would I ask you” | R67: This is a banger benchmark prompt to ask Astra/Fable: “based on everything you know about me, if I had 10x the agency, what would I ask you” | S67: Story / Anecdote | T67: None (pure value) | U67: TOFU: Reach / POV | V67: text | W67: other | X67: informative | Y67: 284556 | Z67: 2213 | AA67: 23 | AB67: 64 | AC67: 0.0080827675 | AD67: 57.3 | AE67: =IF(AD67="","",MIN(AD67,100)) -> 57.3 | AF67: 99.1 | AG67: No | AH67: 4.9 | AI67: Yes | AJ67: No | AK67: Intl: Authority-to-Pipeline DFY | AL67: =ROUND('Start Here'!$B$29*AH67+'Start Here'!$B$30*MIN(IF(AD67="",0,AD67),50)/5+IF(M67<=30000,'Start Here'!$B$31,IF(M67<=60000,'Start Here'!$B$32,0)),1) -> 7.5 | AM67: Specific number/result in the hook; First-person or observed story: narrative pull | AN67: Keep the story hook mechanic and swap in your own proof. Teach one agency growth lesson for founders of 10-50 person boutique firms (US/UK/AU). Ship it as a LinkedIn text/carousel. | AO67: A text post discussing a strategic prompt for scaling an agency tenfold, focusing on leveraging existing knowledge to identify key priorities for growth and optimization. | AP67: agency growth, scaling business, benchmark prompt, strategic planning, business advice, agency scaling, prompt engineering, business strategy | AQ67: agency growth scaling service business revenue | AR67: Backlog
A68: 67 | B68: X | C68: English | D68: Eden | E68: Hidden Gem | F68: Yes | G68: Yes | H68: No | I68: Business Growth & Scale Systems | J68: Agency Growth, High-Ticket Sales, Freelancing & International Clients | K68: Alton Syn | L68: @workflowwhisper | M68: 13198 | N68: 10-20k | O68: 2026-01-17 | P68: https://x.com/WorkflowWhisper/status/2012590119929172319 | Q68: The n8n Gap Just Closed. Here's What $600K/Month Taught Me About the New Automation Economy. | R68: I've been building n8n automations for 4 years. Started as a solo freelancer charging $500 per workflow, scaled to a 12-person agency doing $280K/month, then watched everything change in 2025 and rebuilt the entire operation from scratch. Now I run a $600K/month automation agency (did $753K in November but has averaged out to just over $600K) with 7 employees. Our entire backend is Claude and Cur | S68: Result / Number-Led Claim | T68: None (pure value) | U68: BOFU: Proof / Case Study | V68: text | W68: tutorial | X68: informative | Y68: 381948 | Z68: 1812 | AA68: 111 | AB68: 142 | AC68: 0.0054064951 | AD68: 895.76 | AE68: =IF(AD68="","",MIN(AD68,100)) -> 100 | AF68: 99.8 | AG68: No | AH68: 4.9 | AI68: Yes | AJ68: No | AK68: Intl: Authority-to-Pipeline DFY | AL68: =ROUND('Start Here'!$B$29*AH68+'Start Here'!$B$30*MIN(IF(AD68="",0,AD68),50)/5+IF(M68<=30000,'Start Here'!$B$31,IF(M68<=60000,'Start Here'!$B$32,0)),1) -> 7.5 | AM68: Small-account breakout: the idea beat the audience size; Specific number/result in the hook; Proof-first opening | AN68: Keep the result hook mechanic and swap in your own proof. Teach one business growth & scale systems lesson for founders of 10-50 person boutique firms (US/UK/AU). Ship it as a LinkedIn text/carousel. | AO68: A productivity expert shares his checklist for conducting effective weekly reviews to improve focus and track progress, emphasizing reflection on accomplishments and planning for the next week. | AP68: weekly review, productivity system, checklist, time management, focus, progress tracking, planning, routine | AQ68: freelancer to agency first clients Upwork pricing in dollars Hinglish | AR68: Backlog
A69: 68 | B69: Instagram | C69: English | D69: vidIQ | E69: Hidden Gem | F69: Yes | G69: Yes | H69: No | I69: Marketing Strategy | J69: Client Acquisition, Content Marketing & Systems | K69: coltonhavens6 | L69: @coltonhavens6 | M69: 20800 | N69: 20-30k | O69: Apr-Oct 2026 | P69: https://www.instagram.com/reel/Db_hVF_P5lF/ | Q69: Claude Is Posting 20x A Day For Me | R69: What if Claude just does it for you? #claude #makreting #leads | S69: Result / Number-Led Claim | T69: None (pure value) | U69: TOFU: Reach / POV | V69: Reel: split screen (creator + screen recording) | W69: Education | Y69: 162700 | AD69: 629.2 | AE69: =IF(AD69="","",MIN(AD69,100)) -> 100 | AG69: No | AH69: 4.9 | AI69: Yes | AJ69: No | AK69: Intl: Authority-to-Pipeline DFY | AL69: =ROUND('Start Here'!$B$29*AH69+'Start Here'!$B$30*MIN(IF(AD69="",0,AD69),50)/5+IF(M69<=30000,'Start Here'!$B$31,IF(M69<=60000,'Start Here'!$B$32,0)),1) -> 7.5 | AM69: Specific number/result in the hook; Proof-first opening; Format: screen-recording software walkthrough | AN69: Keep the result hook mechanic and swap in your own proof. Teach one marketing strategy lesson for founders of 10-50 person boutique firms (US/UK/AU). Ship it as a IG reel, then repurpose to LinkedIn. | AO69: The creator demonstrates a workflow for automating daily social media posting using AI and CRM software to drive business leads. | AP69: Business & Marketing | AQ69: Content systems | AR69: Backlog
A70: 69 | B70: X | C70: English | D70: Eden | E70: Hidden Gem | F70: No | G70: Yes | H70: No | I70: Marketing Strategy | J70: Business Growth & Scale Systems, Agency Growth, High-Ticket Sales | K70: Rob O'Rourke | L70: @theroborourke | M70: 10660 | N70: 10-20k | O70: 2026-09-08 | P70: https://x.com/theroborourke/status/2097222027950125427 | Q70: Yesterday this question was asked by @drapzdesigns... | R70: Yesterday this question was asked by @drapzdesigns... How you get from $3-4k branding projects to 10k+ projects From helping a bunch of agency owners and freelancers do this, here are my own thoughts. At a certain stage your skills are going to be pretty much good enough. If you are already charging $3,000, $4,000, $5,000 or whatnot, you already have very good skills that can solve a lot of pro | S70: Story / Anecdote | T70: None (pure value) | U70: TOFU: Reach / POV | V70: text | W70: tutorial | X70: informative | Y70: 20732 | Z70: 258 | AA70: 49 | AB70: 31 | AC70: 0.016303299 | AD70: 7.19 | AE70: =IF(AD70="","",MIN(AD70,100)) -> 7.19 | AF70: 96.2 | AG70: No | AH70: 10 | AI70: No | AJ70: No | AK70: Intl: Authority-to-Pipeline DFY | AL70: =ROUND('Start Here'!$B$29*AH70+'Start Here'!$B$30*MIN(IF(AD70="",0,AD70),50)/5+IF(M70<=30000,'Start Here'!$B$31,IF(M70<=60000,'Start Here'!$B$32,0)),1) -> 7.4 | AM70: First-person or observed story: narrative pull | AN70: Keep the story hook mechanic and swap in your own proof. Teach one marketing strategy lesson for founders of 10-50 person boutique firms (US/UK/AU). Ship it as a LinkedIn text/carousel. | AO70: A text post by Rob O'Rourke offers advice on scaling from $3-4k to $10k+ branding projects. He argues that beyond a certain skill level, the key to higher earnings lies in targeting larger businesses with bigger problems, where branding work can have significant impact, and in effective sales strategies like sales funnels to reach these clients. | AP70: branding, pricing strategy, client selection, sales funnels, business growth, freelancing, agency, value proposition | AQ70: agency growth scaling service business revenue | AR70: Backlog
A71: 70 | B71: X | C71: English | D71: Eden | E71: Hidden Gem | F71: No | G71: Yes | H71: No | I71: Outbound / Warm Outbound | J71: Agency Growth, Consulting / Fractional, Client Acquisition | K71: Michel Lieben | L71: @michlieben | M71: 13265 | N71: 10-20k | O71: 2026-10-12 | P71: https://x.com/MichLieben/status/2109690075546329232 | Q71: How to Get Your First 10 B2B Clients From Zero (FULL COURSE) | R71: I grew my cold outbound agency to $7M ARR and ran outbound for 300+ B2B companies. The first clients came from these same 4 steps, and step 1 only costs your time. It works for agencies, consultants, freelancers, coaches, fractional executives and SaaS founders who sell to other businesses. This is the full process for turning free content into people you can message and book on a call. The 4 | S71: How-To / Listicle | T71: None (pure value) | U71: MOFU: Framework / How-To | V71: image | W71: tutorial | X71: educational | Y71: 11000 | Z71: 107 | AA71: 11 | AB71: 15 | AC71: 0.012090909 | AD71: 7.08 | AE71: =IF(AD71="","",MIN(AD71,100)) -> 7.08 | AF71: 84.6 | AG71: No | AH71: 10 | AI71: No | AJ71: No | AK71: Intl: Authority-to-Pipeline DFY | AL71: =ROUND('Start Here'!$B$29*AH71+'Start Here'!$B$30*MIN(IF(AD71="",0,AD71),50)/5+IF(M71<=30000,'Start Here'!$B$31,IF(M71<=60000,'Start Here'!$B$32,0)),1) -> 7.4 | AM71: Explicit ICP list ('agencies, consultants, fractional executives') + credibility ($7M ARR outbound agency) + 4 steps where step 1 is free. | AN71: Steal the structure verbatim for your pillar post: 'The first 10 clients for a boutique firm come from these 4 steps'. Name your ICP in line 3. | AO71: Dark-themed infographic laying out a five-step client-acquisition roadmap — get seen, one landing page, catch visitors, reach out, repeat — for a cold-outbound agency that grew to $7M ARR. The caption details the same process of converting free content into booked sales calls. | AP71: cold outbound, agency growth, client acquisition, linkedin marketing, b2b, lead magnet, vsl, content marketing | AQ71: "fractional" CMO CFO COO getting clients | AR71: Backlog
A72: 71 | B72: Instagram | C72: English | D72: Eden | E72: Breakout | F72: Yes | G72: No | H72: No | I72: Agency Growth | J72: Marketing Strategy, Outbound / Warm Outbound, Client Acquisition | K72: Austin Schneider | L72: @theaustinschneider | M72: 46241 | N72: 30-50k | O72: 2026-09-18 | P72: https://www.instagram.com/reel/DdcS_4aiYdH/ | Q72: The best marketing money can't buy is a client who wins. | R72: The best marketing money can't buy is a client who wins. Help someone get a real result and they don't just stick around. They talk. That's when everything shifts. Referrals start showing up. Trust is built before you ever say a word. Most agency owners are chasing views and reach. The real game is building something that works so well it markets itself. Put the result first. The growth takes | S72: Story / Anecdote | T72: None (pure value) | U72: BOFU: Proof / Case Study | V72: short_video | W72: promo | X72: informative | Y72: 42229 | Z72: 966 | AA72: 4 | AC72: 0.022969997 | AD72: 23.62 | AE72: =IF(AD72="","",MIN(AD72,100)) -> 23.62 | AF72: 96.7 | AG72: No | AH72: 10 | AI72: No | AJ72: No | AK72: Intl: Authority-to-Pipeline DFY | AL72: =ROUND('Start Here'!$B$29*AH72+'Start Here'!$B$30*MIN(IF(AD72="",0,AD72),50)/5+IF(M72<=30000,'Start Here'!$B$31,IF(M72<=60000,'Start Here'!$B$32,0)),1) -> 7.4 | AM72: First-person or observed story: narrative pull | AN72: Keep the story hook mechanic and swap in your own proof. Teach one agency growth lesson for founders of 10-50 person boutique firms (US/UK/AU). Ship it as a IG reel, then repurpose to LinkedIn. | AO72: The video features two men in a modern indoor setting discussing client success as a powerful marketing strategy. The message emphasizes that delivering real results for clients leads to organic referrals and trust, which ultimately drives agency growth. | AP72: client success, organic marketing, agency growth, referrals, trust building, results-driven, network effect, client retention | AQ72: client acquisition for agencies and consultants | AR72: Backlog
A73: 72 | B73: X | C73: English | D73: Eden | E73: Hidden Gem | F73: Yes | G73: Yes | H73: No | I73: Marketing Strategy | J73: High-Ticket Sales, Business Growth & Scale Systems, Freelancing & International Clients | K73: Ian Wong | L73: @ianwong_ | M73: 5892 | N73: 5-10k | O73: 2026-08-20 | P73: https://x.com/ianwong_/status/2090454226011091033 | Q73: Build, then Buy | R73: A new VP of Sales had joined Opendoor, and — unbeknownst to me — he asked our Customer Experience engineering team to demo Salesforce. I happened to be in the meeting room next door when the demo happened. Our office had thin walls. I overheard the meeting and walked out hot. Why would we pay hundreds of thousands of dollars for that bloated thing? We had some of the best engineers in the world, | S73: Statement / Declarative | T73: None (pure value) | U73: TOFU: Reach / POV | V73: image | W73: other | X73: informative | Y73: 20004 | Z73: 97 | AA73: 10 | AB73: 12 | AC73: 0.0059488102 | AD73: 39.8 | AE73: =IF(AD73="","",MIN(AD73,100)) -> 39.8 | AF73: 91.7 | AG73: No | AH73: 6 | AI73: No | AJ73: No | AK73: Intl: Authority-to-Pipeline DFY | AL73: =ROUND('Start Here'!$B$29*AH73+'Start Here'!$B$30*MIN(IF(AD73="",0,AD73),50)/5+IF(M73<=30000,'Start Here'!$B$31,IF(M73<=60000,'Start Here'!$B$32,0)),1) -> 7.4 | AM73: Small-account breakout: the idea beat the audience size | AN73: Keep the statement hook mechanic and swap in your own proof. Teach one marketing strategy lesson for founders of 10-50 person boutique firms (US/UK/AU). Ship it as a LinkedIn text/carousel. | AO73: The image shows three electronic components against a red background: a small circuit board with handwritten schematic notations, a more complex printed circuit board with a central chip, and a compact enclosed device with a USB port, connected by arrows to suggest progression or relationship. | AP73: circuit board, electronics, hardware, schematic, component, PCB, USB, electronics design | AQ73: sales system CRM follow-up process for service business owners | AR73: Backlog
A74: 73 | B74: X | C74: English | D74: Eden | E74: Hidden Gem | F74: Yes | G74: Yes | H74: No | I74: High-Ticket Sales | J74: Business Growth & Scale Systems, Marketing Strategy, Outbound / Warm Outbound | K74: ecomchigga | L74: @ecomchigga | M74: 12398 | N74: 10-20k | O74: 2025-11-27 | P74: https://x.com/ecomchigga/status/1994132401853722732 | Q74: The exact playbook I used to go from $0 to $50K/month at 18 (steal this): | R74: The exact playbook I used to go from $0 to $50K/month at 18 (steal this): Nobody's teaching this because they're too busy selling you mindset BS. Here's what actually works: THE FOUNDATION NOBODY TALKS ABOUT Your first 1000 followers determine everything. Not because of the number, but because of WHO they are. I spent 2 months manually DMing people who bought from competitors. Asked what they wis | S74: How-To / Listicle | T74: None (pure value) | U74: MOFU: Framework / How-To | V74: carousel | W74: story | X74: inspirational | Y74: 18875 | Z74: 200 | AA74: 18 | AB74: 15 | AC74: 0.012344371 | AD74: 27.02 | AE74: =IF(AD74="","",MIN(AD74,100)) -> 27.02 | AF74: 87.5 | AG74: No | AH74: 7.5 | AI74: No | AJ74: Yes | AK74: Low fit (aspirant/beginner audience) | AL74: =ROUND('Start Here'!$B$29*AH74+'Start Here'!$B$30*MIN(IF(AD74="",0,AD74),50)/5+IF(M74<=30000,'Start Here'!$B$31,IF(M74<=60000,'Start Here'!$B$32,0)),1) -> 7.4 | AM74: Small-account breakout: the idea beat the audience size; Specific number/result in the hook; Scannable, save-worthy steps | AN74: Keep the how-to hook mechanic and swap in your own proof. Teach one high-ticket sales lesson for (re-aim at business owners, not aspirants). Ship it as a LinkedIn text/carousel. | AO74: This carousel story details an entrepreneur's $0 to $50K/month playbook: building targeted audiences, content multiplication, pricing psychology, DM scripts, email sequences, product creation from customer questions, cross-platform traffic, conversion metrics, high-ticket upsells, compound schedule, automation stack, failure recovery, and scaling truths. | AP74: entrepreneurship, startup growth, business strategy, monetization, social media marketing, email marketing, content strategy, pricing psychology | AQ74: high ticket sales calls closing B2B deals | AR74: Backlog
A75: 74 | B75: X | C75: English | D75: Eden | E75: Outlier | F75: No | G75: No | H75: No | I75: Outbound / Warm Outbound | J75: Business Growth & Scale Systems, Marketing Strategy, Client Acquisition | K75: Frederick Potticary | L75: @freddiexpott | M75: 7003 | N75: 5-10k | O75: 2026-10-10 | P75: https://x.com/freddiexpott/status/2108739030569361744 | Q75: Met a guy making $100k every 14 days referring companies to AI data labs | R75: Met a guy making $100k every 14 days referring companies to AI data labs no agency, no retainer, and no product. Here's the actual model He finds 3 AI data labs on LinkedIn and pitches to work with them on a pure referral basis He refers each lab 10 qualified calls a month, that's 30 calls total across all three Each lab is paying $35k to $60k per signed referral Out of 30 calls, 8 companies | S75: Story / Anecdote | T75: None (pure value) | U75: TOFU: Reach / POV | V75: image | W75: other | X75: informative | Y75: 8491 | Z75: 102 | AA75: 9 | AB75: 5 | AC75: 0.013661524 | AD75: 4.64 | AE75: =IF(AD75="","",MIN(AD75,100)) -> 4.64 | AF75: 92.7 | AG75: No | AH75: 10 | AI75: No | AJ75: No | AK75: Intl: Authority-to-Pipeline DFY | AL75: =ROUND('Start Here'!$B$29*AH75+'Start Here'!$B$30*MIN(IF(AD75="",0,AD75),50)/5+IF(M75<=30000,'Start Here'!$B$31,IF(M75<=60000,'Start Here'!$B$32,0)),1) -> 7.3 | AM75: Specific number/result in the hook; First-person or observed story: narrative pull | AN75: Keep the story hook mechanic and swap in your own proof. Teach one outbound / warm outbound lesson for founders of 10-50 person boutique firms (US/UK/AU). Ship it as a LinkedIn text/carousel. | AO75: Screenshot of a dark-themed messaging thread where a sender pitches a "data selling play," claiming $50k per closed company intro and offering to connect whales and lead-gen contacts; the recipient replies that they're already running outbound for it. Caption describes a referral model earning $100k every 14 days by sending companies to AI data labs. | AP75: referral model, ai data labs, dm screenshot, linkedin outbound, lead gen, cold outreach, b2b sales, high ticket | AQ75: high ticket sales calls closing B2B deals | AR75: Backlog
A76: 75 | B76: X | C76: English | D76: Eden | E76: Outlier | F76: No | G76: No | H76: No | I76: Marketing Strategy | J76: Outbound / Warm Outbound, Content Marketing & Systems, Client Acquisition | K76: Daniel Fazio | L76: @danielfazio | M76: 17724 | N76: 10-20k | O76: 2026-08-26 | P76: https://x.com/danielfazio/status/2092685995686666242 | Q76: There’s only 3 ways to get clients. | R76: There’s only 3 ways to get clients. 1. Organic/Audience 2. Ads 3. Outreach That’s it. Nothing else. If you don’t have an audience, and you can’t afford to spend $2,000 on ads to acquire a client, your only option is cold outreach | S76: How-To / Listicle | T76: None (pure value) | U76: MOFU: Framework / How-To | V76: text | W76: tutorial | X76: informative | Y76: 54659 | Z76: 532 | AA76: 62 | AB76: 46 | AC76: 0.011708959 | AD76: 4.46 | AE76: =IF(AD76="","",MIN(AD76,100)) -> 4.46 | AF76: 94.8 | AG76: No | AH76: 10 | AI76: No | AJ76: No | AK76: Intl: Authority-to-Pipeline DFY | AL76: =ROUND('Start Here'!$B$29*AH76+'Start Here'!$B$30*MIN(IF(AD76="",0,AD76),50)/5+IF(M76<=30000,'Start Here'!$B$31,IF(M76<=60000,'Start Here'!$B$32,0)),1) -> 7.3 | AM76: Scannable, save-worthy steps | AN76: Keep the how-to hook mechanic and swap in your own proof. Teach one marketing strategy lesson for founders of 10-50 person boutique firms (US/UK/AU). Ship it as a LinkedIn text/carousel. | AO76: A concise post stating the three primary methods to acquire clients: organic/audience growth, paid ads, and outreach. It emphasizes cold outreach as the viable option for those without an existing audience or ad budget. | AP76: client acquisition, organic growth, paid ads, cold outreach, business strategy, consulting, marketing channels, business advice | AQ76: "fractional" CMO CFO COO getting clients | AR76: Backlog
A77: 76 | B77: X | C77: English | D77: Eden | E77: Outlier | F77: No | G77: No | H77: No | I77: Business Growth & Scale Systems | J77: Consulting / Fractional, Agency Growth, High-Ticket Sales | K77: Connor Abene | L77: @connorabene | M77: 29814 | N77: 20-30k | O77: 2026-09-19 | P77: https://x.com/ConnorAbene/status/2101380828399882659 | Q77: If I had to start a fractional CFO firm from scratch tomorrow, here's the playbook I'd follow: | R77: If I had to start a fractional CFO firm from scratch tomorrow, here's the playbook I'd follow: 1. Pick a revenue band like $1M-5M businesses 2. Pick a specific industry 3. Define 3 recurring outcomes you deliver 4. Package it into one monthly retainer 5. Price it at $3k-$5k a month Get to 10 clients and you're at $360k to $600k in ARR. | S77: Story / Anecdote | T77: None (pure value) | U77: BOFU: Proof / Case Study | V77: text | W77: other | X77: educational | Y77: 5588 | Z77: 63 | AA77: 7 | AB77: 1 | AC77: 0.012705798 | AD77: 4.44 | AE77: =IF(AD77="","",MIN(AD77,100)) -> 4.44 | AF77: 98.8 | AG77: No | AH77: 10 | AI77: No | AJ77: No | AK77: Intl: Authority-to-Pipeline DFY | AL77: =ROUND('Start Here'!$B$29*AH77+'Start Here'!$B$30*MIN(IF(AD77="",0,AD77),50)/5+IF(M77<=30000,'Start Here'!$B$31,IF(M77<=60000,'Start Here'!$B$32,0)),1) -> 7.3 | AM77: 'If I had to start X from scratch' playbook with precise numbers (revenue band, $3-5k retainer, 10 clients). Fractional-exec audience. | AN77: 'If I were a fractional CMO starting today, here is my 90-day pipeline plan' (niche, offer, 20 warm conversations/week, 1 proof post/week). Shows depth in your secondary ICP. | AO77: Connor Abene shares a five-step playbook for launching a fractional CFO firm, from choosing a revenue band and industry to packaging recurring outcomes into a $3k–$5k monthly retainer to reach $360k–$600k ARR with 10 clients. | AP77: fractional cfo, consulting, playbook, retainer, pricing, niche, arr, revenue band | AQ77: "fractional" CMO CFO COO getting clients | AR77: Backlog
A78: 77 | B78: LinkedIn | C78: English | D78: Eden | E78: Hidden Gem | F78: Yes | G78: Yes | H78: No | I78: Agency Growth | J78: Business Growth & Scale Systems, Marketing Strategy | K78: Nick Avaria | L78: @nickavaria | M78: 18671 | N78: 10-20k | O78: 2026-03-03 | P78: https://www.linkedin.com/feed/update/urn:li:activity:7434606028261892096 | Q78: I've acquired & sold 7 agencies. | R78: I've acquired & sold 7 agencies. 1 dashboard runs all of them: Get my 2026 templated version free today. This is the same dashboard we install inside agencies to give founders visibility into: - Margin - Client retention - Utilization - Forecasting - Revenue per employee - CAC and payback - MRR movement - Team load vs. delivery capacity If you're an agency owner doing $100K+ per month and you | S78: Story / Anecdote | T78: None (pure value) | U78: TOFU: Reach / POV | V78: post | Z78: 144 | AA78: 445 | AB78: 0 | AC78: 0.032523468 | AD78: 29.4 | AE78: =IF(AD78="","",MIN(AD78,100)) -> 29.4 | AF78: 97.3 | AG78: No | AH78: 7 | AI78: No | AJ78: No | AK78: Intl: Authority-to-Pipeline DFY | AL78: =ROUND('Start Here'!$B$29*AH78+'Start Here'!$B$30*MIN(IF(AD78="",0,AD78),50)/5+IF(M78<=30000,'Start Here'!$B$31,IF(M78<=60000,'Start Here'!$B$32,0)),1) -> 7.3 | AM78: Small-account breakout: the idea beat the audience size; First-person or observed story: narrative pull; High comment-to-like ratio: debate driver | AN78: Keep the story hook mechanic and swap in your own proof. Teach one agency growth lesson for founders of 10-50 person boutique firms (US/UK/AU). Ship it as a LinkedIn text/carousel. | AQ78: client acquisition for agencies and consultants | AR78: Backlog
A79: 78 | B79: X | C79: English | D79: Eden | E79: Hidden Gem | F79: Yes | G79: Yes | H79: No | I79: High-Ticket Sales | J79: Business Growth & Scale Systems, Marketing Strategy | K79: Wifi Money Plant | L79: @wifimoneyplant | M79: 19758 | N79: 10-20k | O79: 2025-10-26 | P79: https://x.com/WifiMoneyPlant/status/1982521712475316314 | Q79: Just met with a founder | R79: Just met with a founder They make $30m/year Selling 1 info product $500 ticket price Zero sales calls 97% margins 1 employee WTF. | S79: Story / Anecdote | T79: None (pure value) | U79: BOFU: Proof / Case Study | V79: text | W79: story | X79: inspirational | Y79: 196004 | Z79: 1905 | AA79: 150 | AB79: 46 | AC79: 0.010719169 | AD79: 131.32 | AE79: =IF(AD79="","",MIN(AD79,100)) -> 100 | AF79: 99.7 | AG79: No | AH79: 4.5 | AI79: No | AJ79: Yes | AK79: Low fit (aspirant/beginner audience) | AL79: =ROUND('Start Here'!$B$29*AH79+'Start Here'!$B$30*MIN(IF(AD79="",0,AD79),50)/5+IF(M79<=30000,'Start Here'!$B$31,IF(M79<=60000,'Start Here'!$B$32,0)),1) -> 7.3 | AM79: Small-account breakout: the idea beat the audience size; First-person or observed story: narrative pull | AN79: Keep the story hook mechanic and swap in your own proof. Teach one high-ticket sales lesson for (re-aim at business owners, not aspirants). Ship it as a LinkedIn text/carousel. | AO79: A founder making $30M/year selling a single $500 info product with 97% margins, zero sales calls, and only one employee. | AP79: info product, high margins, zero sales calls, small team, scaling, founder story, income report, digital product | AQ79: high ticket sales calls closing B2B deals | AR79: Backlog
A80: 79 | B80: X | C80: English | D80: Eden | E80: Hidden Gem | F80: Yes | G80: Yes | H80: No | I80: Marketing Strategy | J80: Content Marketing & Systems, Business Growth & Scale Systems | K80: James Ebringer | L80: @jamesebringer | M80: 27689 | N80: 20-30k | O80: 2025-11-26 | P80: https://x.com/JamesEbringer/status/1993780615901003863 | Q80: There's a guy making €380k/yr cloning successful English offers, translating them, and selling them in Germany with zero competition | R80: There's a guy making €380k/yr cloning successful English offers, translating them, and selling them in Germany with zero competition He doesn't create products He doesn't build audiences He just finds what's already working in English and copies it to markets where it doesn't exist yet And it's printing Here's how it works: Step 1: Find proven English offers doing $50k+/month Trading course | S80: Result / Number-Led Claim | T80: None (pure value) | U80: BOFU: Proof / Case Study | V80: text | W80: other | X80: informative | Y80: 264060 | Z80: 1489 | AA80: 41 | AB80: 145 | AC80: 0.0063432553 | AD80: 227.8 | AE80: =IF(AD80="","",MIN(AD80,100)) -> 100 | AF80: 99.9 | AG80: No | AH80: 4.5 | AI80: No | AJ80: Yes | AK80: Low fit (aspirant/beginner audience) | AL80: =ROUND('Start Here'!$B$29*AH80+'Start Here'!$B$30*MIN(IF(AD80="",0,AD80),50)/5+IF(M80<=30000,'Start Here'!$B$31,IF(M80<=60000,'Start Here'!$B$32,0)),1) -> 7.3 | AM80: Specific number/result in the hook; Proof-first opening | AN80: Keep the result hook mechanic and swap in your own proof. Teach one marketing strategy lesson for (re-aim at business owners, not aspirants). Ship it as a LinkedIn text/carousel. | AO80: A user shares a case study of a businessman earning €380k/year by cloning successful English digital offers, translating them into German/French/Spanish, and selling in untapped non-English markets. The process involves reverse-engineering proven English offers, translating with native speakers, launching identical systems in new languages, and using faceless content to drive traffic. | AP80: translation arbitrage, market cloning, digital offers, german market, faceless content, eyeballs method, copying successful offers, non english markets | AQ80: how to get international clients as Indian freelancer or agency | AR80: Backlog
A81: 80 | B81: X | C81: English | D81: Eden | E81: Hidden Gem | F81: Yes | G81: Yes | H81: Yes | I81: Outbound / Warm Outbound | J81: Marketing Strategy, Content Marketing & Systems, Business Growth & Scale Systems | K81: spidey | L81: @lochan_twt | M81: 10989 | N81: 10-20k | O81: 2026-09-21 | P81: https://x.com/lochan_twt/status/2101990918002012357 | Q81: how to ACTUALLY get a j*b (no bs) | R81: most people who are really good engineers dont realize that being good =! getting hired. as some guy said, "a focused fool will accomplish more than a distracted genius". you can literally be good at what you do and still get ignored if your application looks exaclty like other 500 people applying for the same job. In big 26 being skilled is still the baseline but knowing how to make people notice | S81: How-To / Listicle | T81: Link / Register | U81: MOFU: Framework / How-To | V81: text | W81: other | X81: informative | Y81: 1669148 | Z81: 4241 | AA81: 35 | AB81: 378 | AC81: 0.0027882489 | AD81: 363.71 | AE81: =IF(AD81="","",MIN(AD81,100)) -> 100 | AF81: 98 | AG81: No | AH81: 4.5 | AI81: No | AJ81: Yes | AK81: Low fit (aspirant/beginner audience) | AL81: =ROUND('Start Here'!$B$29*AH81+'Start Here'!$B$30*MIN(IF(AD81="",0,AD81),50)/5+IF(M81<=30000,'Start Here'!$B$31,IF(M81<=60000,'Start Here'!$B$32,0)),1) -> 7.3 | AM81: Small-account breakout: the idea beat the audience size; Scannable, save-worthy steps | AN81: Keep the how-to hook mechanic and swap in your own proof. Teach one outbound / warm outbound lesson for (re-aim at business owners, not aspirants). Ship it as a LinkedIn text/carousel. | AO81: Long text thread giving job-search advice to engineers: it argues technical skill isn't enough, and outlines tactics like tracking target companies, cold emailing, targeted applications, referrals and publicly showcasing work. The attached image shows a figure pointing at an "Employment / Job Application" form. | AP81: job search, job applications, cold email, referrals, networking, career advice, tech careers, personal branding | AQ81: referrals plateau service business founder stuck at revenue ceiling; cold email outbound that books meetings for consultants | AR81: Backlog
A82: 81 | B82: X | C82: English | D82: Eden | E82: Hidden Gem | F82: Yes | G82: Yes | H82: No | I82: Business Growth & Scale Systems | J82: Marketing Strategy, Client Acquisition, Agency Growth | K82: ecomchigga | L82: @ecomchigga | M82: 12398 | N82: 10-20k | O82: 2025-11-16 | P82: https://x.com/ecomchigga/status/1990191674086039953 | Q82: I made >$600k profits this year at 18 | R82: I made >$600k profits this year at 18 selling digital products. Here’s how I scaled to $6K/day consistently: 1.Create a fresh Twitter/X account (takes 5 seconds). 2.Add a clean PFP + banner using Midjourney or Leonardo (2 minutes). 3.Write a 160-character bio that shows niche + authority (30 seconds). 4.Add a Notion or Typeform link to capture every lead (1 minute). 5. Pin a post offering a free | S82: Build / Demo Reveal | T82: None (pure value) | U82: TOFU: Reach / POV | V82: carousel | W82: other | X82: informative | Y82: 115102 | Z82: 1027 | AA82: 262 | AB82: 153 | AC82: 0.012528019 | AD82: 138.75 | AE82: =IF(AD82="","",MIN(AD82,100)) -> 100 | AF82: 97.7 | AG82: No | AH82: 4.5 | AI82: No | AJ82: Yes | AK82: Low fit (aspirant/beginner audience) | AL82: =ROUND('Start Here'!$B$29*AH82+'Start Here'!$B$30*MIN(IF(AD82="",0,AD82),50)/5+IF(M82<=30000,'Start Here'!$B$31,IF(M82<=60000,'Start Here'!$B$32,0)),1) -> 7.3 | AM82: Small-account breakout: the idea beat the audience size; Specific number/result in the hook; Shows the system or tool, not just claims; High comment-to-like ratio: debate driver | AN82: Keep the build hook mechanic and swap in your own proof. Teach one business growth & scale systems lesson for (re-aim at business owners, not aspirants). Ship it as a LinkedIn text/carousel. | AO82: A sleek gray Audi R8 sports car is parked on a paved street, reflecting the surrounding environment. The scene shows green trees, bushes, and a building partially visible behind the foliage with streetlights along the sidewalk. | AP82: audi r8, sports car, car exterior, glossy finish, paved street, green trees, sidewalk, streetlights | AQ82: sales system CRM follow-up process for service business owners | AR82: Backlog
A83: 82 | B83: X | C83: English | D83: Eden | E83: Outlier | F83: No | G83: No | H83: No | I83: Marketing Strategy | J83: Content Marketing & Systems, Client Acquisition, Business Growth & Scale Systems | K83: paolo trivellato | L83: @paolo_scales | M83: 17119 | N83: 10-20k | O83: 2026-01-17 | P83: https://x.com/paolo_scales/status/2012583400318574774 | Q83: LinkedIn is a $100k/mo goldmine and 99% of people are doing it wrong | R83: LinkedIn is a $100k/mo goldmine and 99% of people are doing it wrong Everyone's posting motivational quotes and asking for engagement Meanwhile there's a handful of guys quietly printing $100-300k/month selling to desperate execs AI SaaS, tax consultants, LLM SEO agencies - doesn't matter They're all using the same inbound funnel that converts 8-12% of commenters into booked calls He | S83: Contrarian / Myth-Bust | T83: None (pure value) | U83: TOFU: Reach / POV | V83: text | W83: tutorial | X83: informative | Y83: 11996 | Z83: 149 | AA83: 7 | AB83: 9 | AC83: 0.013754585 | AD83: 3.82 | AE83: =IF(AD83="","",MIN(AD83,100)) -> 3.82 | AF83: 89.3 | AG83: No | AH83: 10 | AI83: No | AJ83: No | AK83: Intl: Authority-to-Pipeline DFY | AL83: =ROUND('Start Here'!$B$29*AH83+'Start Here'!$B$30*MIN(IF(AD83="",0,AD83),50)/5+IF(M83<=30000,'Start Here'!$B$31,IF(M83<=60000,'Start Here'!$B$32,0)),1) -> 7.2 | AM83: Specific number/result in the hook; Challenges a belief the ICP holds | AN83: Keep the contrarian hook mechanic and swap in your own proof. Teach one marketing strategy lesson for founders of 10-50 person boutique firms (US/UK/AU). Ship it as a LinkedIn text/carousel. | AO83: A LinkedIn income blueprint claims to generate $60k+/mo using an inbound funnel: craft a profile as storefront, post 5-7x/week with structured posts (hook, insight, CTA), offer valuable lead magnets to commenters, and convert via pre-sold email sequence and Calendly calls. | AP83: linkedin funnel, lead magnet, content system, organic growth, saas sales, booked calls, profile optimization, inbound marketing | AQ83: client acquisition for agencies and consultants | AR83: Backlog
A84: 83 | B84: X | C84: English | D84: Eden | E84: Hidden Gem | F84: Yes | G84: Yes | H84: No | I84: Outbound / Warm Outbound | J84: Content Marketing & Systems, Freelancing & International Clients, Client Acquisition | K84: Jason Fox | L84: @jasoncfox | M84: 8592 | N84: 5-10k | O84: 2025-12-29 | P84: https://x.com/jasoncfox/status/2005610481969504723 | Q84: I got cold DM'd by this guy | R84: I got cold DM'd by this guy No B.S, actually researched me and my content I didn't respond, he followed up with out entitlement, even sent a video covering some quick tweaks I could make I replied wanting more info, didn't think much of it This guy is up at 2:45am in Australia filming me loom videos and writing scripts for FREE This is the type of work ethic and hustle that will get | S84: Story / Anecdote | T84: DM ask | U84: TOFU: Reach / POV | V84: image | W84: story | X84: inspirational | Y84: 14235 | Z84: 133 | AA84: 22 | AB84: 5 | AC84: 0.011239902 | AD84: 20.44 | AE84: =IF(AD84="","",MIN(AD84,100)) -> 20.44 | AF84: 97.9 | AG84: No | AH84: 8 | AI84: No | AJ84: No | AK84: Intl: Authority-to-Pipeline DFY | AL84: =ROUND('Start Here'!$B$29*AH84+'Start Here'!$B$30*MIN(IF(AD84="",0,AD84),50)/5+IF(M84<=30000,'Start Here'!$B$31,IF(M84<=60000,'Start Here'!$B$32,0)),1) -> 7.2 | AM84: Small-account breakout: the idea beat the audience size; First-person or observed story: narrative pull | AN84: Keep the story hook mechanic and swap in your own proof. Teach one outbound / warm outbound lesson for founders of 10-50 person boutique firms (US/UK/AU). Ship it as a LinkedIn text/carousel. | AO84: A verification screen from DocuSign showing a completed contract for 'Agency - SERVICES AGREEMENT' sent to Jason, visually representing an instance of being approached by a proactive freelancer who demonstrated effort and belief in their service through unsolicited free work. | AP84: cold dm, hustle, work ethic, client acquisition, freelance, service demonstration, entitlement, free work | AQ84: freelancer to agency first clients Upwork pricing in dollars Hinglish | AR84: Backlog
A85: 84 | B85: X | C85: English | D85: Eden | E85: Outlier | F85: No | G85: No | H85: No | I85: Marketing Strategy | J85: Content Marketing & Systems, Business Growth & Scale Systems, Client Acquisition | K85: Benjamin Chan | L85: @itsmebenchan | M85: 7366 | N85: 5-10k | O85: 2026-09-04 | P85: https://x.com/ItsMeBenChan/status/2095894359766118712 | Q85: The Ultimate Twitter Playbook (2026 Edition) | R85: When you’ve finished reading this article, you’ll know exactly how to build a Twitter funnel that’ll book you 20-30 calls/month and become “the guy” in your niche. Over the last 3 years I’ve: Worked with 250+ entrepreneurs, founders, executives, and professionals at their crafts to scale their brands on X. Written over 3,000+ posts across myself and clients and generated over 60,000,000+ impres | S85: Result / Number-Led Claim | T85: None (pure value) | U85: TOFU: Reach / POV | V85: image | W85: tutorial | X85: educational | Y85: 10563 | Z85: 92 | AA85: 6 | AB85: 3 | AC85: 0.0095616776 | AD85: 3.72 | AE85: =IF(AD85="","",MIN(AD85,100)) -> 3.72 | AF85: 83.8 | AG85: No | AH85: 10 | AI85: No | AJ85: No | AK85: Intl: Authority-to-Pipeline DFY | AL85: =ROUND('Start Here'!$B$29*AH85+'Start Here'!$B$30*MIN(IF(AD85="",0,AD85),50)/5+IF(M85<=30000,'Start Here'!$B$31,IF(M85<=60000,'Start Here'!$B$32,0)),1) -> 7.2 | AM85: Proof-first opening | AN85: Keep the result hook mechanic and swap in your own proof. Teach one marketing strategy lesson for founders of 10-50 person boutique firms (US/UK/AU). Ship it as a LinkedIn text/carousel. | AO85: A minimalist graphic illustrates a step-by-step Twitter funnel system for building authority and generating leads. The visual uses numbered platforms to represent the sequential process outlined in the accompanying article. | AP85: twitter funnel, personal branding, content strategy, profile optimization, brand positioning, content pillars, lead generation, social media marketing | AQ85: contrarian take on marketing and sales advice for small B2B companies | AR85: Backlog
A86: 85 | B86: LinkedIn | C86: English | D86: Eden | E86: Outlier | F86: No | G86: No | H86: No | I86: High-Ticket Sales | J86: Marketing Strategy, Content Marketing & Systems, Agency Growth | K86: Kush Shah | L86: @writewithkush | M86: 10064 | N86: 10-20k | O86: 2026-09-16 | P86: https://www.linkedin.com/feed/update/urn:li:activity:7505943146720165888 | Q86: "I don't mind paying you $2,000. I just don't want to." | R86: "I don't mind paying you $2,000. I just don't want to." A founder said this over a call 2 weeks ago. He also added: "I want to test your system for two weeks first, and if it brings in deals, I'll pay you plus a bonus." I told him no. Here is why: You do not walk into an Italian restaurant, order three pizzas, take two bites of each, and say: "If this hits my taste buds right, I will pay th | S86: Objection / Quote Hook | T86: None (pure value) | U86: TOFU: Reach / POV | V86: text | W86: other | X86: critical | Z86: 56 | AA86: 14 | AB86: 0 | AC86: 0.0072321521 | AD86: 3.62 | AE86: =IF(AD86="","",MIN(AD86,100)) -> 3.62 | AF86: 85.1 | AG86: No | AH86: 10 | AI86: No | AJ86: No | AK86: Intl: Authority-to-Pipeline DFY | AL86: =ROUND('Start Here'!$B$29*AH86+'Start Here'!$B$30*MIN(IF(AD86="",0,AD86),50)/5+IF(M86<=30000,'Start Here'!$B$31,IF(M86<=60000,'Start Here'!$B$32,0)),1) -> 7.2 | AM86: Objection quote as hook ('I don't mind paying you $2,000. I just don't want to.') + firm stance + analogy. Small account, strong comments. | AN86: Use real prospect objections from your calls as hooks: 'Can we do a 2-week trial first?' Explain why you say no, and what you offer instead (paid diagnostic). | AO86: Kush Shah recounts a founder refusing to pay $2,000 upfront, instead requesting a free two-week trial with performance-based pay. He declines and argues that content creators shouldn't take on the risk of clients' broken sales pipelines, telling readers to "pay the chef." | AP86: freelance, client management, pricing, content marketing, sales, free work, compensation, leverage | AQ86: "fractional" CMO CFO COO getting clients | AR86: Backlog
A87: 86 | B87: X | C87: English | D87: Eden | E87: Outlier | F87: No | G87: No | H87: No | I87: Outbound / Warm Outbound | J87: Consulting / Fractional, Business Growth & Scale Systems, Client Acquisition | K87: Connor Abene | L87: @connorabene | M87: 29814 | N87: 20-30k | O87: 2026-09-16 | P87: https://x.com/ConnorAbene/status/2100260277967081695 | Q87: I know a really good CFO who’s looking for his next thing. | R87: I know a really good CFO who’s looking for his next thing. Open to anything 20+ hours/week or full-time. Previously CFO of a ~$50M company and has done fractional CFO work since. Very reasonable on comp. Remote only, but happy to travel when needed. More importantly, just a genuinely good person. If you know someone looking, shoot me a DM. | S87: Story / Anecdote | T87: DM ask | U87: TOFU: Reach / POV | V87: text | W87: other | X87: neutral | Y87: 20647 | Z87: 50 | AA87: 1 | AB87: 5 | AC87: 0.0027122584 | AD87: 3.53 | AE87: =IF(AD87="","",MIN(AD87,100)) -> 3.53 | AF87: 97.8 | AG87: No | AH87: 10 | AI87: No | AJ87: No | AK87: Intl: Authority-to-Pipeline DFY | AL87: =ROUND('Start Here'!$B$29*AH87+'Start Here'!$B$30*MIN(IF(AD87="",0,AD87),50)/5+IF(M87<=30000,'Start Here'!$B$31,IF(M87<=60000,'Start Here'!$B$32,0)),1) -> 7.2 | AM87: First-person or observed story: narrative pull | AN87: Keep the story hook mechanic and swap in your own proof. Teach one outbound / warm outbound lesson for founders of 10-50 person boutique firms (US/UK/AU). Ship it as a LinkedIn text/carousel. | AO87: A LinkedIn-style text post from Connor Abene recommending a CFO contact who is seeking fractional or full-time work. He describes the candidate's background (~$50M company CFO, fractional work since), remote-only preference, and asks readers to DM him with leads. | AP87: cfo, job search, fractional cfo, remote work, referral, networking, hiring, executive | AQ87: "fractional" CMO CFO COO getting clients | AR87: Backlog
A88: 87 | B88: Instagram | C88: English | D88: vidIQ | E88: Hidden Gem | F88: Yes | G88: Yes | H88: No | I88: Marketing Strategy | J88: Client Acquisition, High-Ticket Sales, Outbound / Warm Outbound | K88: alex1beck | L88: @alex1beck | M88: 7300 | N88: 5-10k | O88: Apr-Oct 2026 | P88: https://www.instagram.com/reel/DbDrqpnDu9d/ | Q88: The text that wakes up a dead lead | R88: A "dead" lead usually isn't dead, most people just send the wrong text. ㅤ Here's the exact two-part ... | S88: Contrarian / Myth-Bust | T88: None (pure value) | U88: TOFU: Reach / POV | V88: Reel: Single-shot talking head interspersed with full-screen text-message mockups. | W88: Education | Y88: 46900 | AD88: 19.8 | AE88: =IF(AD88="","",MIN(AD88,100)) -> 19.8 | AG88: No | AH88: 8 | AI88: No | AJ88: No | AK88: Intl: Authority-to-Pipeline DFY | AL88: =ROUND('Start Here'!$B$29*AH88+'Start Here'!$B$30*MIN(IF(AD88="",0,AD88),50)/5+IF(M88<=30000,'Start Here'!$B$31,IF(M88<=60000,'Start Here'!$B$32,0)),1) -> 7.2 | AM88: Small-account breakout: the idea beat the audience size; Challenges a belief the ICP holds; Format: tutorial with screen-overlay examples | AN88: Keep the contrarian hook mechanic and swap in your own proof. Teach one marketing strategy lesson for founders of 10-50 person boutique firms (US/UK/AU). Ship it as a IG reel, then repurpose to LinkedIn. | AO88: A creator explains a specific follow-up text message strategy to re-engage prospects who previously ghosted or didn't close a sale. | AP88: Business | AQ88: Content systems | AR88: Backlog
A89: 88 | B89: X | C89: English | D89: Eden | E89: Hidden Gem | F89: Yes | G89: Yes | H89: No | I89: Business Growth & Scale Systems | J89: Outbound / Warm Outbound | K89: Dimitar Angelov | L89: @dimitarangg | M89: 6310 | N89: 5-10k | O89: 2026-02-13 | P89: https://x.com/dimitarangg/status/2022410074593939657 | Q89: how to book 60+ calls/mo by automating cold outreach with clawdbot (x + email + linkedin) | R89: most people are still manually sending 50+ dms a day and wondering why they're struggling to hit $5k/mo. i deployed an ai agent that runs twitter + linkedin + email 24/7 and books 60+ calls monthly while i sleep. here's the complete clawdbot automation system that’s printing for me and my clients. YOUR SALES TEAM IS YOUR BIGGEST BOTTLENECK here's what nobody in the b2b space wants to admit out | S89: How-To / Listicle | T89: None (pure value) | U89: MOFU: Framework / How-To | V89: text | W89: other | X89: neutral | Y89: 284208 | Z89: 812 | AA89: 38 | AB89: 65 | AC89: 0.0032194731 | AD89: 75.02 | AE89: =IF(AD89="","",MIN(AD89,100)) -> 75.02 | AF89: 99.5 | AG89: No | AH89: 4.3 | AI89: No | AJ89: No | AK89: Intl: Authority-to-Pipeline DFY | AL89: =ROUND('Start Here'!$B$29*AH89+'Start Here'!$B$30*MIN(IF(AD89="",0,AD89),50)/5+IF(M89<=30000,'Start Here'!$B$31,IF(M89<=60000,'Start Here'!$B$32,0)),1) -> 7.2 | AM89: Small-account breakout: the idea beat the audience size; Scannable, save-worthy steps | AN89: Keep the how-to hook mechanic and swap in your own proof. Teach one business growth & scale systems lesson for founders of 10-50 person boutique firms (US/UK/AU). Ship it as a LinkedIn text/carousel. | AO89: Link only post without additional context or visual elements. | AQ89: sales system CRM follow-up process for service business owners | AR89: Backlog
A90: 89 | B90: X | C90: English | D90: Eden | E90: Hidden Gem | F90: Yes | G90: Yes | H90: No | I90: Outbound / Warm Outbound | J90: Business Growth & Scale Systems | K90: Levi Munneke | L90: @levikmunneke | M90: 6563 | N90: 5-10k | O90: 2026-03-20 | P90: https://x.com/levikmunneke/status/2035123865463267798 | Q90: this turns claude code and google maps into a 7-figure outbound team | R90: too many people are sending 20-50 cold emails a day. then wondering why their calendar is empty. here's what the operators quietly winning in 2026 are actually doing. google maps has 265 million business listings. they don't receive nearly as many emails as the businesses on Apollo getting bombarded with outreach. not because nobody wants their business. because nobody built the machine to r | S90: Statement / Declarative | T90: None (pure value) | U90: TOFU: Reach / POV | V90: article | Y90: 303250 | Z90: 549 | AA90: 41 | AB90: 42 | AC90: 0.002084089 | AD90: 64.52 | AE90: =IF(AD90="","",MIN(AD90,100)) -> 64.52 | AF90: 99.6 | AG90: No | AH90: 4.3 | AI90: No | AJ90: No | AK90: Intl: Authority-to-Pipeline DFY | AL90: =ROUND('Start Here'!$B$29*AH90+'Start Here'!$B$30*MIN(IF(AD90="",0,AD90),50)/5+IF(M90<=30000,'Start Here'!$B$31,IF(M90<=60000,'Start Here'!$B$32,0)),1) -> 7.2 | AM90: Small-account breakout: the idea beat the audience size | AN90: Keep the statement hook mechanic and swap in your own proof. Teach one outbound / warm outbound lesson for founders of 10-50 person boutique firms (US/UK/AU). Ship it as a LinkedIn text/carousel. | AQ90: LinkedIn DM outreach scripts and warm prospecting signals | AR90: Backlog
A91: 90 | B91: X | C91: English | D91: Eden | E91: Outlier | F91: No | G91: No | H91: No | I91: Content Marketing & Systems | J91: Marketing Strategy, Outbound / Warm Outbound, Client Acquisition | K91: paolo trivellato | L91: @paolo_scales | M91: 17119 | N91: 10-20k | O91: 2026-09-08 | P91: https://x.com/paolo_scales/status/2097335350930588073 | Q91: Instantly’s $3.3M/Mo LinkedIn Playbook (Full Breakdown) | R91: Instantly is doing $3.3M a month. Their LinkedIn company page has ~66k followers. The members behind this company collectively have 500,000+ followers on this platform, about 8 times the size of the corporate account. Founders look at that and think the company's account was pulling the real weight. Orchestrating big launches. Bringing in all leads behind the scenes. But in reality, if it weren' | S91: Build / Demo Reveal | T91: None (pure value) | U91: TOFU: Reach / POV | V91: image | W91: other | X91: informative | Y91: 26073 | Z91: 97 | AA91: 18 | AB91: 7 | AC91: 0.00467917 | AD91: 2.26 | AE91: =IF(AD91="","",MIN(AD91,100)) -> 2.26 | AF91: 81.8 | AG91: No | AH91: 10 | AI91: No | AJ91: No | AK91: Intl: Authority-to-Pipeline DFY | AL91: =ROUND('Start Here'!$B$29*AH91+'Start Here'!$B$30*MIN(IF(AD91="",0,AD91),50)/5+IF(M91<=30000,'Start Here'!$B$31,IF(M91<=60000,'Start Here'!$B$32,0)),1) -> 7.1 | AM91: Specific number/result in the hook; Shows the system or tool, not just claims | AN91: Keep the build hook mechanic and swap in your own proof. Teach one content marketing & systems lesson for founders of 10-50 person boutique firms (US/UK/AU). Ship it as a LinkedIn text/carousel. | AO91: Text-heavy LinkedIn analysis of how Instantly's founder, executive and AE accounts collectively outgrow its corporate page, breaking down the company's four-part content engine. The image itself is a simple brand graphic: the "instantly" logo with a blue lightning bolt on a blue textured background. | AP91: personal branding, linkedin growth, b2b saas, founder-led marketing, content strategy, outbound, instantly, case study | AQ91: high ticket sales calls closing B2B deals | AR91: Backlog
A92: 91 | B92: X | C92: English | D92: Eden | E92: Hidden Gem | F92: Yes | G92: Yes | H92: No | I92: Outbound / Warm Outbound | J92: Business Growth & Scale Systems, Marketing Strategy, Client Acquisition | K92: Romàn | L92: @romanbuildsaas | M92: 22306 | N92: 20-30k | O92: 2026-01-31 | P92: https://x.com/romanbuildsaas/status/2017670516719432131 | Q92: I built 3 AI agents that run my LinkedIn end-to-end: | R92: I built 3 AI agents that run my LinkedIn end-to-end: • They write my posts • They reply to every comment • They find high-intent leads and handle outreach I’m sharing the entire system. Want it? Repost ♻️ so others see it Comment “Agents” and I’ll DM you. https://t.co/R56jtyGOlk | S92: Build / Demo Reveal | T92: Comment keyword → DM | U92: Lead Capture (MOFU) | V92: long_video | W92: tutorial | X92: informative | Y92: 78459 | Z92: 1007 | AA92: 937 | AB92: 343 | AC92: 0.029148982 | AD92: 26.76 | AE92: =IF(AD92="","",MIN(AD92,100)) -> 26.76 | AF92: 98.9 | AG92: No | AH92: 6.9 | AI92: Yes | AJ92: No | AK92: Intl: Authority-to-Pipeline DFY | AL92: =ROUND('Start Here'!$B$29*AH92+'Start Here'!$B$30*MIN(IF(AD92="",0,AD92),50)/5+IF(M92<=30000,'Start Here'!$B$31,IF(M92<=60000,'Start Here'!$B$32,0)),1) -> 7.1 | AM92: Shows the system or tool, not just claims; Keyword CTA converts reach into DMs | AN92: Keep the build hook mechanic and swap in your own proof. Teach one outbound / warm outbound lesson for founders of 10-50 person boutique firms (US/UK/AU). Ship it as a LinkedIn text/carousel. | AO92: A video shows a LinkedIn profile and messages thread, with a narrator explaining how AI agents can automate similar processes. The video demonstrates the capability to write posts, reply to comments, and manage outreach using AI systems. | AP92: ai automation, social media, linkedin, ai agents, workflow automation, linkedin outreach, ai posts, ai replies | AQ92: LinkedIn DM outreach scripts and warm prospecting signals | AR92: Backlog
A93: 92 | B93: LinkedIn | C93: English | D93: Eden | E93: Hidden Gem | F93: Yes | G93: Yes | H93: No | I93: Marketing Strategy | J93: Content Marketing & Systems, Client Acquisition | K93: Zach Schieffer | L93: @zach-schieffer | M93: 21476 | N93: 20-30k | O93: 2026-10-01 | P93: https://www.linkedin.com/feed/update/urn:li:activity:7511422825266688001 | Q93: How to get ahead of 99% of beauty brands: | R93: How to get ahead of 99% of beauty brands: After studying 449 Rhode emails across 33 months, here’s their playbook: 1. They start selling the product BEFORE you can buy it. February’s mask launch had 4 pre-launch emails: the reveal, benefits for each mask + the development story 2. Product development became content. The day before Caffeine Reset launched, they shared “50+ iterations and 1.5 ye | S93: How-To / Listicle | T93: None (pure value) | U93: MOFU: Framework / How-To | V93: image | W93: promo | X93: educational | Z93: 816 | AA93: 1087 | AB93: 23 | AC93: 0.089878202 | AD93: 34.07 | AE93: =IF(AD93="","",MIN(AD93,100)) -> 34.07 | AF93: 99.3 | AG93: No | AH93: 6 | AI93: No | AJ93: No | AK93: Intl: Authority-to-Pipeline DFY | AL93: =ROUND('Start Here'!$B$29*AH93+'Start Here'!$B$30*MIN(IF(AD93="",0,AD93),50)/5+IF(M93<=30000,'Start Here'!$B$31,IF(M93<=60000,'Start Here'!$B$32,0)),1) -> 7 | AM93: Scannable, save-worthy steps; High comment-to-like ratio: debate driver | AN93: Keep the how-to hook mechanic and swap in your own proof. Teach one marketing strategy lesson for founders of 10-50 person boutique firms (US/UK/AU). Ship it as a LinkedIn text/carousel. | AO93: Promotional graphic offering a "rhode Email Swipe File + Strategy Guide" built from 449 Rhode emails across 33 months, shown as a dense grid of email preview thumbnails. A bottom bar asks viewers to comment "RHODE" to receive the guide. | AP93: email marketing, newsletters, beauty brand, rhode, swipe file, email strategy, lead magnet, comment to get | AQ93: case study how we generated pipeline for a B2B client with content and outbound | AR93: Backlog
A94: 93 | B94: X | C94: English | D94: Eden | E94: Hidden Gem | F94: Yes | G94: Yes | H94: Yes | I94: Freelancing & International Clients | J94: Outbound / Warm Outbound | K94: Dan Greenheck | L94: @dangreenheck | M94: 12471 | N94: 10-20k | O94: 2026-09-21 | P94: https://x.com/dangreenheck/status/2102137910921240807 | Q94: I think it's time to hang up my Three.js hat. | R94: I think it's time to hang up my Three.js hat. First of all, this is not a pity post—I'll be fine. I'm also not 100% confident about this. But I'm an over-sharer and like to talk out loud, so I thought I would share some thoughts on where I see things going and why I'm considering quitting Three.js development. Some signals I've noticed lately that have gotten me thinking: - Since Astra was rele | S94: Story / Anecdote | T94: None (pure value) | U94: TOFU: Reach / POV | V94: text | W94: other | X94: emotional | Y94: 441630 | Z94: 2845 | AA94: 324 | AB94: 229 | AC94: 0.0076942237 | AD94: 53.25 | AE94: =IF(AD94="","",MIN(AD94,100)) -> 53.25 | AF94: 99.3 | AG94: No | AH94: 4 | AI94: No | AJ94: No | AK94: Intl: Authority-to-Pipeline DFY | AL94: =ROUND('Start Here'!$B$29*AH94+'Start Here'!$B$30*MIN(IF(AD94="",0,AD94),50)/5+IF(M94<=30000,'Start Here'!$B$31,IF(M94<=60000,'Start Here'!$B$32,0)),1) -> 7 | AM94: Small-account breakout: the idea beat the audience size; First-person or observed story: narrative pull | AN94: Keep the story hook mechanic and swap in your own proof. Teach one freelancing & international clients lesson for founders of 10-50 person boutique firms (US/UK/AU). Ship it as a LinkedIn text/carousel. | AO94: A freelance Three.js/WebGL developer shares thoughts on considering leaving Three.js development, citing AI-driven replication of his work, declining client referrals, and lost enjoyment of hard problems. He plans to finish Water Pro v4 before deciding what's next and invites other developers and freelancers to share their perspectives. | AP94: three.js, webgl, graphics programming, freelance developer, ai displacement, career reflection, burnout, vibe coding | AQ94: referrals plateau service business founder stuck at revenue ceiling | AR94: Backlog
